Workbook
Name ServiceLevel: Assumptions!$B$5
Name z: Assumptions!$B$6
Name OrderCost: Assumptions!$B$7
Name HoldRate: Assumptions!$B$8
Name WeeksYear: Assumptions!$B$9
Name CurrentCoverWks: Assumptions!$B$10
Name LastWeek: Assumptions!$B$11
Name ACut: Assumptions!$B$13
Name BCut: Assumptions!$B$14
Name XMaxCV: Assumptions!$B$15
Name YMaxCV: Assumptions!$B$16
Name wLate: Assumptions!$B$18
Name wLTV: Assumptions!$B$19
Name wQuality: Assumptions!$B$20
Name wCountry: Assumptions!$B$21
Name wSpend: Assumptions!$B$22
Name BadLate: Assumptions!$B$25
Name BadLTV: Assumptions!$B$26
Name BadQuality: Assumptions!$B$27
Name BadSpend: Assumptions!$B$28
Name Markup: Assumptions!$B$30
Name CountryList: Assumptions!$A$33:$A$40
Name CountryScore: Assumptions!$B$33:$B$40
Name DriverList: Assumptions!$A$43:$A$47
Name DriverAction: Assumptions!$C$43:$C$47
Name SegList: Assumptions!$A$50:$A$58
Name SegStrategy: Assumptions!$C$50:$C$58
Name D_Week: Weekly_Demand!$A$2:$A$5097
Name D_SKU: Weekly_Demand!$B$2:$B$5097
Name D_Units: Weekly_Demand!$C$2:$C$5097
Name D_Last52: Weekly_Demand!$D$2:$D$5097
Name D_Units2: Weekly_Demand!$E$2:$E$5097
Name PO_Sup: Purchase_Orders!$B$2:$B$1275
Name PO_SKU: Purchase_Orders!$C$2:$C$1275
Name PO_QtyOrd: Purchase_Orders!$G$2:$G$1275
Name PO_QtyRec: Purchase_Orders!$H$2:$H$1275
Name PO_QtyDef: Purchase_Orders!$I$2:$I$1275
Name PO_Value: Purchase_Orders!$J$2:$J$1275
Name PO_LT: Purchase_Orders!$K$2:$K$1275
Name PO_LT2: Purchase_Orders!$L$2:$L$1275
Name PO_OnTime: Purchase_Orders!$M$2:$M$1275
Name PO_DaysLate: Purchase_Orders!$N$2:$N$1275
Name SC_ID: Supplier_Scorecard!$A$5:$A$12
Name SC_LT: Supplier_Scorecard!$I$5:$I$12
Name SC_LTStd: Supplier_Scorecard!$J$5:$J$12
Name P_SKU: Inventory_Policy!$A$5:$A$53
Name P_Name: Inventory_Policy!$B$5:$B$53
Name P_Sup: Inventory_Policy!$D$5:$D$53
Name P_Cost: Inventory_Policy!$E$5:$E$53
Name P_Spend: Inventory_Policy!$I$5:$I$53
Name P_ABC: Inventory_Policy!$K$5:$K$53
Name P_XYZ: Inventory_Policy!$M$5:$M$53
Name P_Seg: Inventory_Policy!$N$5:$N$53
Name P_LT: Inventory_Policy!$O$5:$O$53
Name P_SS: Inventory_Policy!$Q$5:$Q$53
Name P_ROP: Inventory_Policy!$R$5:$R$53
Name P_EOQ: Inventory_Policy!$S$5:$S$53
Name P_OnHand: Inventory_Policy!$T$5:$T$53
Name P_OnOrder: Inventory_Policy!$U$5:$U$53
Name P_Pos: Inventory_Policy!$V$5:$V$53

Sheet README
A1: Supply Chain Inventory Optimization & Supplier Risk Analytics (Excel model)
A2: Every result is a live Excel formula. Built by Dhruvilkumar Upadhyay.
A4: How to use
A5: 1. Assumptions | B5: Change any blue-on-yellow cell (service level, ordering cost, risk weights...). The whole model recalculates.
A6: 2. Dashboard | B6: KPIs, inventory status, supplier risk chart, ABC-XYZ matrix and the 'what to order today' list.
A7: 3. Inventory_Policy | B7: One row per SKU: ABC-XYZ class, safety stock, reorder point, EOQ, status and suggested order quantity.
A8: 4. Supplier_Scorecard | B8: On-time delivery, lead time, defects, spend share and a weighted 0-100 risk score with a recommended action.
A9: 5. Forecast | B9: Pick a SKU from the dropdown in B4 to back-test 3 forecasting methods and see a 12-week forecast.
A10: 6. Disruption_Simulator | B10: Pick a supplier (B4) and an extra delay (B5) to see which SKUs stock out and the revenue at risk.
A11: 7. Landed_Cost | B11: Offshore vs nearshore: total landed cost (price, freight, duty, brokerage, plus the cost of safety stock and in-transit inventory) for every SKU bought overseas.
A12: Data sheets | B12: Products, Suppliers, Weekly_Demand, Purchase_Orders, Inventory. Replace them with your own data (same columns).
A13: Colour code | B13: Blue text = input you can change. Green text = link to another sheet. Black = formula.
A14: Key formulas
A15: Safety stock | B15: z x SQRT( lead time x demand std² + avg demand² x lead time std² )
A16: Reorder point | B16: avg weekly demand x lead time + safety stock
A17: EOQ | B17: SQRT( 2 x annual demand x ordering cost / (unit cost x holding rate) )
A18: WAPE | B18: SUM(|actual - forecast|) / SUM(actual)
A19: Data source | B19: NorthBridge is a fictional company. The data is simulated because real supply chain data is confidential. The analysis is built to run the same way on a real ERP export.
A20: Python version | B20: The same analysis is automated in Python (src/main.py). That version uses forecast error for safety stock, so numbers differ slightly.

Sheet Dashboard
A1: Supply Chain Control Tower
A2: Inventory optimization, demand forecasting and supplier risk. All figures are live formulas; change inputs on the Assumptions sheet.
B4: Annual spend analysed | E4: Spend in A-class SKUs | H4: SKUs to order now | K4: EOQ saving per year
B5: =SUM(P_Spend) | E5: =SUMIF(P_ABC,"A",P_Spend)/SUM(P_Spend) | H5: =COUNTIF(P_Status,"Order now")+COUNTIF(P_Status,"Critical - expedite") | K5: =SUM(P_Saving)
B6: =COUNTA(P_SKU)&" SKUs, "&COUNTA(SC_ID)&" suppliers" | E6: ="from "&COUNTIF(P_ABC,"A")&" SKUs ("&TEXT(COUNTIF(P_ABC,"A")/COUNTA(P_SKU),"0%")&")" | H6: =COUNTIF(P_Status,"Critical - expedite")&" critical (below safety stock)" | K6: =TEXT(SUM(P_Saving)/SUM(P_CurCost),"0.0%")&" lower ordering + holding cost"
B8: Excess inventory | E8: Safety stock investment | H8: Supplier on-time delivery | K8: High-risk suppliers
B9: =SUM(P_Excess) | E9: =SUM(P_SSValue) | H9: =AVERAGE(PO_OnTime) | K9: =COUNTIF(Supplier_Scorecard!$Z$5:$Z$12,"High")
B10: =COUNTIF(P_Status,"Overstock")&" SKUs above max stock" | E10: ="at "&TEXT(ServiceLevel,"0%")&" service level" | H10: =COUNTA(PO_OnTime)&" purchase orders" | K10: ="Top: "&INDEX(Supplier_Scorecard!$B$5:$B$12,MATCH(1,Supplier_Scorecard!$AC$5:$AC$12,0))
B12: Inventory status | M12: ABC-XYZ matrix (SKU count)
B13: Critical - expedite | C13: =COUNTIF(P_Status,B13) | N13: X stable | O13: Y variable | P13: Z erratic
B14: Order now | C14: =COUNTIF(P_Status,B14) | M14: A | N14: =COUNTIFS(P_ABC,"A",P_XYZ,"X") | O14: =COUNTIFS(P_ABC,"A",P_XYZ,"Y") | P14: =COUNTIFS(P_ABC,"A",P_XYZ,"Z")
B15: Healthy | C15: =COUNTIF(P_Status,B15) | M15: B | N15: =COUNTIFS(P_ABC,"B",P_XYZ,"X") | O15: =COUNTIFS(P_ABC,"B",P_XYZ,"Y") | P15: =COUNTIFS(P_ABC,"B",P_XYZ,"Z")
B16: Overstock | C16: =COUNTIF(P_Status,B16) | M16: C | N16: =COUNTIFS(P_ABC,"C",P_XYZ,"X") | O16: =COUNTIFS(P_ABC,"C",P_XYZ,"Y") | P16: =COUNTIFS(P_ABC,"C",P_XYZ,"Z")
B33: What to order today
B34: Product | C34: SKU | E34: Status | F34: Position | H34: Reorder point | I34: Order qty | K34: Supplier
B35: =IF($R35="","",INDEX(P_Name,$R35)) | C35: =IF($R35="","",INDEX(P_SKU,$R35)) | E35: =IF($R35="","",INDEX(P_Status,$R35)) | F35: =IF($R35="","",INDEX(P_Pos,$R35)) | H35: =IF($R35="","",INDEX(P_ROP,$R35)) | I35: =IF($R35="","",INDEX(P_Order,$R35)) | K35: =IF($R35="","",INDEX(P_Sup,$R35)) | R35: =IFERROR(MATCH(1,P_ActRow,0),"")
B36: =IF($R36="","",INDEX(P_Name,$R36)) | C36: =IF($R36="","",INDEX(P_SKU,$R36)) | E36: =IF($R36="","",INDEX(P_Status,$R36)) | F36: =IF($R36="","",INDEX(P_Pos,$R36)) | H36: =IF($R36="","",INDEX(P_ROP,$R36)) | I36: =IF($R36="","",INDEX(P_Order,$R36)) | K36: =IF($R36="","",INDEX(P_Sup,$R36)) | R36: =IFERROR(MATCH(2,P_ActRow,0),"")
B37: =IF($R37="","",INDEX(P_Name,$R37)) | C37: =IF($R37="","",INDEX(P_SKU,$R37)) | E37: =IF($R37="","",INDEX(P_Status,$R37)) | F37: =IF($R37="","",INDEX(P_Pos,$R37)) | H37: =IF($R37="","",INDEX(P_ROP,$R37)) | I37: =IF($R37="","",INDEX(P_Order,$R37)) | K37: =IF($R37="","",INDEX(P_Sup,$R37)) | R37: =IFERROR(MATCH(3,P_ActRow,0),"")
B38: =IF($R38="","",INDEX(P_Name,$R38)) | C38: =IF($R38="","",INDEX(P_SKU,$R38)) | E38: =IF($R38="","",INDEX(P_Status,$R38)) | F38: =IF($R38="","",INDEX(P_Pos,$R38)) | H38: =IF($R38="","",INDEX(P_ROP,$R38)) | I38: =IF($R38="","",INDEX(P_Order,$R38)) | K38: =IF($R38="","",INDEX(P_Sup,$R38)) | R38: =IFERROR(MATCH(4,P_ActRow,0),"")
B39: =IF($R39="","",INDEX(P_Name,$R39)) | C39: =IF($R39="","",INDEX(P_SKU,$R39)) | E39: =IF($R39="","",INDEX(P_Status,$R39)) | F39: =IF($R39="","",INDEX(P_Pos,$R39)) | H39: =IF($R39="","",INDEX(P_ROP,$R39)) | I39: =IF($R39="","",INDEX(P_Order,$R39)) | K39: =IF($R39="","",INDEX(P_Sup,$R39)) | R39: =IFERROR(MATCH(5,P_ActRow,0),"")
B40: =IF($R40="","",INDEX(P_Name,$R40)) | C40: =IF($R40="","",INDEX(P_SKU,$R40)) | E40: =IF($R40="","",INDEX(P_Status,$R40)) | F40: =IF($R40="","",INDEX(P_Pos,$R40)) | H40: =IF($R40="","",INDEX(P_ROP,$R40)) | I40: =IF($R40="","",INDEX(P_Order,$R40)) | K40: =IF($R40="","",INDEX(P_Sup,$R40)) | R40: =IFERROR(MATCH(6,P_ActRow,0),"")
B41: =IF($R41="","",INDEX(P_Name,$R41)) | C41: =IF($R41="","",INDEX(P_SKU,$R41)) | E41: =IF($R41="","",INDEX(P_Status,$R41)) | F41: =IF($R41="","",INDEX(P_Pos,$R41)) | H41: =IF($R41="","",INDEX(P_ROP,$R41)) | I41: =IF($R41="","",INDEX(P_Order,$R41)) | K41: =IF($R41="","",INDEX(P_Sup,$R41)) | R41: =IFERROR(MATCH(7,P_ActRow,0),"")
B42: =IF($R42="","",INDEX(P_Name,$R42)) | C42: =IF($R42="","",INDEX(P_SKU,$R42)) | E42: =IF($R42="","",INDEX(P_Status,$R42)) | F42: =IF($R42="","",INDEX(P_Pos,$R42)) | H42: =IF($R42="","",INDEX(P_ROP,$R42)) | I42: =IF($R42="","",INDEX(P_Order,$R42)) | K42: =IF($R42="","",INDEX(P_Sup,$R42)) | R42: =IFERROR(MATCH(8,P_ActRow,0),"")
B43: =IF($R43="","",INDEX(P_Name,$R43)) | C43: =IF($R43="","",INDEX(P_SKU,$R43)) | E43: =IF($R43="","",INDEX(P_Status,$R43)) | F43: =IF($R43="","",INDEX(P_Pos,$R43)) | H43: =IF($R43="","",INDEX(P_ROP,$R43)) | I43: =IF($R43="","",INDEX(P_Order,$R43)) | K43: =IF($R43="","",INDEX(P_Sup,$R43)) | R43: =IFERROR(MATCH(9,P_ActRow,0),"")
B44: =IF($R44="","",INDEX(P_Name,$R44)) | C44: =IF($R44="","",INDEX(P_SKU,$R44)) | E44: =IF($R44="","",INDEX(P_Status,$R44)) | F44: =IF($R44="","",INDEX(P_Pos,$R44)) | H44: =IF($R44="","",INDEX(P_ROP,$R44)) | I44: =IF($R44="","",INDEX(P_Order,$R44)) | K44: =IF($R44="","",INDEX(P_Sup,$R44)) | R44: =IFERROR(MATCH(10,P_ActRow,0),"")
B45: =IF($R45="","",INDEX(P_Name,$R45)) | C45: =IF($R45="","",INDEX(P_SKU,$R45)) | E45: =IF($R45="","",INDEX(P_Status,$R45)) | F45: =IF($R45="","",INDEX(P_Pos,$R45)) | H45: =IF($R45="","",INDEX(P_ROP,$R45)) | I45: =IF($R45="","",INDEX(P_Order,$R45)) | K45: =IF($R45="","",INDEX(P_Sup,$R45)) | R45: =IFERROR(MATCH(11,P_ActRow,0),"")
B46: =IF($R46="","",INDEX(P_Name,$R46)) | C46: =IF($R46="","",INDEX(P_SKU,$R46)) | E46: =IF($R46="","",INDEX(P_Status,$R46)) | F46: =IF($R46="","",INDEX(P_Pos,$R46)) | H46: =IF($R46="","",INDEX(P_ROP,$R46)) | I46: =IF($R46="","",INDEX(P_Order,$R46)) | K46: =IF($R46="","",INDEX(P_Sup,$R46)) | R46: =IFERROR(MATCH(12,P_ActRow,0),"")
B47: =IF($R47="","",INDEX(P_Name,$R47)) | C47: =IF($R47="","",INDEX(P_SKU,$R47)) | E47: =IF($R47="","",INDEX(P_Status,$R47)) | F47: =IF($R47="","",INDEX(P_Pos,$R47)) | H47: =IF($R47="","",INDEX(P_ROP,$R47)) | I47: =IF($R47="","",INDEX(P_Order,$R47)) | K47: =IF($R47="","",INDEX(P_Sup,$R47)) | R47: =IFERROR(MATCH(13,P_ActRow,0),"")
B48: =IF($R48="","",INDEX(P_Name,$R48)) | C48: =IF($R48="","",INDEX(P_SKU,$R48)) | E48: =IF($R48="","",INDEX(P_Status,$R48)) | F48: =IF($R48="","",INDEX(P_Pos,$R48)) | H48: =IF($R48="","",INDEX(P_ROP,$R48)) | I48: =IF($R48="","",INDEX(P_Order,$R48)) | K48: =IF($R48="","",INDEX(P_Sup,$R48)) | R48: =IFERROR(MATCH(14,P_ActRow,0),"")
B49: =IF($R49="","",INDEX(P_Name,$R49)) | C49: =IF($R49="","",INDEX(P_SKU,$R49)) | E49: =IF($R49="","",INDEX(P_Status,$R49)) | F49: =IF($R49="","",INDEX(P_Pos,$R49)) | H49: =IF($R49="","",INDEX(P_ROP,$R49)) | I49: =IF($R49="","",INDEX(P_Order,$R49)) | K49: =IF($R49="","",INDEX(P_Sup,$R49)) | R49: =IFERROR(MATCH(15,P_ActRow,0),"")
B50: =IF($R50="","",INDEX(P_Name,$R50)) | C50: =IF($R50="","",INDEX(P_SKU,$R50)) | E50: =IF($R50="","",INDEX(P_Status,$R50)) | F50: =IF($R50="","",INDEX(P_Pos,$R50)) | H50: =IF($R50="","",INDEX(P_ROP,$R50)) | I50: =IF($R50="","",INDEX(P_Order,$R50)) | K50: =IF($R50="","",INDEX(P_Sup,$R50)) | R50: =IFERROR(MATCH(16,P_ActRow,0),"")
B51: =IF($R51="","",INDEX(P_Name,$R51)) | C51: =IF($R51="","",INDEX(P_SKU,$R51)) | E51: =IF($R51="","",INDEX(P_Status,$R51)) | F51: =IF($R51="","",INDEX(P_Pos,$R51)) | H51: =IF($R51="","",INDEX(P_ROP,$R51)) | I51: =IF($R51="","",INDEX(P_Order,$R51)) | K51: =IF($R51="","",INDEX(P_Sup,$R51)) | R51: =IFERROR(MATCH(17,P_ActRow,0),"")
B52: =IF($R52="","",INDEX(P_Name,$R52)) | C52: =IF($R52="","",INDEX(P_SKU,$R52)) | E52: =IF($R52="","",INDEX(P_Status,$R52)) | F52: =IF($R52="","",INDEX(P_Pos,$R52)) | H52: =IF($R52="","",INDEX(P_ROP,$R52)) | I52: =IF($R52="","",INDEX(P_Order,$R52)) | K52: =IF($R52="","",INDEX(P_Sup,$R52)) | R52: =IFERROR(MATCH(18,P_ActRow,0),"")
B53: =IF($R53="","",INDEX(P_Name,$R53)) | C53: =IF($R53="","",INDEX(P_SKU,$R53)) | E53: =IF($R53="","",INDEX(P_Status,$R53)) | F53: =IF($R53="","",INDEX(P_Pos,$R53)) | H53: =IF($R53="","",INDEX(P_ROP,$R53)) | I53: =IF($R53="","",INDEX(P_Order,$R53)) | K53: =IF($R53="","",INDEX(P_Sup,$R53)) | R53: =IFERROR(MATCH(19,P_ActRow,0),"")
B54: =IF($R54="","",INDEX(P_Name,$R54)) | C54: =IF($R54="","",INDEX(P_SKU,$R54)) | E54: =IF($R54="","",INDEX(P_Status,$R54)) | F54: =IF($R54="","",INDEX(P_Pos,$R54)) | H54: =IF($R54="","",INDEX(P_ROP,$R54)) | I54: =IF($R54="","",INDEX(P_Order,$R54)) | K54: =IF($R54="","",INDEX(P_Sup,$R54)) | R54: =IFERROR(MATCH(20,P_ActRow,0),"")
B55: =IF(COUNT(P_ActRow)>20,"+ "&(COUNT(P_ActRow)-20)&" more on the Inventory_Policy sheet","")

Sheet Assumptions
A1: Assumptions
A2: Blue text on yellow = inputs you can change. Everything else in the workbook recalculates.
A4: Inventory policy
A5: Service level | B5: 0.95 | C5: Target share of order cycles with no stockout
A6: z-score | B6: =NORMSINV(ServiceLevel) | C6: Calculated from the service level (95% -> 1.645)
A7: Ordering cost per PO (CAD) | B7: 85 | C7: Admin, freight booking, receiving. Assumption
A8: Annual holding cost rate | B8: 0.22 | C8: Capital, storage, insurance, obsolescence. Assumption
A9: Weeks per year | B9: 52
A10: Current ordering habit (weeks of demand per PO) | B10: 4 | C10: Used to compare today's ordering with EOQ
A11: Last week in data | B11: =MAX(Weekly_Demand!$A$2:$A$5097) | C11: Analysis uses the 52 weeks up to this date
A12: Classification
A13: ABC: A-class cut-off (cumulative spend) | B13: 0.8 | C13: First 80% of spend = A
A14: ABC: B-class cut-off | B14: 0.95 | C14: Next 15% = B, rest = C
A15: XYZ: X max coefficient of variation | B15: 0.25 | C15: Stable demand
A16: XYZ: Y max coefficient of variation | B16: 0.5 | C16: Variable demand; above = Z (erratic)
A17: Supplier risk weights (must total 100%)
A18: Weight: late delivery | B18: 0.3
A19: Weight: lead-time variability | B19: 0.2
A20: Weight: quality (defects) | B20: 0.2
A21: Weight: country / route risk | B21: 0.15
A22: Weight: spend dependency | B22: 0.15
A23: Check: weights total | B23: =wLate+wLTV+wQuality+wCountry+wSpend | C23: Should be 100%
A24: 'Clearly bad' thresholds (factor score = 1)
A25: Late-delivery rate | B25: 0.35 | C25: 35% of POs late
A26: Lead-time coefficient of variation | B26: 0.3
A27: Defect rate | B27: 0.025 | C27: 2.5% of units defective
A28: Share of total spend with one supplier | B28: 0.3
A29: Disruption simulator
A30: Selling price markup on cost | B30: 1.35 | C30: Used to turn units short into revenue at risk. Assumption
A32: Country / route risk (1 = low, 5 = high)
A33: Canada | B33: 1 | C33: Illustrative assumptions (distance, port congestion, tariffs, geopolitics), not official ratings
A34: USA | B34: 2
A35: Germany | B35: 2
A36: Mexico | B36: 3
A37: Malaysia | B37: 3
A38: India | B38: 4
A39: Vietnam | B39: 4
A40: China | B40: 5
A42: Recommended action by main risk driver
A43: late delivery | C43: Quarterly business review with OTD target; add late-delivery clause to contract
A44: lead time variability | C44: Raise safety stock on its SKUs; book freight earlier; track via ASN
A45: quality | C45: Supplier corrective action request (SCAR); increase incoming inspection
A46: country risk | C46: Qualify a nearshore/domestic second source for critical SKUs
A47: spend dependency | C47: Dual-source top SKUs to reduce concentration risk
A49: Stocking strategy by ABC-XYZ segment
A50: AX | C50: Tight control, frequent review, low safety stock, consider VMI/automation
A51: AY | C51: Weekly review, forecast-driven replenishment, moderate safety stock
A52: AZ | C52: Highest attention: collaborate with customers, dual-source, buffer stock
A53: BX | C53: Automated reorder point, periodic review
A54: BY | C54: Standard reorder point policy, monthly review
A55: BZ | C55: Higher safety stock or make-to-order where possible
A56: CX | C56: Automate fully, order in larger batches
A57: CY | C57: Automate, larger batches, low review effort
A58: CZ | C58: Review if SKU is needed; consider dropping or ordering on demand

Sheet Inventory_Policy
A1: Inventory Policy: ABC-XYZ, Safety Stock, Reorder Point, EOQ
A2: One row per SKU. Demand statistics use the last 52 weeks. Status compares inventory position (on hand + on order) with safety stock and reorder point.
A4: SKU | B4: Product | C4: Category | D4: Supplier ID | E4: Unit cost (CAD) | F4: Annual units (52w) | G4: Avg weekly demand | H4: Weekly demand std | I4: Annual spend (CAD) | J4: Cum. spend share before SKU | K4: ABC | L4: Demand CV | M4: XYZ | N4: Segment | O4: Lead time (wks) | P4: Lead time std (wks) | Q4: Safety stock | R4: Reorder point | S4: EOQ | T4: On hand | U4: On order | V4: Inventory position | W4: Weeks of cover | X4: Status | Y4: Suggested order qty | Z4: Excess value (CAD) | AA4: Safety stock value (CAD) | AB4: Current ordering cost/yr | AC4: EOQ ordering cost/yr | AD4: Annual saving (CAD) | AE4: Strategy | AF4: helper: simulator row | AG4: helper: action row
A5: =Products!A2 | B5: =Products!B2 | C5: =Products!C2 | D5: =Products!E2 | E5: =Products!D2 | F5: =SUMIFS(D_Units,D_SKU,A5,D_Last52,1) | G5: =IFERROR(AVERAGEIFS(D_Units,D_SKU,A5,D_Last52,1),0) | H5: =IFERROR(SQRT(MAX(0,(SUMIFS(D_Units2,D_SKU,A5)-COUNTIFS(D_SKU,A5,D_Last52,1)*G5^2)/(COUNTIFS(D_SKU,A5,D_Last52,1)-1))),0) | I5: =F5*E5 | J5: =IFERROR(SUMIF($I$5:$I$53,">"&I5)/SUM($I$5:$I$53),0) | K5: =IF(J5<ACut,"A",IF(J5<BCut,"B","C")) | L5: =IFERROR(H5/G5,0) | M5: =IF(L5<=XMaxCV,"X",IF(L5<=YMaxCV,"Y","Z")) | N5: =K5&M5 | O5: =IFERROR(INDEX(SC_LT,MATCH(D5,SC_ID,0)),0) | P5: =IFERROR(INDEX(SC_LTStd,MATCH(D5,SC_ID,0)),0) | Q5: =ROUNDUP(z*SQRT(O5*H5^2+G5^2*P5^2),0) | R5: =ROUNDUP(G5*O5+Q5,0) | S5: =IFERROR(ROUNDUP(SQRT(2*G5*WeeksYear*OrderCost/(E5*HoldRate)),0),0) | T5: =IFERROR(INDEX(Inventory!$B:$B,MATCH(A5,Inventory!$A:$A,0)),0) | U5: =IFERROR(INDEX(Inventory!$C:$C,MATCH(A5,Inventory!$A:$A,0)),0) | V5: =T5+U5 | W5: =IFERROR(T5/G5,0) | X5: =IF(V5<Q5,"Critical - expedite",IF(V5<=R5,"Order now",IF(V5>R5+S5,"Overstock","Healthy"))) | Y5: =IF(OR(X5="Critical - expedite",X5="Order now"),MAX(S5,R5+S5-V5),0) | Z5: =IF(X5="Overstock",(V5-R5-S5)*E5,0) | AA5: =Q5*E5 | AB5: =IFERROR(G5*WeeksYear/(G5*CurrentCoverWks)*OrderCost+G5*CurrentCoverWks/2*E5*HoldRate,0) | AC5: =IFERROR(G5*WeeksYear/S5*OrderCost+S5/2*E5*HoldRate,0) | AD5: =AB5-AC5 | AE5: =IFERROR(INDEX(SegStrategy,MATCH(N5,SegList,0)),"") | AF5: =IF(D5=SimSupplier,COUNTIF($D$5:D5,SimSupplier),"") | AG5: =IF(OR(X5="Critical - expedite",X5="Order now"),COUNTIF($X$5:X5,"Critical - expedite")+COUNTIF($X$5:X5,"Order now"),"")
A6: =Products!A3 | B6: =Products!B3 | C6: =Products!C3 | D6: =Products!E3 | E6: =Products!D3 | F6: =SUMIFS(D_Units,D_SKU,A6,D_Last52,1) | G6: =IFERROR(AVERAGEIFS(D_Units,D_SKU,A6,D_Last52,1),0) | H6: =IFERROR(SQRT(MAX(0,(SUMIFS(D_Units2,D_SKU,A6)-COUNTIFS(D_SKU,A6,D_Last52,1)*G6^2)/(COUNTIFS(D_SKU,A6,D_Last52,1)-1))),0) | I6: =F6*E6 | J6: =IFERROR(SUMIF($I$5:$I$53,">"&I6)/SUM($I$5:$I$53),0) | K6: =IF(J6<ACut,"A",IF(J6<BCut,"B","C")) | L6: =IFERROR(H6/G6,0) | M6: =IF(L6<=XMaxCV,"X",IF(L6<=YMaxCV,"Y","Z")) | N6: =K6&M6 | O6: =IFERROR(INDEX(SC_LT,MATCH(D6,SC_ID,0)),0) | P6: =IFERROR(INDEX(SC_LTStd,MATCH(D6,SC_ID,0)),0) | Q6: =ROUNDUP(z*SQRT(O6*H6^2+G6^2*P6^2),0) | R6: =ROUNDUP(G6*O6+Q6,0) | S6: =IFERROR(ROUNDUP(SQRT(2*G6*WeeksYear*OrderCost/(E6*HoldRate)),0),0) | T6: =IFERROR(INDEX(Inventory!$B:$B,MATCH(A6,Inventory!$A:$A,0)),0) | U6: =IFERROR(INDEX(Inventory!$C:$C,MATCH(A6,Inventory!$A:$A,0)),0) | V6: =T6+U6 | W6: =IFERROR(T6/G6,0) | X6: =IF(V6<Q6,"Critical - expedite",IF(V6<=R6,"Order now",IF(V6>R6+S6,"Overstock","Healthy"))) | Y6: =IF(OR(X6="Critical - expedite",X6="Order now"),MAX(S6,R6+S6-V6),0) | Z6: =IF(X6="Overstock",(V6-R6-S6)*E6,0) | AA6: =Q6*E6 | AB6: =IFERROR(G6*WeeksYear/(G6*CurrentCoverWks)*OrderCost+G6*CurrentCoverWks/2*E6*HoldRate,0) | AC6: =IFERROR(G6*WeeksYear/S6*OrderCost+S6/2*E6*HoldRate,0) | AD6: =AB6-AC6 | AE6: =IFERROR(INDEX(SegStrategy,MATCH(N6,SegList,0)),"") | AF6: =IF(D6=SimSupplier,COUNTIF($D$5:D6,SimSupplier),"") | AG6: =IF(OR(X6="Critical - expedite",X6="Order now"),COUNTIF($X$5:X6,"Critical - expedite")+COUNTIF($X$5:X6,"Order now"),"")
A7: =Products!A4 | B7: =Products!B4 | C7: =Products!C4 | D7: =Products!E4 | E7: =Products!D4 | F7: =SUMIFS(D_Units,D_SKU,A7,D_Last52,1) | G7: =IFERROR(AVERAGEIFS(D_Units,D_SKU,A7,D_Last52,1),0) | H7: =IFERROR(SQRT(MAX(0,(SUMIFS(D_Units2,D_SKU,A7)-COUNTIFS(D_SKU,A7,D_Last52,1)*G7^2)/(COUNTIFS(D_SKU,A7,D_Last52,1)-1))),0) | I7: =F7*E7 | J7: =IFERROR(SUMIF($I$5:$I$53,">"&I7)/SUM($I$5:$I$53),0) | K7: =IF(J7<ACut,"A",IF(J7<BCut,"B","C")) | L7: =IFERROR(H7/G7,0) | M7: =IF(L7<=XMaxCV,"X",IF(L7<=YMaxCV,"Y","Z")) | N7: =K7&M7 | O7: =IFERROR(INDEX(SC_LT,MATCH(D7,SC_ID,0)),0) | P7: =IFERROR(INDEX(SC_LTStd,MATCH(D7,SC_ID,0)),0) | Q7: =ROUNDUP(z*SQRT(O7*H7^2+G7^2*P7^2),0) | R7: =ROUNDUP(G7*O7+Q7,0) | S7: =IFERROR(ROUNDUP(SQRT(2*G7*WeeksYear*OrderCost/(E7*HoldRate)),0),0) | T7: =IFERROR(INDEX(Inventory!$B:$B,MATCH(A7,Inventory!$A:$A,0)),0) | U7: =IFERROR(INDEX(Inventory!$C:$C,MATCH(A7,Inventory!$A:$A,0)),0) | V7: =T7+U7 | W7: =IFERROR(T7/G7,0) | X7: =IF(V7<Q7,"Critical - expedite",IF(V7<=R7,"Order now",IF(V7>R7+S7,"Overstock","Healthy"))) | Y7: =IF(OR(X7="Critical - expedite",X7="Order now"),MAX(S7,R7+S7-V7),0) | Z7: =IF(X7="Overstock",(V7-R7-S7)*E7,0) | AA7: =Q7*E7 | AB7: =IFERROR(G7*WeeksYear/(G7*CurrentCoverWks)*OrderCost+G7*CurrentCoverWks/2*E7*HoldRate,0) | AC7: =IFERROR(G7*WeeksYear/S7*OrderCost+S7/2*E7*HoldRate,0) | AD7: =AB7-AC7 | AE7: =IFERROR(INDEX(SegStrategy,MATCH(N7,SegList,0)),"") | AF7: =IF(D7=SimSupplier,COUNTIF($D$5:D7,SimSupplier),"") | AG7: =IF(OR(X7="Critical - expedite",X7="Order now"),COUNTIF($X$5:X7,"Critical - expedite")+COUNTIF($X$5:X7,"Order now"),"")
A8: =Products!A5 | B8: =Products!B5 | C8: =Products!C5 | D8: =Products!E5 | E8: =Products!D5 | F8: =SUMIFS(D_Units,D_SKU,A8,D_Last52,1) | G8: =IFERROR(AVERAGEIFS(D_Units,D_SKU,A8,D_Last52,1),0) | H8: =IFERROR(SQRT(MAX(0,(SUMIFS(D_Units2,D_SKU,A8)-COUNTIFS(D_SKU,A8,D_Last52,1)*G8^2)/(COUNTIFS(D_SKU,A8,D_Last52,1)-1))),0) | I8: =F8*E8 | J8: =IFERROR(SUMIF($I$5:$I$53,">"&I8)/SUM($I$5:$I$53),0) | K8: =IF(J8<ACut,"A",IF(J8<BCut,"B","C")) | L8: =IFERROR(H8/G8,0) | M8: =IF(L8<=XMaxCV,"X",IF(L8<=YMaxCV,"Y","Z")) | N8: =K8&M8 | O8: =IFERROR(INDEX(SC_LT,MATCH(D8,SC_ID,0)),0) | P8: =IFERROR(INDEX(SC_LTStd,MATCH(D8,SC_ID,0)),0) | Q8: =ROUNDUP(z*SQRT(O8*H8^2+G8^2*P8^2),0) | R8: =ROUNDUP(G8*O8+Q8,0) | S8: =IFERROR(ROUNDUP(SQRT(2*G8*WeeksYear*OrderCost/(E8*HoldRate)),0),0) | T8: =IFERROR(INDEX(Inventory!$B:$B,MATCH(A8,Inventory!$A:$A,0)),0) | U8: =IFERROR(INDEX(Inventory!$C:$C,MATCH(A8,Inventory!$A:$A,0)),0) | V8: =T8+U8 | W8: =IFERROR(T8/G8,0) | X8: =IF(V8<Q8,"Critical - expedite",IF(V8<=R8,"Order now",IF(V8>R8+S8,"Overstock","Healthy"))) | Y8: =IF(OR(X8="Critical - expedite",X8="Order now"),MAX(S8,R8+S8-V8),0) | Z8: =IF(X8="Overstock",(V8-R8-S8)*E8,0) | AA8: =Q8*E8 | AB8: =IFERROR(G8*WeeksYear/(G8*CurrentCoverWks)*OrderCost+G8*CurrentCoverWks/2*E8*HoldRate,0) | AC8: =IFERROR(G8*WeeksYear/S8*OrderCost+S8/2*E8*HoldRate,0) | AD8: =AB8-AC8 | AE8: =IFERROR(INDEX(SegStrategy,MATCH(N8,SegList,0)),"") | AF8: =IF(D8=SimSupplier,COUNTIF($D$5:D8,SimSupplier),"") | AG8: =IF(OR(X8="Critical - expedite",X8="Order now"),COUNTIF($X$5:X8,"Critical - expedite")+COUNTIF($X$5:X8,"Order now"),"")
A9: =Products!A6 | B9: =Products!B6 | C9: =Products!C6 | D9: =Products!E6 | E9: =Products!D6 | F9: =SUMIFS(D_Units,D_SKU,A9,D_Last52,1) | G9: =IFERROR(AVERAGEIFS(D_Units,D_SKU,A9,D_Last52,1),0) | H9: =IFERROR(SQRT(MAX(0,(SUMIFS(D_Units2,D_SKU,A9)-COUNTIFS(D_SKU,A9,D_Last52,1)*G9^2)/(COUNTIFS(D_SKU,A9,D_Last52,1)-1))),0) | I9: =F9*E9 | J9: =IFERROR(SUMIF($I$5:$I$53,">"&I9)/SUM($I$5:$I$53),0) | K9: =IF(J9<ACut,"A",IF(J9<BCut,"B","C")) | L9: =IFERROR(H9/G9,0) | M9: =IF(L9<=XMaxCV,"X",IF(L9<=YMaxCV,"Y","Z")) | N9: =K9&M9 | O9: =IFERROR(INDEX(SC_LT,MATCH(D9,SC_ID,0)),0) | P9: =IFERROR(INDEX(SC_LTStd,MATCH(D9,SC_ID,0)),0) | Q9: =ROUNDUP(z*SQRT(O9*H9^2+G9^2*P9^2),0) | R9: =ROUNDUP(G9*O9+Q9,0) | S9: =IFERROR(ROUNDUP(SQRT(2*G9*WeeksYear*OrderCost/(E9*HoldRate)),0),0) | T9: =IFERROR(INDEX(Inventory!$B:$B,MATCH(A9,Inventory!$A:$A,0)),0) | U9: =IFERROR(INDEX(Inventory!$C:$C,MATCH(A9,Inventory!$A:$A,0)),0) | V9: =T9+U9 | W9: =IFERROR(T9/G9,0) | X9: =IF(V9<Q9,"Critical - expedite",IF(V9<=R9,"Order now",IF(V9>R9+S9,"Overstock","Healthy"))) | Y9: =IF(OR(X9="Critical - expedite",X9="Order now"),MAX(S9,R9+S9-V9),0) | Z9: =IF(X9="Overstock",(V9-R9-S9)*E9,0) | AA9: =Q9*E9 | AB9: =IFERROR(G9*WeeksYear/(G9*CurrentCoverWks)*OrderCost+G9*CurrentCoverWks/2*E9*HoldRate,0) | AC9: =IFERROR(G9*WeeksYear/S9*OrderCost+S9/2*E9*HoldRate,0) | AD9: =AB9-AC9 | AE9: =IFERROR(INDEX(SegStrategy,MATCH(N9,SegList,0)),"") | AF9: =IF(D9=SimSupplier,COUNTIF($D$5:D9,SimSupplier),"") | AG9: =IF(OR(X9="Critical - expedite",X9="Order now"),COUNTIF($X$5:X9,"Critical - expedite")+COUNTIF($X$5:X9,"Order now"),"")
A10: =Products!A7 | B10: =Products!B7 | C10: =Products!C7 | D10: =Products!E7 | E10: =Products!D7 | F10: =SUMIFS(D_Units,D_SKU,A10,D_Last52,1) | G10: =IFERROR(AVERAGEIFS(D_Units,D_SKU,A10,D_Last52,1),0) | H10: =IFERROR(SQRT(MAX(0,(SUMIFS(D_Units2,D_SKU,A10)-COUNTIFS(D_SKU,A10,D_Last52,1)*G10^2)/(COUNTIFS(D_SKU,A10,D_Last52,1)-1))),0) | I10: =F10*E10 | J10: =IFERROR(SUMIF($I$5:$I$53,">"&I10)/SUM($I$5:$I$53),0) | K10: =IF(J10<ACut,"A",IF(J10<BCut,"B","C")) | L10: =IFERROR(H10/G10,0) | M10: =IF(L10<=XMaxCV,"X",IF(L10<=YMaxCV,"Y","Z")) | N10: =K10&M10 | O10: =IFERROR(INDEX(SC_LT,MATCH(D10,SC_ID,0)),0) | P10: =IFERROR(INDEX(SC_LTStd,MATCH(D10,SC_ID,0)),0) | Q10: =ROUNDUP(z*SQRT(O10*H10^2+G10^2*P10^2),0) | R10: =ROUNDUP(G10*O10+Q10,0) | S10: =IFERROR(ROUNDUP(SQRT(2*G10*WeeksYear*OrderCost/(E10*HoldRate)),0),0) | T10: =IFERROR(INDEX(Inventory!$B:$B,MATCH(A10,Inventory!$A:$A,0)),0) | U10: =IFERROR(INDEX(Inventory!$C:$C,MATCH(A10,Inventory!$A:$A,0)),0) | V10: =T10+U10 | W10: =IFERROR(T10/G10,0) | X10: =IF(V10<Q10,"Critical - expedite",IF(V10<=R10,"Order now",IF(V10>R10+S10,"Overstock","Healthy"))) | Y10: =IF(OR(X10="Critical - expedite",X10="Order now"),MAX(S10,R10+S10-V10),0) | Z10: =IF(X10="Overstock",(V10-R10-S10)*E10,0) | AA10: =Q10*E10 | AB10: =IFERROR(G10*WeeksYear/(G10*CurrentCoverWks)*OrderCost+G10*CurrentCoverWks/2*E10*HoldRate,0) | AC10: =IFERROR(G10*WeeksYear/S10*OrderCost+S10/2*E10*HoldRate,0) | AD10: =AB10-AC10 | AE10: =IFERROR(INDEX(SegStrategy,MATCH(N10,SegList,0)),"") | AF10: =IF(D10=SimSupplier,COUNTIF($D$5:D10,SimSupplier),"") | AG10: =IF(OR(X10="Critical - expedite",X10="Order now"),COUNTIF($X$5:X10,"Critical - expedite")+COUNTIF($X$5:X10,"Order now"),"")
A11: =Products!A8 | B11: =Products!B8 | C11: =Products!C8 | D11: =Products!E8 | E11: =Products!D8 | F11: =SUMIFS(D_Units,D_SKU,A11,D_Last52,1) | G11: =IFERROR(AVERAGEIFS(D_Units,D_SKU,A11,D_Last52,1),0) | H11: =IFERROR(SQRT(MAX(0,(SUMIFS(D_Units2,D_SKU,A11)-COUNTIFS(D_SKU,A11,D_Last52,1)*G11^2)/(COUNTIFS(D_SKU,A11,D_Last52,1)-1))),0) | I11: =F11*E11 | J11: =IFERROR(SUMIF($I$5:$I$53,">"&I11)/SUM($I$5:$I$53),0) | K11: =IF(J11<ACut,"A",IF(J11<BCut,"B","C")) | L11: =IFERROR(H11/G11,0) | M11: =IF(L11<=XMaxCV,"X",IF(L11<=YMaxCV,"Y","Z")) | N11: =K11&M11 | O11: =IFERROR(INDEX(SC_LT,MATCH(D11,SC_ID,0)),0) | P11: =IFERROR(INDEX(SC_LTStd,MATCH(D11,SC_ID,0)),0) | Q11: =ROUNDUP(z*SQRT(O11*H11^2+G11^2*P11^2),0) | R11: =ROUNDUP(G11*O11+Q11,0) | S11: =IFERROR(ROUNDUP(SQRT(2*G11*WeeksYear*OrderCost/(E11*HoldRate)),0),0) | T11: =IFERROR(INDEX(Inventory!$B:$B,MATCH(A11,Inventory!$A:$A,0)),0) | U11: =IFERROR(INDEX(Inventory!$C:$C,MATCH(A11,Inventory!$A:$A,0)),0) | V11: =T11+U11 | W11: =IFERROR(T11/G11,0) | X11: =IF(V11<Q11,"Critical - expedite",IF(V11<=R11,"Order now",IF(V11>R11+S11,"Overstock","Healthy"))) | Y11: =IF(OR(X11="Critical - expedite",X11="Order now"),MAX(S11,R11+S11-V11),0) | Z11: =IF(X11="Overstock",(V11-R11-S11)*E11,0) | AA11: =Q11*E11 | AB11: =IFERROR(G11*WeeksYear/(G11*CurrentCoverWks)*OrderCost+G11*CurrentCoverWks/2*E11*HoldRate,0) | AC11: =IFERROR(G11*WeeksYear/S11*OrderCost+S11/2*E11*HoldRate,0) | AD11: =AB11-AC11 | AE11: =IFERROR(INDEX(SegStrategy,MATCH(N11,SegList,0)),"") | AF11: =IF(D11=SimSupplier,COUNTIF($D$5:D11,SimSupplier),"") | AG11: =IF(OR(X11="Critical - expedite",X11="Order now"),COUNTIF($X$5:X11,"Critical - expedite")+COUNTIF($X$5:X11,"Order now"),"")
A12: =Products!A9 | B12: =Products!B9 | C12: =Products!C9 | D12: =Products!E9 | E12: =Products!D9 | F12: =SUMIFS(D_Units,D_SKU,A12,D_Last52,1) | G12: =IFERROR(AVERAGEIFS(D_Units,D_SKU,A12,D_Last52,1),0) | H12: =IFERROR(SQRT(MAX(0,(SUMIFS(D_Units2,D_SKU,A12)-COUNTIFS(D_SKU,A12,D_Last52,1)*G12^2)/(COUNTIFS(D_SKU,A12,D_Last52,1)-1))),0) | I12: =F12*E12 | J12: =IFERROR(SUMIF($I$5:$I$53,">"&I12)/SUM($I$5:$I$53),0) | K12: =IF(J12<ACut,"A",IF(J12<BCut,"B","C")) | L12: =IFERROR(H12/G12,0) | M12: =IF(L12<=XMaxCV,"X",IF(L12<=YMaxCV,"Y","Z")) | N12: =K12&M12 | O12: =IFERROR(INDEX(SC_LT,MATCH(D12,SC_ID,0)),0) | P12: =IFERROR(INDEX(SC_LTStd,MATCH(D12,SC_ID,0)),0) | Q12: =ROUNDUP(z*SQRT(O12*H12^2+G12^2*P12^2),0) | R12: =ROUNDUP(G12*O12+Q12,0) | S12: =IFERROR(ROUNDUP(SQRT(2*G12*WeeksYear*OrderCost/(E12*HoldRate)),0),0) | T12: =IFERROR(INDEX(Inventory!$B:$B,MATCH(A12,Inventory!$A:$A,0)),0) | U12: =IFERROR(INDEX(Inventory!$C:$C,MATCH(A12,Inventory!$A:$A,0)),0) | V12: =T12+U12 | W12: =IFERROR(T12/G12,0) | X12: =IF(V12<Q12,"Critical - expedite",IF(V12<=R12,"Order now",IF(V12>R12+S12,"Overstock","Healthy"))) | Y12: =IF(OR(X12="Critical - expedite",X12="Order now"),MAX(S12,R12+S12-V12),0) | Z12: =IF(X12="Overstock",(V12-R12-S12)*E12,0) | AA12: =Q12*E12 | AB12: =IFERROR(G12*WeeksYear/(G12*CurrentCoverWks)*OrderCost+G12*CurrentCoverWks/2*E12*HoldRate,0) | AC12: =IFERROR(G12*WeeksYear/S12*OrderCost+S12/2*E12*HoldRate,0) | AD12: =AB12-AC12 | AE12: =IFERROR(INDEX(SegStrategy,MATCH(N12,SegList,0)),"") | AF12: =IF(D12=SimSupplier,COUNTIF($D$5:D12,SimSupplier),"") | AG12: =IF(OR(X12="Critical - expedite",X12="Order now"),COUNTIF($X$5:X12,"Critical - expedite")+COUNTIF($X$5:X12,"Order now"),"")
A13: =Products!A10 | B13: =Products!B10 | C13: =Products!C10 | D13: =Products!E10 | E13: =Products!D10 | F13: =SUMIFS(D_Units,D_SKU,A13,D_Last52,1) | G13: =IFERROR(AVERAGEIFS(D_Units,D_SKU,A13,D_Last52,1),0) | H13: =IFERROR(SQRT(MAX(0,(SUMIFS(D_Units2,D_SKU,A13)-COUNTIFS(D_SKU,A13,D_Last52,1)*G13^2)/(COUNTIFS(D_SKU,A13,D_Last52,1)-1))),0) | I13: =F13*E13 | J13: =IFERROR(SUMIF($I$5:$I$53,">"&I13)/SUM($I$5:$I$53),0) | K13: =IF(J13<ACut,"A",IF(J13<BCut,"B","C")) | L13: =IFERROR(H13/G13,0) | M13: =IF(L13<=XMaxCV,"X",IF(L13<=YMaxCV,"Y","Z")) | N13: =K13&M13 | O13: =IFERROR(INDEX(SC_LT,MATCH(D13,SC_ID,0)),0) | P13: =IFERROR(INDEX(SC_LTStd,MATCH(D13,SC_ID,0)),0) | Q13: =ROUNDUP(z*SQRT(O13*H13^2+G13^2*P13^2),0) | R13: =ROUNDUP(G13*O13+Q13,0) | S13: =IFERROR(ROUNDUP(SQRT(2*G13*WeeksYear*OrderCost/(E13*HoldRate)),0),0) | T13: =IFERROR(INDEX(Inventory!$B:$B,MATCH(A13,Inventory!$A:$A,0)),0) | U13: =IFERROR(INDEX(Inventory!$C:$C,MATCH(A13,Inventory!$A:$A,0)),0) | V13: =T13+U13 | W13: =IFERROR(T13/G13,0) | X13: =IF(V13<Q13,"Critical - expedite",IF(V13<=R13,"Order now",IF(V13>R13+S13,"Overstock","Healthy"))) | Y13: =IF(OR(X13="Critical - expedite",X13="Order now"),MAX(S13,R13+S13-V13),0) | Z13: =IF(X13="Overstock",(V13-R13-S13)*E13,0) | AA13: =Q13*E13 | AB13: =IFERROR(G13*WeeksYear/(G13*CurrentCoverWks)*OrderCost+G13*CurrentCoverWks/2*E13*HoldRate,0) | AC13: =IFERROR(G13*WeeksYear/S13*OrderCost+S13/2*E13*HoldRate,0) | AD13: =AB13-AC13 | AE13: =IFERROR(INDEX(SegStrategy,MATCH(N13,SegList,0)),"") | AF13: =IF(D13=SimSupplier,COUNTIF($D$5:D13,SimSupplier),"") | AG13: =IF(OR(X13="Critical - expedite",X13="Order now"),COUNTIF($X$5:X13,"Critical - expedite")+COUNTIF($X$5:X13,"Order now"),"")
A14: =Products!A11 | B14: =Products!B11 | C14: =Products!C11 | D14: =Products!E11 | E14: =Products!D11 | F14: =SUMIFS(D_Units,D_SKU,A14,D_Last52,1) | G14: =IFERROR(AVERAGEIFS(D_Units,D_SKU,A14,D_Last52,1),0) | H14: =IFERROR(SQRT(MAX(0,(SUMIFS(D_Units2,D_SKU,A14)-COUNTIFS(D_SKU,A14,D_Last52,1)*G14^2)/(COUNTIFS(D_SKU,A14,D_Last52,1)-1))),0) | I14: =F14*E14 | J14: =IFERROR(SUMIF($I$5:$I$53,">"&I14)/SUM($I$5:$I$53),0) | K14: =IF(J14<ACut,"A",IF(J14<BCut,"B","C")) | L14: =IFERROR(H14/G14,0) | M14: =IF(L14<=XMaxCV,"X",IF(L14<=YMaxCV,"Y","Z")) | N14: =K14&M14 | O14: =IFERROR(INDEX(SC_LT,MATCH(D14,SC_ID,0)),0) | P14: =IFERROR(INDEX(SC_LTStd,MATCH(D14,SC_ID,0)),0) | Q14: =ROUNDUP(z*SQRT(O14*H14^2+G14^2*P14^2),0) | R14: =ROUNDUP(G14*O14+Q14,0) | S14: =IFERROR(ROUNDUP(SQRT(2*G14*WeeksYear*OrderCost/(E14*HoldRate)),0),0) | T14: =IFERROR(INDEX(Inventory!$B:$B,MATCH(A14,Inventory!$A:$A,0)),0) | U14: =IFERROR(INDEX(Inventory!$C:$C,MATCH(A14,Inventory!$A:$A,0)),0) | V14: =T14+U14 | W14: =IFERROR(T14/G14,0) | X14: =IF(V14<Q14,"Critical - expedite",IF(V14<=R14,"Order now",IF(V14>R14+S14,"Overstock","Healthy"))) | Y14: =IF(OR(X14="Critical - expedite",X14="Order now"),MAX(S14,R14+S14-V14),0) | Z14: =IF(X14="Overstock",(V14-R14-S14)*E14,0) | AA14: =Q14*E14 | AB14: =IFERROR(G14*WeeksYear/(G14*CurrentCoverWks)*OrderCost+G14*CurrentCoverWks/2*E14*HoldRate,0) | AC14: =IFERROR(G14*WeeksYear/S14*OrderCost+S14/2*E14*HoldRate,0) | AD14: =AB14-AC14 | AE14: =IFERROR(INDEX(SegStrategy,MATCH(N14,SegList,0)),"") | AF14: =IF(D14=SimSupplier,COUNTIF($D$5:D14,SimSupplier),"") | AG14: =IF(OR(X14="Critical - expedite",X14="Order now"),COUNTIF($X$5:X14,"Critical - expedite")+COUNTIF($X$5:X14,"Order now"),"")
A15: =Products!A12 | B15: =Products!B12 | C15: =Products!C12 | D15: =Products!E12 | E15: =Products!D12 | F15: =SUMIFS(D_Units,D_SKU,A15,D_Last52,1) | G15: =IFERROR(AVERAGEIFS(D_Units,D_SKU,A15,D_Last52,1),0) | H15: =IFERROR(SQRT(MAX(0,(SUMIFS(D_Units2,D_SKU,A15)-COUNTIFS(D_SKU,A15,D_Last52,1)*G15^2)/(COUNTIFS(D_SKU,A15,D_Last52,1)-1))),0) | I15: =F15*E15 | J15: =IFERROR(SUMIF($I$5:$I$53,">"&I15)/SUM($I$5:$I$53),0) | K15: =IF(J15<ACut,"A",IF(J15<BCut,"B","C")) | L15: =IFERROR(H15/G15,0) | M15: =IF(L15<=XMaxCV,"X",IF(L15<=YMaxCV,"Y","Z")) | N15: =K15&M15 | O15: =IFERROR(INDEX(SC_LT,MATCH(D15,SC_ID,0)),0) | P15: =IFERROR(INDEX(SC_LTStd,MATCH(D15,SC_ID,0)),0) | Q15: =ROUNDUP(z*SQRT(O15*H15^2+G15^2*P15^2),0) | R15: =ROUNDUP(G15*O15+Q15,0) | S15: =IFERROR(ROUNDUP(SQRT(2*G15*WeeksYear*OrderCost/(E15*HoldRate)),0),0) | T15: =IFERROR(INDEX(Inventory!$B:$B,MATCH(A15,Inventory!$A:$A,0)),0) | U15: =IFERROR(INDEX(Inventory!$C:$C,MATCH(A15,Inventory!$A:$A,0)),0) | V15: =T15+U15 | W15: =IFERROR(T15/G15,0) | X15: =IF(V15<Q15,"Critical - expedite",IF(V15<=R15,"Order now",IF(V15>R15+S15,"Overstock","Healthy"))) | Y15: =IF(OR(X15="Critical - expedite",X15="Order now"),MAX(S15,R15+S15-V15),0) | Z15: =IF(X15="Overstock",(V15-R15-S15)*E15,0) | AA15: =Q15*E15 | AB15: =IFERROR(G15*WeeksYear/(G15*CurrentCoverWks)*OrderCost+G15*CurrentCoverWks/2*E15*HoldRate,0) | AC15: =IFERROR(G15*WeeksYear/S15*OrderCost+S15/2*E15*HoldRate,0) | AD15: =AB15-AC15 | AE15: =IFERROR(INDEX(SegStrategy,MATCH(N15,SegList,0)),"") | AF15: =IF(D15=SimSupplier,COUNTIF($D$5:D15,SimSupplier),"") | AG15: =IF(OR(X15="Critical - expedite",X15="Order now"),COUNTIF($X$5:X15,"Critical - expedite")+COUNTIF($X$5:X15,"Order now"),"")
A16: =Products!A13 | B16: =Products!B13 | C16: =Products!C13 | D16: =Products!E13 | E16: =Products!D13 | F16: =SUMIFS(D_Units,D_SKU,A16,D_Last52,1) | G16: =IFERROR(AVERAGEIFS(D_Units,D_SKU,A16,D_Last52,1),0) | H16: =IFERROR(SQRT(MAX(0,(SUMIFS(D_Units2,D_SKU,A16)-COUNTIFS(D_SKU,A16,D_Last52,1)*G16^2)/(COUNTIFS(D_SKU,A16,D_Last52,1)-1))),0) | I16: =F16*E16 | J16: =IFERROR(SUMIF($I$5:$I$53,">"&I16)/SUM($I$5:$I$53),0) | K16: =IF(J16<ACut,"A",IF(J16<BCut,"B","C")) | L16: =IFERROR(H16/G16,0) | M16: =IF(L16<=XMaxCV,"X",IF(L16<=YMaxCV,"Y","Z")) | N16: =K16&M16 | O16: =IFERROR(INDEX(SC_LT,MATCH(D16,SC_ID,0)),0) | P16: =IFERROR(INDEX(SC_LTStd,MATCH(D16,SC_ID,0)),0) | Q16: =ROUNDUP(z*SQRT(O16*H16^2+G16^2*P16^2),0) | R16: =ROUNDUP(G16*O16+Q16,0) | S16: =IFERROR(ROUNDUP(SQRT(2*G16*WeeksYear*OrderCost/(E16*HoldRate)),0),0) | T16: =IFERROR(INDEX(Inventory!$B:$B,MATCH(A16,Inventory!$A:$A,0)),0) | U16: =IFERROR(INDEX(Inventory!$C:$C,MATCH(A16,Inventory!$A:$A,0)),0) | V16: =T16+U16 | W16: =IFERROR(T16/G16,0) | X16: =IF(V16<Q16,"Critical - expedite",IF(V16<=R16,"Order now",IF(V16>R16+S16,"Overstock","Healthy"))) | Y16: =IF(OR(X16="Critical - expedite",X16="Order now"),MAX(S16,R16+S16-V16),0) | Z16: =IF(X16="Overstock",(V16-R16-S16)*E16,0) | AA16: =Q16*E16 | AB16: =IFERROR(G16*WeeksYear/(G16*CurrentCoverWks)*OrderCost+G16*CurrentCoverWks/2*E16*HoldRate,0) | AC16: =IFERROR(G16*WeeksYear/S16*OrderCost+S16/2*E16*HoldRate,0) | AD16: =AB16-AC16 | AE16: =IFERROR(INDEX(SegStrategy,MATCH(N16,SegList,0)),"") | AF16: =IF(D16=SimSupplier,COUNTIF($D$5:D16,SimSupplier),"") | AG16: =IF(OR(X16="Critical - expedite",X16="Order now"),COUNTIF($X$5:X16,"Critical - expedite")+COUNTIF($X$5:X16,"Order now"),"")
... A53: =Products!A50 | B53: =Products!B50 | C53: =Products!C50 | D53: =Products!E50 | E53: =Products!D50 | F53: =SUMIFS(D_Units,D_SKU,A53,D_Last52,1) | G53: =IFERROR(AVERAGEIFS(D_Units,D_SKU,A53,D_Last52,1),0) | H53: =IFERROR(SQRT(MAX(0,(SUMIFS(D_Units2,D_SKU,A53)-COUNTIFS(D_SKU,A53,D_Last52,1)*G53^2)/(COUNTIFS(D_SKU,A53,D_Last52,1)-1))),0) | I53: =F53*E53 | J53: =IFERROR(SUMIF($I$5:$I$53,">"&I53)/SUM($I$5:$I$53),0) | K53: =IF(J53<ACut,"A",IF(J53<BCut,"B","C")) | L53: =IFERROR(H53/G53,0) | M53: =IF(L53<=XMaxCV,"X",IF(L53<=YMaxCV,"Y","Z")) | N53: =K53&M53 | O53: =IFERROR(INDEX(SC_LT,MATCH(D53,SC_ID,0)),0) | P53: =IFERROR(INDEX(SC_LTStd,MATCH(D53,SC_ID,0)),0) | Q53: =ROUNDUP(z*SQRT(O53*H53^2+G53^2*P53^2),0) | R53: =ROUNDUP(G53*O53+Q53,0) | S53: =IFERROR(ROUNDUP(SQRT(2*G53*WeeksYear*OrderCost/(E53*HoldRate)),0),0) | T53: =IFERROR(INDEX(Inventory!$B:$B,MATCH(A53,Inventory!$A:$A,0)),0) | U53: =IFERROR(INDEX(Inventory!$C:$C,MATCH(A53,Inventory!$A:$A,0)),0) | V53: =T53+U53 | W53: =IFERROR(T53/G53,0) | X53: =IF(V53<Q53,"Critical - expedite",IF(V53<=R53,"Order now",IF(V53>R53+S53,"Overstock","Healthy"))) | Y53: =IF(OR(X53="Critical - expedite",X53="Order now"),MAX(S53,R53+S53-V53),0) | Z53: =IF(X53="Overstock",(V53-R53-S53)*E53,0) | AA53: =Q53*E53 | AB53: =IFERROR(G53*WeeksYear/(G53*CurrentCoverWks)*OrderCost+G53*CurrentCoverWks/2*E53*HoldRate,0) | AC53: =IFERROR(G53*WeeksYear/S53*OrderCost+S53/2*E53*HoldRate,0) | AD53: =AB53-AC53 | AE53: =IFERROR(INDEX(SegStrategy,MATCH(N53,SegList,0)),"") | AF53: =IF(D53=SimSupplier,COUNTIF($D$5:D53,SimSupplier),"") | AG53: =IF(OR(X53="Critical - expedite",X53="Order now"),COUNTIF($X$5:X53,"Critical - expedite")+COUNTIF($X$5:X53,"Order now"),"")

Sheet Supplier_Scorecard
A1: Supplier Scorecard & Risk Score
A2: Every column is a formula over the Purchase_Orders sheet. Weights and thresholds are on the Assumptions sheet.
T3: Weighted contribution of each factor (used to find the main driver)
A4: Supplier ID | B4: Supplier | C4: Country | D4: POs | E4: Spend (CAD) | F4: Share of spend | G4: On-time delivery | H4: Avg days late | I4: Avg lead time (wks) | J4: Lead time std (wks) | K4: Lead time CV | L4: Fill rate | M4: Defect rate | N4: Country risk (1-5) | O4: Factor: late | P4: Factor: LT variability | Q4: Factor: quality | R4: Factor: country | S4: Factor: spend | T4: late delivery | U4: lead time variability | V4: quality | W4: country risk | X4: spend dependency | Y4: Risk score (0-100) | Z4: Risk tier | AA4: Main risk driver | AB4: Recommended action | AC4: Risk rank
A5: =Suppliers!A2 | B5: =Suppliers!B2 | C5: =Suppliers!C2 | D5: =COUNTIF(PO_Sup,A5) | E5: =SUMIF(PO_Sup,A5,PO_Value) | F5: =IFERROR(E5/SUM($E$5:$E$12),0) | G5: =IFERROR(AVERAGEIF(PO_Sup,A5,PO_OnTime),0) | H5: =IFERROR(AVERAGEIF(PO_Sup,A5,PO_DaysLate),0) | I5: =IFERROR(AVERAGEIF(PO_Sup,A5,PO_LT),0) | J5: =IFERROR(SQRT(MAX(0,(SUMIF(PO_Sup,A5,PO_LT2)-D5*I5^2)/(D5-1))),0) | K5: =IFERROR(J5/I5,0) | L5: =IFERROR(SUMIF(PO_Sup,A5,PO_QtyRec)/SUMIF(PO_Sup,A5,PO_QtyOrd),0) | M5: =IFERROR(SUMIF(PO_Sup,A5,PO_QtyDef)/SUMIF(PO_Sup,A5,PO_QtyRec),0) | N5: =IFERROR(INDEX(CountryScore,MATCH(C5,CountryList,0)),3) | O5: =MIN(1,MAX(0,(1-G5)/BadLate)) | P5: =MIN(1,MAX(0,K5/BadLTV)) | Q5: =MIN(1,MAX(0,M5/BadQuality)) | R5: =MIN(1,MAX(0,(N5-1)/4)) | S5: =MIN(1,MAX(0,F5/BadSpend)) | T5: =O5*wLate | U5: =P5*wLTV | V5: =Q5*wQuality | W5: =R5*wCountry | X5: =S5*wSpend | Y5: =ROUND(SUM(T5:X5)*100,1) | Z5: =IF(Y5>60,"High",IF(Y5>35,"Medium","Low")) | AA5: =INDEX($T$4:$X$4,MATCH(MAX(T5:X5),T5:X5,0)) | AB5: =IF(AND(Z5="Low",F5>=0.25),"Reliable, but holds a large share of spend: keep as primary and qualify a backup supplier for its A-class SKUs",IF(Z5="Low","Maintain; candidate for volume consolidation / preferred-supplier status",IF(Z5="High","Priority: ","")&INDEX(DriverAction,MATCH(AA5,DriverList,0)))) | AC5: =RANK(Y5,$Y$5:$Y$12)
A6: =Suppliers!A3 | B6: =Suppliers!B3 | C6: =Suppliers!C3 | D6: =COUNTIF(PO_Sup,A6) | E6: =SUMIF(PO_Sup,A6,PO_Value) | F6: =IFERROR(E6/SUM($E$5:$E$12),0) | G6: =IFERROR(AVERAGEIF(PO_Sup,A6,PO_OnTime),0) | H6: =IFERROR(AVERAGEIF(PO_Sup,A6,PO_DaysLate),0) | I6: =IFERROR(AVERAGEIF(PO_Sup,A6,PO_LT),0) | J6: =IFERROR(SQRT(MAX(0,(SUMIF(PO_Sup,A6,PO_LT2)-D6*I6^2)/(D6-1))),0) | K6: =IFERROR(J6/I6,0) | L6: =IFERROR(SUMIF(PO_Sup,A6,PO_QtyRec)/SUMIF(PO_Sup,A6,PO_QtyOrd),0) | M6: =IFERROR(SUMIF(PO_Sup,A6,PO_QtyDef)/SUMIF(PO_Sup,A6,PO_QtyRec),0) | N6: =IFERROR(INDEX(CountryScore,MATCH(C6,CountryList,0)),3) | O6: =MIN(1,MAX(0,(1-G6)/BadLate)) | P6: =MIN(1,MAX(0,K6/BadLTV)) | Q6: =MIN(1,MAX(0,M6/BadQuality)) | R6: =MIN(1,MAX(0,(N6-1)/4)) | S6: =MIN(1,MAX(0,F6/BadSpend)) | T6: =O6*wLate | U6: =P6*wLTV | V6: =Q6*wQuality | W6: =R6*wCountry | X6: =S6*wSpend | Y6: =ROUND(SUM(T6:X6)*100,1) | Z6: =IF(Y6>60,"High",IF(Y6>35,"Medium","Low")) | AA6: =INDEX($T$4:$X$4,MATCH(MAX(T6:X6),T6:X6,0)) | AB6: =IF(AND(Z6="Low",F6>=0.25),"Reliable, but holds a large share of spend: keep as primary and qualify a backup supplier for its A-class SKUs",IF(Z6="Low","Maintain; candidate for volume consolidation / preferred-supplier status",IF(Z6="High","Priority: ","")&INDEX(DriverAction,MATCH(AA6,DriverList,0)))) | AC6: =RANK(Y6,$Y$5:$Y$12)
A7: =Suppliers!A4 | B7: =Suppliers!B4 | C7: =Suppliers!C4 | D7: =COUNTIF(PO_Sup,A7) | E7: =SUMIF(PO_Sup,A7,PO_Value) | F7: =IFERROR(E7/SUM($E$5:$E$12),0) | G7: =IFERROR(AVERAGEIF(PO_Sup,A7,PO_OnTime),0) | H7: =IFERROR(AVERAGEIF(PO_Sup,A7,PO_DaysLate),0) | I7: =IFERROR(AVERAGEIF(PO_Sup,A7,PO_LT),0) | J7: =IFERROR(SQRT(MAX(0,(SUMIF(PO_Sup,A7,PO_LT2)-D7*I7^2)/(D7-1))),0) | K7: =IFERROR(J7/I7,0) | L7: =IFERROR(SUMIF(PO_Sup,A7,PO_QtyRec)/SUMIF(PO_Sup,A7,PO_QtyOrd),0) | M7: =IFERROR(SUMIF(PO_Sup,A7,PO_QtyDef)/SUMIF(PO_Sup,A7,PO_QtyRec),0) | N7: =IFERROR(INDEX(CountryScore,MATCH(C7,CountryList,0)),3) | O7: =MIN(1,MAX(0,(1-G7)/BadLate)) | P7: =MIN(1,MAX(0,K7/BadLTV)) | Q7: =MIN(1,MAX(0,M7/BadQuality)) | R7: =MIN(1,MAX(0,(N7-1)/4)) | S7: =MIN(1,MAX(0,F7/BadSpend)) | T7: =O7*wLate | U7: =P7*wLTV | V7: =Q7*wQuality | W7: =R7*wCountry | X7: =S7*wSpend | Y7: =ROUND(SUM(T7:X7)*100,1) | Z7: =IF(Y7>60,"High",IF(Y7>35,"Medium","Low")) | AA7: =INDEX($T$4:$X$4,MATCH(MAX(T7:X7),T7:X7,0)) | AB7: =IF(AND(Z7="Low",F7>=0.25),"Reliable, but holds a large share of spend: keep as primary and qualify a backup supplier for its A-class SKUs",IF(Z7="Low","Maintain; candidate for volume consolidation / preferred-supplier status",IF(Z7="High","Priority: ","")&INDEX(DriverAction,MATCH(AA7,DriverList,0)))) | AC7: =RANK(Y7,$Y$5:$Y$12)
A8: =Suppliers!A5 | B8: =Suppliers!B5 | C8: =Suppliers!C5 | D8: =COUNTIF(PO_Sup,A8) | E8: =SUMIF(PO_Sup,A8,PO_Value) | F8: =IFERROR(E8/SUM($E$5:$E$12),0) | G8: =IFERROR(AVERAGEIF(PO_Sup,A8,PO_OnTime),0) | H8: =IFERROR(AVERAGEIF(PO_Sup,A8,PO_DaysLate),0) | I8: =IFERROR(AVERAGEIF(PO_Sup,A8,PO_LT),0) | J8: =IFERROR(SQRT(MAX(0,(SUMIF(PO_Sup,A8,PO_LT2)-D8*I8^2)/(D8-1))),0) | K8: =IFERROR(J8/I8,0) | L8: =IFERROR(SUMIF(PO_Sup,A8,PO_QtyRec)/SUMIF(PO_Sup,A8,PO_QtyOrd),0) | M8: =IFERROR(SUMIF(PO_Sup,A8,PO_QtyDef)/SUMIF(PO_Sup,A8,PO_QtyRec),0) | N8: =IFERROR(INDEX(CountryScore,MATCH(C8,CountryList,0)),3) | O8: =MIN(1,MAX(0,(1-G8)/BadLate)) | P8: =MIN(1,MAX(0,K8/BadLTV)) | Q8: =MIN(1,MAX(0,M8/BadQuality)) | R8: =MIN(1,MAX(0,(N8-1)/4)) | S8: =MIN(1,MAX(0,F8/BadSpend)) | T8: =O8*wLate | U8: =P8*wLTV | V8: =Q8*wQuality | W8: =R8*wCountry | X8: =S8*wSpend | Y8: =ROUND(SUM(T8:X8)*100,1) | Z8: =IF(Y8>60,"High",IF(Y8>35,"Medium","Low")) | AA8: =INDEX($T$4:$X$4,MATCH(MAX(T8:X8),T8:X8,0)) | AB8: =IF(AND(Z8="Low",F8>=0.25),"Reliable, but holds a large share of spend: keep as primary and qualify a backup supplier for its A-class SKUs",IF(Z8="Low","Maintain; candidate for volume consolidation / preferred-supplier status",IF(Z8="High","Priority: ","")&INDEX(DriverAction,MATCH(AA8,DriverList,0)))) | AC8: =RANK(Y8,$Y$5:$Y$12)
A9: =Suppliers!A6 | B9: =Suppliers!B6 | C9: =Suppliers!C6 | D9: =COUNTIF(PO_Sup,A9) | E9: =SUMIF(PO_Sup,A9,PO_Value) | F9: =IFERROR(E9/SUM($E$5:$E$12),0) | G9: =IFERROR(AVERAGEIF(PO_Sup,A9,PO_OnTime),0) | H9: =IFERROR(AVERAGEIF(PO_Sup,A9,PO_DaysLate),0) | I9: =IFERROR(AVERAGEIF(PO_Sup,A9,PO_LT),0) | J9: =IFERROR(SQRT(MAX(0,(SUMIF(PO_Sup,A9,PO_LT2)-D9*I9^2)/(D9-1))),0) | K9: =IFERROR(J9/I9,0) | L9: =IFERROR(SUMIF(PO_Sup,A9,PO_QtyRec)/SUMIF(PO_Sup,A9,PO_QtyOrd),0) | M9: =IFERROR(SUMIF(PO_Sup,A9,PO_QtyDef)/SUMIF(PO_Sup,A9,PO_QtyRec),0) | N9: =IFERROR(INDEX(CountryScore,MATCH(C9,CountryList,0)),3) | O9: =MIN(1,MAX(0,(1-G9)/BadLate)) | P9: =MIN(1,MAX(0,K9/BadLTV)) | Q9: =MIN(1,MAX(0,M9/BadQuality)) | R9: =MIN(1,MAX(0,(N9-1)/4)) | S9: =MIN(1,MAX(0,F9/BadSpend)) | T9: =O9*wLate | U9: =P9*wLTV | V9: =Q9*wQuality | W9: =R9*wCountry | X9: =S9*wSpend | Y9: =ROUND(SUM(T9:X9)*100,1) | Z9: =IF(Y9>60,"High",IF(Y9>35,"Medium","Low")) | AA9: =INDEX($T$4:$X$4,MATCH(MAX(T9:X9),T9:X9,0)) | AB9: =IF(AND(Z9="Low",F9>=0.25),"Reliable, but holds a large share of spend: keep as primary and qualify a backup supplier for its A-class SKUs",IF(Z9="Low","Maintain; candidate for volume consolidation / preferred-supplier status",IF(Z9="High","Priority: ","")&INDEX(DriverAction,MATCH(AA9,DriverList,0)))) | AC9: =RANK(Y9,$Y$5:$Y$12)
A10: =Suppliers!A7 | B10: =Suppliers!B7 | C10: =Suppliers!C7 | D10: =COUNTIF(PO_Sup,A10) | E10: =SUMIF(PO_Sup,A10,PO_Value) | F10: =IFERROR(E10/SUM($E$5:$E$12),0) | G10: =IFERROR(AVERAGEIF(PO_Sup,A10,PO_OnTime),0) | H10: =IFERROR(AVERAGEIF(PO_Sup,A10,PO_DaysLate),0) | I10: =IFERROR(AVERAGEIF(PO_Sup,A10,PO_LT),0) | J10: =IFERROR(SQRT(MAX(0,(SUMIF(PO_Sup,A10,PO_LT2)-D10*I10^2)/(D10-1))),0) | K10: =IFERROR(J10/I10,0) | L10: =IFERROR(SUMIF(PO_Sup,A10,PO_QtyRec)/SUMIF(PO_Sup,A10,PO_QtyOrd),0) | M10: =IFERROR(SUMIF(PO_Sup,A10,PO_QtyDef)/SUMIF(PO_Sup,A10,PO_QtyRec),0) | N10: =IFERROR(INDEX(CountryScore,MATCH(C10,CountryList,0)),3) | O10: =MIN(1,MAX(0,(1-G10)/BadLate)) | P10: =MIN(1,MAX(0,K10/BadLTV)) | Q10: =MIN(1,MAX(0,M10/BadQuality)) | R10: =MIN(1,MAX(0,(N10-1)/4)) | S10: =MIN(1,MAX(0,F10/BadSpend)) | T10: =O10*wLate | U10: =P10*wLTV | V10: =Q10*wQuality | W10: =R10*wCountry | X10: =S10*wSpend | Y10: =ROUND(SUM(T10:X10)*100,1) | Z10: =IF(Y10>60,"High",IF(Y10>35,"Medium","Low")) | AA10: =INDEX($T$4:$X$4,MATCH(MAX(T10:X10),T10:X10,0)) | AB10: =IF(AND(Z10="Low",F10>=0.25),"Reliable, but holds a large share of spend: keep as primary and qualify a backup supplier for its A-class SKUs",IF(Z10="Low","Maintain; candidate for volume consolidation / preferred-supplier status",IF(Z10="High","Priority: ","")&INDEX(DriverAction,MATCH(AA10,DriverList,0)))) | AC10: =RANK(Y10,$Y$5:$Y$12)
A11: =Suppliers!A8 | B11: =Suppliers!B8 | C11: =Suppliers!C8 | D11: =COUNTIF(PO_Sup,A11) | E11: =SUMIF(PO_Sup,A11,PO_Value) | F11: =IFERROR(E11/SUM($E$5:$E$12),0) | G11: =IFERROR(AVERAGEIF(PO_Sup,A11,PO_OnTime),0) | H11: =IFERROR(AVERAGEIF(PO_Sup,A11,PO_DaysLate),0) | I11: =IFERROR(AVERAGEIF(PO_Sup,A11,PO_LT),0) | J11: =IFERROR(SQRT(MAX(0,(SUMIF(PO_Sup,A11,PO_LT2)-D11*I11^2)/(D11-1))),0) | K11: =IFERROR(J11/I11,0) | L11: =IFERROR(SUMIF(PO_Sup,A11,PO_QtyRec)/SUMIF(PO_Sup,A11,PO_QtyOrd),0) | M11: =IFERROR(SUMIF(PO_Sup,A11,PO_QtyDef)/SUMIF(PO_Sup,A11,PO_QtyRec),0) | N11: =IFERROR(INDEX(CountryScore,MATCH(C11,CountryList,0)),3) | O11: =MIN(1,MAX(0,(1-G11)/BadLate)) | P11: =MIN(1,MAX(0,K11/BadLTV)) | Q11: =MIN(1,MAX(0,M11/BadQuality)) | R11: =MIN(1,MAX(0,(N11-1)/4)) | S11: =MIN(1,MAX(0,F11/BadSpend)) | T11: =O11*wLate | U11: =P11*wLTV | V11: =Q11*wQuality | W11: =R11*wCountry | X11: =S11*wSpend | Y11: =ROUND(SUM(T11:X11)*100,1) | Z11: =IF(Y11>60,"High",IF(Y11>35,"Medium","Low")) | AA11: =INDEX($T$4:$X$4,MATCH(MAX(T11:X11),T11:X11,0)) | AB11: =IF(AND(Z11="Low",F11>=0.25),"Reliable, but holds a large share of spend: keep as primary and qualify a backup supplier for its A-class SKUs",IF(Z11="Low","Maintain; candidate for volume consolidation / preferred-supplier status",IF(Z11="High","Priority: ","")&INDEX(DriverAction,MATCH(AA11,DriverList,0)))) | AC11: =RANK(Y11,$Y$5:$Y$12)
A12: =Suppliers!A9 | B12: =Suppliers!B9 | C12: =Suppliers!C9 | D12: =COUNTIF(PO_Sup,A12) | E12: =SUMIF(PO_Sup,A12,PO_Value) | F12: =IFERROR(E12/SUM($E$5:$E$12),0) | G12: =IFERROR(AVERAGEIF(PO_Sup,A12,PO_OnTime),0) | H12: =IFERROR(AVERAGEIF(PO_Sup,A12,PO_DaysLate),0) | I12: =IFERROR(AVERAGEIF(PO_Sup,A12,PO_LT),0) | J12: =IFERROR(SQRT(MAX(0,(SUMIF(PO_Sup,A12,PO_LT2)-D12*I12^2)/(D12-1))),0) | K12: =IFERROR(J12/I12,0) | L12: =IFERROR(SUMIF(PO_Sup,A12,PO_QtyRec)/SUMIF(PO_Sup,A12,PO_QtyOrd),0) | M12: =IFERROR(SUMIF(PO_Sup,A12,PO_QtyDef)/SUMIF(PO_Sup,A12,PO_QtyRec),0) | N12: =IFERROR(INDEX(CountryScore,MATCH(C12,CountryList,0)),3) | O12: =MIN(1,MAX(0,(1-G12)/BadLate)) | P12: =MIN(1,MAX(0,K12/BadLTV)) | Q12: =MIN(1,MAX(0,M12/BadQuality)) | R12: =MIN(1,MAX(0,(N12-1)/4)) | S12: =MIN(1,MAX(0,F12/BadSpend)) | T12: =O12*wLate | U12: =P12*wLTV | V12: =Q12*wQuality | W12: =R12*wCountry | X12: =S12*wSpend | Y12: =ROUND(SUM(T12:X12)*100,1) | Z12: =IF(Y12>60,"High",IF(Y12>35,"Medium","Low")) | AA12: =INDEX($T$4:$X$4,MATCH(MAX(T12:X12),T12:X12,0)) | AB12: =IF(AND(Z12="Low",F12>=0.25),"Reliable, but holds a large share of spend: keep as primary and qualify a backup supplier for its A-class SKUs",IF(Z12="Low","Maintain; candidate for volume consolidation / preferred-supplier status",IF(Z12="High","Priority: ","")&INDEX(DriverAction,MATCH(AA12,DriverList,0)))) | AC12: =RANK(Y12,$Y$5:$Y$12)

Sheet Forecast
A1: Demand Forecast Back-test (one SKU at a time)
A2: Pick a SKU. Three methods forecast each week one step ahead; accuracy (WAPE) is measured on the last 12 weeks.
A4: SKU (pick from list) | B4: NB-0001
A5: Product | B5: =IFERROR(INDEX(P_Name,MATCH(FcSKU,P_SKU,0)),"")
A6: Smoothing factor alpha (0-1) | B6: 0.3
A7: Test window (weeks) | B7: 12
A9: Accuracy on last 12 weeks
A10: Moving avg (4w) | B10: =IFERROR(SUMPRODUCT(ABS($C$109:$C$120-D109:D120))/SUM($C$109:$C$120),0) | C10: WAPE = sum(|actual - forecast|) / sum(actual)
A11: Exp. smoothing | B11: =IFERROR(SUMPRODUCT(ABS($C$109:$C$120-F109:F120))/SUM($C$109:$C$120),0)
A12: Seasonal naive | B12: =IFERROR(SUMPRODUCT(ABS($C$109:$C$120-G109:G120))/SUM($C$109:$C$120),0)
A13: Best method (lowest WAPE) | B13: =INDEX(A10:A12,MATCH(MIN(B10:B12),B10:B12,0))
A14: Next 12 weeks, best method (units) | B14: =SUM(H121:H132)
A15: Best method index (1-3) | B15: =MATCH(MIN(B10:B12),B10:B12,0)
A16: Week # | B16: Week start | C16: Actual units | D16: Moving avg (4w) | E16: SES level | F16: Exp. smoothing | G16: Seasonal naive | H16: Best method
A17: 1 | B17: 45292 | C17: =SUMIFS(D_Units,D_SKU,FcSKU,D_Week,B17) | E17: =C17
A18: 2 | B18: 45299 | C18: =SUMIFS(D_Units,D_SKU,FcSKU,D_Week,B18) | E18: =Alpha*C18+(1-Alpha)*E17 | F18: =E17
A19: 3 | B19: 45306 | C19: =SUMIFS(D_Units,D_SKU,FcSKU,D_Week,B19) | E19: =Alpha*C19+(1-Alpha)*E18 | F19: =E18
A20: 4 | B20: 45313 | C20: =SUMIFS(D_Units,D_SKU,FcSKU,D_Week,B20) | E20: =Alpha*C20+(1-Alpha)*E19 | F20: =E19
A21: 5 | B21: 45320 | C21: =SUMIFS(D_Units,D_SKU,FcSKU,D_Week,B21) | D21: =AVERAGE(C17:C20) | E21: =Alpha*C21+(1-Alpha)*E20 | F21: =E20
A22: 6 | B22: 45327 | C22: =SUMIFS(D_Units,D_SKU,FcSKU,D_Week,B22) | D22: =AVERAGE(C18:C21) | E22: =Alpha*C22+(1-Alpha)*E21 | F22: =E21
A23: 7 | B23: 45334 | C23: =SUMIFS(D_Units,D_SKU,FcSKU,D_Week,B23) | D23: =AVERAGE(C19:C22) | E23: =Alpha*C23+(1-Alpha)*E22 | F23: =E22
A24: 8 | B24: 45341 | C24: =SUMIFS(D_Units,D_SKU,FcSKU,D_Week,B24) | D24: =AVERAGE(C20:C23) | E24: =Alpha*C24+(1-Alpha)*E23 | F24: =E23
A25: 9 | B25: 45348 | C25: =SUMIFS(D_Units,D_SKU,FcSKU,D_Week,B25) | D25: =AVERAGE(C21:C24) | E25: =Alpha*C25+(1-Alpha)*E24 | F25: =E24
A26: 10 | B26: 45355 | C26: =SUMIFS(D_Units,D_SKU,FcSKU,D_Week,B26) | D26: =AVERAGE(C22:C25) | E26: =Alpha*C26+(1-Alpha)*E25 | F26: =E25
A27: 11 | B27: 45362 | C27: =SUMIFS(D_Units,D_SKU,FcSKU,D_Week,B27) | D27: =AVERAGE(C23:C26) | E27: =Alpha*C27+(1-Alpha)*E26 | F27: =E26
A28: 12 | B28: 45369 | C28: =SUMIFS(D_Units,D_SKU,FcSKU,D_Week,B28) | D28: =AVERAGE(C24:C27) | E28: =Alpha*C28+(1-Alpha)*E27 | F28: =E27
A29: 13 | B29: 45376 | C29: =SUMIFS(D_Units,D_SKU,FcSKU,D_Week,B29) | D29: =AVERAGE(C25:C28) | E29: =Alpha*C29+(1-Alpha)*E28 | F29: =E28
A30: 14 | B30: 45383 | C30: =SUMIFS(D_Units,D_SKU,FcSKU,D_Week,B30) | D30: =AVERAGE(C26:C29) | E30: =Alpha*C30+(1-Alpha)*E29 | F30: =E29
A31: 15 | B31: 45390 | C31: =SUMIFS(D_Units,D_SKU,FcSKU,D_Week,B31) | D31: =AVERAGE(C27:C30) | E31: =Alpha*C31+(1-Alpha)*E30 | F31: =E30
A32: 16 | B32: 45397 | C32: =SUMIFS(D_Units,D_SKU,FcSKU,D_Week,B32) | D32: =AVERAGE(C28:C31) | E32: =Alpha*C32+(1-Alpha)*E31 | F32: =E31
... A68: 52 | B68: 45649 | C68: =SUMIFS(D_Units,D_SKU,FcSKU,D_Week,B68) | D68: =AVERAGE(C64:C67) | E68: =Alpha*C68+(1-Alpha)*E67 | F68: =E67
A69: 53 | B69: 45656 | C69: =SUMIFS(D_Units,D_SKU,FcSKU,D_Week,B69) | D69: =AVERAGE(C65:C68) | E69: =Alpha*C69+(1-Alpha)*E68 | F69: =E68 | G69: =C17
A70: 54 | B70: 45663 | C70: =SUMIFS(D_Units,D_SKU,FcSKU,D_Week,B70) | D70: =AVERAGE(C66:C69) | E70: =Alpha*C70+(1-Alpha)*E69 | F70: =E69 | G70: =C18
A71: 55 | B71: 45670 | C71: =SUMIFS(D_Units,D_SKU,FcSKU,D_Week,B71) | D71: =AVERAGE(C67:C70) | E71: =Alpha*C71+(1-Alpha)*E70 | F71: =E70 | G71: =C19
A72: 56 | B72: 45677 | C72: =SUMIFS(D_Units,D_SKU,FcSKU,D_Week,B72) | D72: =AVERAGE(C68:C71) | E72: =Alpha*C72+(1-Alpha)*E71 | F72: =E71 | G72: =C20
A73: 57 | B73: 45684 | C73: =SUMIFS(D_Units,D_SKU,FcSKU,D_Week,B73) | D73: =AVERAGE(C69:C72) | E73: =Alpha*C73+(1-Alpha)*E72 | F73: =E72 | G73: =C21
A74: 58 | B74: 45691 | C74: =SUMIFS(D_Units,D_SKU,FcSKU,D_Week,B74) | D74: =AVERAGE(C70:C73) | E74: =Alpha*C74+(1-Alpha)*E73 | F74: =E73 | G74: =C22
A75: 59 | B75: 45698 | C75: =SUMIFS(D_Units,D_SKU,FcSKU,D_Week,B75) | D75: =AVERAGE(C71:C74) | E75: =Alpha*C75+(1-Alpha)*E74 | F75: =E74 | G75: =C23
A76: 60 | B76: 45705 | C76: =SUMIFS(D_Units,D_SKU,FcSKU,D_Week,B76) | D76: =AVERAGE(C72:C75) | E76: =Alpha*C76+(1-Alpha)*E75 | F76: =E75 | G76: =C24
A77: 61 | B77: 45712 | C77: =SUMIFS(D_Units,D_SKU,FcSKU,D_Week,B77) | D77: =AVERAGE(C73:C76) | E77: =Alpha*C77+(1-Alpha)*E76 | F77: =E76 | G77: =C25
A78: 62 | B78: 45719 | C78: =SUMIFS(D_Units,D_SKU,FcSKU,D_Week,B78) | D78: =AVERAGE(C74:C77) | E78: =Alpha*C78+(1-Alpha)*E77 | F78: =E77 | G78: =C26
A79: 63 | B79: 45726 | C79: =SUMIFS(D_Units,D_SKU,FcSKU,D_Week,B79) | D79: =AVERAGE(C75:C78) | E79: =Alpha*C79+(1-Alpha)*E78 | F79: =E78 | G79: =C27
A80: 64 | B80: 45733 | C80: =SUMIFS(D_Units,D_SKU,FcSKU,D_Week,B80) | D80: =AVERAGE(C76:C79) | E80: =Alpha*C80+(1-Alpha)*E79 | F80: =E79 | G80: =C28
... A108: 92 | B108: 45929 | C108: =SUMIFS(D_Units,D_SKU,FcSKU,D_Week,B108) | D108: =AVERAGE(C104:C107) | E108: =Alpha*C108+(1-Alpha)*E107 | F108: =E107 | G108: =C56
A109: 93 | B109: 45936 | C109: =SUMIFS(D_Units,D_SKU,FcSKU,D_Week,B109) | D109: =AVERAGE(C105:C108) | E109: =Alpha*C109+(1-Alpha)*E108 | F109: =E108 | G109: =C57 | H109: =IF(k_best=1,D109,IF(k_best=2,F109,G109))
A110: 94 | B110: 45943 | C110: =SUMIFS(D_Units,D_SKU,FcSKU,D_Week,B110) | D110: =AVERAGE(C106:C109) | E110: =Alpha*C110+(1-Alpha)*E109 | F110: =E109 | G110: =C58 | H110: =IF(k_best=1,D110,IF(k_best=2,F110,G110))
A111: 95 | B111: 45950 | C111: =SUMIFS(D_Units,D_SKU,FcSKU,D_Week,B111) | D111: =AVERAGE(C107:C110) | E111: =Alpha*C111+(1-Alpha)*E110 | F111: =E110 | G111: =C59 | H111: =IF(k_best=1,D111,IF(k_best=2,F111,G111))
A112: 96 | B112: 45957 | C112: =SUMIFS(D_Units,D_SKU,FcSKU,D_Week,B112) | D112: =AVERAGE(C108:C111) | E112: =Alpha*C112+(1-Alpha)*E111 | F112: =E111 | G112: =C60 | H112: =IF(k_best=1,D112,IF(k_best=2,F112,G112))
A113: 97 | B113: 45964 | C113: =SUMIFS(D_Units,D_SKU,FcSKU,D_Week,B113) | D113: =AVERAGE(C109:C112) | E113: =Alpha*C113+(1-Alpha)*E112 | F113: =E112 | G113: =C61 | H113: =IF(k_best=1,D113,IF(k_best=2,F113,G113))
A114: 98 | B114: 45971 | C114: =SUMIFS(D_Units,D_SKU,FcSKU,D_Week,B114) | D114: =AVERAGE(C110:C113) | E114: =Alpha*C114+(1-Alpha)*E113 | F114: =E113 | G114: =C62 | H114: =IF(k_best=1,D114,IF(k_best=2,F114,G114))
A115: 99 | B115: 45978 | C115: =SUMIFS(D_Units,D_SKU,FcSKU,D_Week,B115) | D115: =AVERAGE(C111:C114) | E115: =Alpha*C115+(1-Alpha)*E114 | F115: =E114 | G115: =C63 | H115: =IF(k_best=1,D115,IF(k_best=2,F115,G115))
A116: 100 | B116: 45985 | C116: =SUMIFS(D_Units,D_SKU,FcSKU,D_Week,B116) | D116: =AVERAGE(C112:C115) | E116: =Alpha*C116+(1-Alpha)*E115 | F116: =E115 | G116: =C64 | H116: =IF(k_best=1,D116,IF(k_best=2,F116,G116))
A117: 101 | B117: 45992 | C117: =SUMIFS(D_Units,D_SKU,FcSKU,D_Week,B117) | D117: =AVERAGE(C113:C116) | E117: =Alpha*C117+(1-Alpha)*E116 | F117: =E116 | G117: =C65 | H117: =IF(k_best=1,D117,IF(k_best=2,F117,G117))
A118: 102 | B118: 45999 | C118: =SUMIFS(D_Units,D_SKU,FcSKU,D_Week,B118) | D118: =AVERAGE(C114:C117) | E118: =Alpha*C118+(1-Alpha)*E117 | F118: =E117 | G118: =C66 | H118: =IF(k_best=1,D118,IF(k_best=2,F118,G118))
A119: 103 | B119: 46006 | C119: =SUMIFS(D_Units,D_SKU,FcSKU,D_Week,B119) | D119: =AVERAGE(C115:C118) | E119: =Alpha*C119+(1-Alpha)*E118 | F119: =E118 | G119: =C67 | H119: =IF(k_best=1,D119,IF(k_best=2,F119,G119))
A120: 104 | B120: 46013 | C120: =SUMIFS(D_Units,D_SKU,FcSKU,D_Week,B120) | D120: =AVERAGE(C116:C119) | E120: =Alpha*C120+(1-Alpha)*E119 | F120: =E119 | G120: =C68 | H120: =IF(k_best=1,D120,IF(k_best=2,F120,G120)) | I120: <- history ends; shaded rows = 12-week forecast
A121: 105 | B121: =B120+7 | D121: =AVERAGE($C$117:$C$120) | F121: =$E$120 | G121: =C69 | H121: =IF(k_best=1,D121,IF(k_best=2,F121,G121))
A122: 106 | B122: =B121+7 | D122: =AVERAGE($C$117:$C$120) | F122: =$E$120 | G122: =C70 | H122: =IF(k_best=1,D122,IF(k_best=2,F122,G122))
A123: 107 | B123: =B122+7 | D123: =AVERAGE($C$117:$C$120) | F123: =$E$120 | G123: =C71 | H123: =IF(k_best=1,D123,IF(k_best=2,F123,G123))
A124: 108 | B124: =B123+7 | D124: =AVERAGE($C$117:$C$120) | F124: =$E$120 | G124: =C72 | H124: =IF(k_best=1,D124,IF(k_best=2,F124,G124))
A125: 109 | B125: =B124+7 | D125: =AVERAGE($C$117:$C$120) | F125: =$E$120 | G125: =C73 | H125: =IF(k_best=1,D125,IF(k_best=2,F125,G125))
A126: 110 | B126: =B125+7 | D126: =AVERAGE($C$117:$C$120) | F126: =$E$120 | G126: =C74 | H126: =IF(k_best=1,D126,IF(k_best=2,F126,G126))
A127: 111 | B127: =B126+7 | D127: =AVERAGE($C$117:$C$120) | F127: =$E$120 | G127: =C75 | H127: =IF(k_best=1,D127,IF(k_best=2,F127,G127))
A128: 112 | B128: =B127+7 | D128: =AVERAGE($C$117:$C$120) | F128: =$E$120 | G128: =C76 | H128: =IF(k_best=1,D128,IF(k_best=2,F128,G128))
A129: 113 | B129: =B128+7 | D129: =AVERAGE($C$117:$C$120) | F129: =$E$120 | G129: =C77 | H129: =IF(k_best=1,D129,IF(k_best=2,F129,G129))
A130: 114 | B130: =B129+7 | D130: =AVERAGE($C$117:$C$120) | F130: =$E$120 | G130: =C78 | H130: =IF(k_best=1,D130,IF(k_best=2,F130,G130))
A131: 115 | B131: =B130+7 | D131: =AVERAGE($C$117:$C$120) | F131: =$E$120 | G131: =C79 | H131: =IF(k_best=1,D131,IF(k_best=2,F131,G131))
A132: 116 | B132: =B131+7 | D132: =AVERAGE($C$117:$C$120) | F132: =$E$120 | G132: =C80 | H132: =IF(k_best=1,D132,IF(k_best=2,F132,G132))

Sheet Disruption_Simulator
A1: Disruption Simulator
A2: What if a supplier is delayed (port strike, tariff hold, factory shutdown)? Pick a supplier and a delay.
A4: Supplier (pick from list) | B4: S08 | C4: =IFERROR(INDEX(Supplier_Scorecard!$B$5:$B$12,MATCH(B4,SC_ID,0)),"")
A5: Extra delay (weeks) | B5: 4
A7: SKUs that stock out | B7: =COUNTIF(J13:J42,"Stockout")&" of "&COUNTIF(P_Sup,SimSupplier)
A8: Revenue at risk (CAD) | B8: =SUM(L13:L42)
A9: Extra buffer stock to prevent it (CAD) | B9: =SUM(N13:N42)
A12: # | B12: SKU | C12: Product | D12: ABC | E12: Avg weekly demand | F12: On hand + on order | G12: Weeks of stock | H12: Lead time (wks) | I12: New lead time | J12: Outcome | K12: Units short | L12: Revenue at risk (CAD) | M12: Buffer units | N12: Buffer cost (CAD) | O12: row
A13: 1 | B13: =IF(O13="","",INDEX(P_SKU,O13)) | C13: =IF(O13="","",INDEX(P_Name,O13)) | D13: =IF(O13="","",INDEX(P_ABC,O13)) | E13: =IF(O13="","",INDEX(P_Demand,O13)) | F13: =IF(O13="","",INDEX(P_Pos,O13)) | G13: =IF(O13="","",IFERROR(F13/E13,999)) | H13: =IF(O13="","",INDEX(P_LT,O13)) | I13: =IF(O13="","",H13+SimDelay) | J13: =IF(O13="","",IF(I13>G13,"Stockout","Covered")) | K13: =IF(O13="","",ROUNDUP(MAX(0,I13-G13)*E13,0)) | L13: =IF(O13="","",K13*INDEX(P_Cost,O13)*Markup) | M13: =IF(O13="","",ROUNDUP(E13*SimDelay,0)) | N13: =IF(O13="","",M13*INDEX(P_Cost,O13)) | O13: =IFERROR(MATCH(A13,P_SimRow,0),"")
A14: 2 | B14: =IF(O14="","",INDEX(P_SKU,O14)) | C14: =IF(O14="","",INDEX(P_Name,O14)) | D14: =IF(O14="","",INDEX(P_ABC,O14)) | E14: =IF(O14="","",INDEX(P_Demand,O14)) | F14: =IF(O14="","",INDEX(P_Pos,O14)) | G14: =IF(O14="","",IFERROR(F14/E14,999)) | H14: =IF(O14="","",INDEX(P_LT,O14)) | I14: =IF(O14="","",H14+SimDelay) | J14: =IF(O14="","",IF(I14>G14,"Stockout","Covered")) | K14: =IF(O14="","",ROUNDUP(MAX(0,I14-G14)*E14,0)) | L14: =IF(O14="","",K14*INDEX(P_Cost,O14)*Markup) | M14: =IF(O14="","",ROUNDUP(E14*SimDelay,0)) | N14: =IF(O14="","",M14*INDEX(P_Cost,O14)) | O14: =IFERROR(MATCH(A14,P_SimRow,0),"")
A15: 3 | B15: =IF(O15="","",INDEX(P_SKU,O15)) | C15: =IF(O15="","",INDEX(P_Name,O15)) | D15: =IF(O15="","",INDEX(P_ABC,O15)) | E15: =IF(O15="","",INDEX(P_Demand,O15)) | F15: =IF(O15="","",INDEX(P_Pos,O15)) | G15: =IF(O15="","",IFERROR(F15/E15,999)) | H15: =IF(O15="","",INDEX(P_LT,O15)) | I15: =IF(O15="","",H15+SimDelay) | J15: =IF(O15="","",IF(I15>G15,"Stockout","Covered")) | K15: =IF(O15="","",ROUNDUP(MAX(0,I15-G15)*E15,0)) | L15: =IF(O15="","",K15*INDEX(P_Cost,O15)*Markup) | M15: =IF(O15="","",ROUNDUP(E15*SimDelay,0)) | N15: =IF(O15="","",M15*INDEX(P_Cost,O15)) | O15: =IFERROR(MATCH(A15,P_SimRow,0),"")
A16: 4 | B16: =IF(O16="","",INDEX(P_SKU,O16)) | C16: =IF(O16="","",INDEX(P_Name,O16)) | D16: =IF(O16="","",INDEX(P_ABC,O16)) | E16: =IF(O16="","",INDEX(P_Demand,O16)) | F16: =IF(O16="","",INDEX(P_Pos,O16)) | G16: =IF(O16="","",IFERROR(F16/E16,999)) | H16: =IF(O16="","",INDEX(P_LT,O16)) | I16: =IF(O16="","",H16+SimDelay) | J16: =IF(O16="","",IF(I16>G16,"Stockout","Covered")) | K16: =IF(O16="","",ROUNDUP(MAX(0,I16-G16)*E16,0)) | L16: =IF(O16="","",K16*INDEX(P_Cost,O16)*Markup) | M16: =IF(O16="","",ROUNDUP(E16*SimDelay,0)) | N16: =IF(O16="","",M16*INDEX(P_Cost,O16)) | O16: =IFERROR(MATCH(A16,P_SimRow,0),"")
A17: 5 | B17: =IF(O17="","",INDEX(P_SKU,O17)) | C17: =IF(O17="","",INDEX(P_Name,O17)) | D17: =IF(O17="","",INDEX(P_ABC,O17)) | E17: =IF(O17="","",INDEX(P_Demand,O17)) | F17: =IF(O17="","",INDEX(P_Pos,O17)) | G17: =IF(O17="","",IFERROR(F17/E17,999)) | H17: =IF(O17="","",INDEX(P_LT,O17)) | I17: =IF(O17="","",H17+SimDelay) | J17: =IF(O17="","",IF(I17>G17,"Stockout","Covered")) | K17: =IF(O17="","",ROUNDUP(MAX(0,I17-G17)*E17,0)) | L17: =IF(O17="","",K17*INDEX(P_Cost,O17)*Markup) | M17: =IF(O17="","",ROUNDUP(E17*SimDelay,0)) | N17: =IF(O17="","",M17*INDEX(P_Cost,O17)) | O17: =IFERROR(MATCH(A17,P_SimRow,0),"")
A18: 6 | B18: =IF(O18="","",INDEX(P_SKU,O18)) | C18: =IF(O18="","",INDEX(P_Name,O18)) | D18: =IF(O18="","",INDEX(P_ABC,O18)) | E18: =IF(O18="","",INDEX(P_Demand,O18)) | F18: =IF(O18="","",INDEX(P_Pos,O18)) | G18: =IF(O18="","",IFERROR(F18/E18,999)) | H18: =IF(O18="","",INDEX(P_LT,O18)) | I18: =IF(O18="","",H18+SimDelay) | J18: =IF(O18="","",IF(I18>G18,"Stockout","Covered")) | K18: =IF(O18="","",ROUNDUP(MAX(0,I18-G18)*E18,0)) | L18: =IF(O18="","",K18*INDEX(P_Cost,O18)*Markup) | M18: =IF(O18="","",ROUNDUP(E18*SimDelay,0)) | N18: =IF(O18="","",M18*INDEX(P_Cost,O18)) | O18: =IFERROR(MATCH(A18,P_SimRow,0),"")
A19: 7 | B19: =IF(O19="","",INDEX(P_SKU,O19)) | C19: =IF(O19="","",INDEX(P_Name,O19)) | D19: =IF(O19="","",INDEX(P_ABC,O19)) | E19: =IF(O19="","",INDEX(P_Demand,O19)) | F19: =IF(O19="","",INDEX(P_Pos,O19)) | G19: =IF(O19="","",IFERROR(F19/E19,999)) | H19: =IF(O19="","",INDEX(P_LT,O19)) | I19: =IF(O19="","",H19+SimDelay) | J19: =IF(O19="","",IF(I19>G19,"Stockout","Covered")) | K19: =IF(O19="","",ROUNDUP(MAX(0,I19-G19)*E19,0)) | L19: =IF(O19="","",K19*INDEX(P_Cost,O19)*Markup) | M19: =IF(O19="","",ROUNDUP(E19*SimDelay,0)) | N19: =IF(O19="","",M19*INDEX(P_Cost,O19)) | O19: =IFERROR(MATCH(A19,P_SimRow,0),"")
A20: 8 | B20: =IF(O20="","",INDEX(P_SKU,O20)) | C20: =IF(O20="","",INDEX(P_Name,O20)) | D20: =IF(O20="","",INDEX(P_ABC,O20)) | E20: =IF(O20="","",INDEX(P_Demand,O20)) | F20: =IF(O20="","",INDEX(P_Pos,O20)) | G20: =IF(O20="","",IFERROR(F20/E20,999)) | H20: =IF(O20="","",INDEX(P_LT,O20)) | I20: =IF(O20="","",H20+SimDelay) | J20: =IF(O20="","",IF(I20>G20,"Stockout","Covered")) | K20: =IF(O20="","",ROUNDUP(MAX(0,I20-G20)*E20,0)) | L20: =IF(O20="","",K20*INDEX(P_Cost,O20)*Markup) | M20: =IF(O20="","",ROUNDUP(E20*SimDelay,0)) | N20: =IF(O20="","",M20*INDEX(P_Cost,O20)) | O20: =IFERROR(MATCH(A20,P_SimRow,0),"")
A21: 9 | B21: =IF(O21="","",INDEX(P_SKU,O21)) | C21: =IF(O21="","",INDEX(P_Name,O21)) | D21: =IF(O21="","",INDEX(P_ABC,O21)) | E21: =IF(O21="","",INDEX(P_Demand,O21)) | F21: =IF(O21="","",INDEX(P_Pos,O21)) | G21: =IF(O21="","",IFERROR(F21/E21,999)) | H21: =IF(O21="","",INDEX(P_LT,O21)) | I21: =IF(O21="","",H21+SimDelay) | J21: =IF(O21="","",IF(I21>G21,"Stockout","Covered")) | K21: =IF(O21="","",ROUNDUP(MAX(0,I21-G21)*E21,0)) | L21: =IF(O21="","",K21*INDEX(P_Cost,O21)*Markup) | M21: =IF(O21="","",ROUNDUP(E21*SimDelay,0)) | N21: =IF(O21="","",M21*INDEX(P_Cost,O21)) | O21: =IFERROR(MATCH(A21,P_SimRow,0),"")
A22: 10 | B22: =IF(O22="","",INDEX(P_SKU,O22)) | C22: =IF(O22="","",INDEX(P_Name,O22)) | D22: =IF(O22="","",INDEX(P_ABC,O22)) | E22: =IF(O22="","",INDEX(P_Demand,O22)) | F22: =IF(O22="","",INDEX(P_Pos,O22)) | G22: =IF(O22="","",IFERROR(F22/E22,999)) | H22: =IF(O22="","",INDEX(P_LT,O22)) | I22: =IF(O22="","",H22+SimDelay) | J22: =IF(O22="","",IF(I22>G22,"Stockout","Covered")) | K22: =IF(O22="","",ROUNDUP(MAX(0,I22-G22)*E22,0)) | L22: =IF(O22="","",K22*INDEX(P_Cost,O22)*Markup) | M22: =IF(O22="","",ROUNDUP(E22*SimDelay,0)) | N22: =IF(O22="","",M22*INDEX(P_Cost,O22)) | O22: =IFERROR(MATCH(A22,P_SimRow,0),"")
A23: 11 | B23: =IF(O23="","",INDEX(P_SKU,O23)) | C23: =IF(O23="","",INDEX(P_Name,O23)) | D23: =IF(O23="","",INDEX(P_ABC,O23)) | E23: =IF(O23="","",INDEX(P_Demand,O23)) | F23: =IF(O23="","",INDEX(P_Pos,O23)) | G23: =IF(O23="","",IFERROR(F23/E23,999)) | H23: =IF(O23="","",INDEX(P_LT,O23)) | I23: =IF(O23="","",H23+SimDelay) | J23: =IF(O23="","",IF(I23>G23,"Stockout","Covered")) | K23: =IF(O23="","",ROUNDUP(MAX(0,I23-G23)*E23,0)) | L23: =IF(O23="","",K23*INDEX(P_Cost,O23)*Markup) | M23: =IF(O23="","",ROUNDUP(E23*SimDelay,0)) | N23: =IF(O23="","",M23*INDEX(P_Cost,O23)) | O23: =IFERROR(MATCH(A23,P_SimRow,0),"")
A24: 12 | B24: =IF(O24="","",INDEX(P_SKU,O24)) | C24: =IF(O24="","",INDEX(P_Name,O24)) | D24: =IF(O24="","",INDEX(P_ABC,O24)) | E24: =IF(O24="","",INDEX(P_Demand,O24)) | F24: =IF(O24="","",INDEX(P_Pos,O24)) | G24: =IF(O24="","",IFERROR(F24/E24,999)) | H24: =IF(O24="","",INDEX(P_LT,O24)) | I24: =IF(O24="","",H24+SimDelay) | J24: =IF(O24="","",IF(I24>G24,"Stockout","Covered")) | K24: =IF(O24="","",ROUNDUP(MAX(0,I24-G24)*E24,0)) | L24: =IF(O24="","",K24*INDEX(P_Cost,O24)*Markup) | M24: =IF(O24="","",ROUNDUP(E24*SimDelay,0)) | N24: =IF(O24="","",M24*INDEX(P_Cost,O24)) | O24: =IFERROR(MATCH(A24,P_SimRow,0),"")
... A42: 30 | B42: =IF(O42="","",INDEX(P_SKU,O42)) | C42: =IF(O42="","",INDEX(P_Name,O42)) | D42: =IF(O42="","",INDEX(P_ABC,O42)) | E42: =IF(O42="","",INDEX(P_Demand,O42)) | F42: =IF(O42="","",INDEX(P_Pos,O42)) | G42: =IF(O42="","",IFERROR(F42/E42,999)) | H42: =IF(O42="","",INDEX(P_LT,O42)) | I42: =IF(O42="","",H42+SimDelay) | J42: =IF(O42="","",IF(I42>G42,"Stockout","Covered")) | K42: =IF(O42="","",ROUNDUP(MAX(0,I42-G42)*E42,0)) | L42: =IF(O42="","",K42*INDEX(P_Cost,O42)*Markup) | M42: =IF(O42="","",ROUNDUP(E42*SimDelay,0)) | N42: =IF(O42="","",M42*INDEX(P_Cost,O42)) | O42: =IFERROR(MATCH(A42,P_SimRow,0),"")

Sheet Landed_Cost
A1: Logistics & Landed Cost: Offshore vs Nearshore
A2: Total annual landed cost = units x landed unit cost + carrying cost of safety stock and in-transit inventory. Blue-on-yellow cells are inputs.
A4: Country | B4: Price index | C4: Freight % | D4: Duty % | E4: Brokerage % | F4: Region | G4: Landed multiplier | H4: Cost to land 100 | I4: Avg lead time (wks) | K4: Summary
A5: China | B5: 1 | C5: 0.1 | D5: 0.065 | E5: 0.015 | F5: Offshore | G5: =B5*(1+C5+D5+E5) | H5: =100*G5 | I5: =IFERROR(AVERAGEIF(Supplier_Scorecard!$C$5:$C$12,A5,Supplier_Scorecard!$I$5:$I$12),"-") | K5: Offshore SKUs reviewed | N5: =COUNTA(A18:A43)
A6: India | B6: 1 | C6: 0.11 | D6: 0.065 | E6: 0.015 | F6: Offshore | G6: =B6*(1+C6+D6+E6) | H6: =100*G6 | I6: =IFERROR(AVERAGEIF(Supplier_Scorecard!$C$5:$C$12,A6,Supplier_Scorecard!$I$5:$I$12),"-") | K6: Cheaper to source nearshore | N6: =COUNTIF(W18:W43,"Nearshore: lower total cost")
A7: Vietnam | B7: 1.02 | C7: 0.11 | D7: 0 | E7: 0.015 | F7: Offshore | G7: =B7*(1+C7+D7+E7) | H7: =100*G7 | I7: =IFERROR(AVERAGEIF(Supplier_Scorecard!$C$5:$C$12,A7,Supplier_Scorecard!$I$5:$I$12),"-") | K7: Nearshore candidates (incl. small premium) | N7: =COUNTIF(W18:W43,"Nearshore*")
A8: Malaysia | B8: 0.97 | C8: 0.1 | D8: 0 | E8: 0.015 | F8: Offshore | G8: =B8*(1+C8+D8+E8) | H8: =100*G8 | I8: =IFERROR(AVERAGEIF(Supplier_Scorecard!$C$5:$C$12,A8,Supplier_Scorecard!$I$5:$I$12),"-") | K8: Saving/yr if cheaper SKUs move | N8: =SUMIF(T18:T43,">0")
A9: Germany | B9: 1.2 | C9: 0.07 | D9: 0 | E9: 0.01 | F9: Offshore | G9: =B9*(1+C9+D9+E9) | H9: =100*G9 | I9: =IFERROR(AVERAGEIF(Supplier_Scorecard!$C$5:$C$12,A9,Supplier_Scorecard!$I$5:$I$12),"-") | K9: Inventory released if candidates move | N9: =SUMIF(W18:W43,"Nearshore*",V18:V43)
A10: Mexico | B10: 1.18 | C10: 0.045 | D10: 0 | E10: 0.01 | F10: Nearshore | G10: =B10*(1+C10+D10+E10) | H10: =100*G10 | I10: =IFERROR(AVERAGEIF(Supplier_Scorecard!$C$5:$C$12,A10,Supplier_Scorecard!$I$5:$I$12),"-")
A11: USA | B11: 1.38 | C11: 0.03 | D11: 0 | E11: 0.01 | F11: Nearshore | G11: =B11*(1+C11+D11+E11) | H11: =100*G11 | I11: =IFERROR(AVERAGEIF(Supplier_Scorecard!$C$5:$C$12,A11,Supplier_Scorecard!$I$5:$I$12),"-")
A12: Canada | B12: 1.45 | C12: 0.015 | D12: 0 | E12: 0 | F12: Domestic | G12: =B12*(1+C12+D12+E12) | H12: =100*G12 | I12: =IFERROR(AVERAGEIF(Supplier_Scorecard!$C$5:$C$12,A12,Supplier_Scorecard!$I$5:$I$12),"-")
A13: Duty rates are illustrative (CUSMA, CETA, CPTPP). Check the Canada Customs Tariff for real HS codes.
A14: Accept nearshore premium up to | B14: 0.03
A16: Comparison for every SKU bought offshore
A17: SKU | B17: Product | C17: Supplier | D17: Country | E17: Weekly demand | F17: Demand std | G17: Unit cost now | H17: Base price | I17: Now: landed unit | J17: Now: inventory value | K17: Now: total/yr | L17: Mexico: total/yr | M17: Mexico: inventory value | N17: USA: total/yr | O17: USA: inventory value | P17: Canada: total/yr | Q17: Canada: inventory value | R17: Best nearshore | S17: Best nearshore total/yr | T17: Saving/yr | U17: Saving % | V17: Inventory released | W17: Recommendation | X17: row
A18: =INDEX(P_SKU,$X18) | B18: =INDEX(P_Name,$X18) | C18: =INDEX(P_Sup,$X18) | D18: =INDEX(Supplier_Scorecard!$C$5:$C$12,MATCH(C18,SC_ID,0)) | E18: =INDEX(P_Demand,$X18) | F18: =INDEX(P_Std,$X18) | G18: =INDEX(P_Cost,$X18) | H18: =G18/INDEX(LC_Price,MATCH(D18,LC_Country,0)) | I18: =H18*INDEX(LC_Mult,MATCH(D18,LC_Country,0)) | J18: =(z*SQRT(INDEX(SC_LT,MATCH(C18,SC_ID,0))*F18^2+E18^2*INDEX(SC_LTStd,MATCH(C18,SC_ID,0))^2)+E18*INDEX(SC_LT,MATCH(C18,SC_ID,0)))*I18 | K18: =E18*WeeksYear*I18+(z*SQRT(INDEX(SC_LT,MATCH(C18,SC_ID,0))*F18^2+E18^2*INDEX(SC_LTStd,MATCH(C18,SC_ID,0))^2)+E18*INDEX(SC_LT,MATCH(C18,SC_ID,0)))*I18*HoldRate | L18: =IFERROR(E18*WeeksYear*(H18*INDEX(LC_Mult,MATCH("Mexico",LC_Country,0)))+(z*SQRT(INDEX(SC_LT,MATCH("S04",SC_ID,0))*F18^2+E18^2*INDEX(SC_LTStd,MATCH("S04",SC_ID,0))^2)+E18*INDEX(SC_LT,MATCH("S04",SC_ID,0)))*(H18*INDEX(LC_Mult,MATCH("Mexico",LC_Country,0)))*HoldRate,9.99E+99) | M18: =IFERROR((z*SQRT(INDEX(SC_LT,MATCH("S04",SC_ID,0))*F18^2+E18^2*INDEX(SC_LTStd,MATCH("S04",SC_ID,0))^2)+E18*INDEX(SC_LT,MATCH("S04",SC_ID,0)))*(H18*INDEX(LC_Mult,MATCH("Mexico",LC_Country,0))),0) | N18: =IFERROR(E18*WeeksYear*(H18*INDEX(LC_Mult,MATCH("USA",LC_Country,0)))+(z*SQRT(INDEX(SC_LT,MATCH("S02",SC_ID,0))*F18^2+E18^2*INDEX(SC_LTStd,MATCH("S02",SC_ID,0))^2)+E18*INDEX(SC_LT,MATCH("S02",SC_ID,0)))*(H18*INDEX(LC_Mult,MATCH("USA",LC_Country,0)))*HoldRate,9.99E+99) | O18: =IFERROR((z*SQRT(INDEX(SC_LT,MATCH("S02",SC_ID,0))*F18^2+E18^2*INDEX(SC_LTStd,MATCH("S02",SC_ID,0))^2)+E18*INDEX(SC_LT,MATCH("S02",SC_ID,0)))*(H18*INDEX(LC_Mult,MATCH("USA",LC_Country,0))),0) | P18: =IFERROR(E18*WeeksYear*(H18*INDEX(LC_Mult,MATCH("Canada",LC_Country,0)))+(z*SQRT(INDEX(SC_LT,MATCH("S01",SC_ID,0))*F18^2+E18^2*INDEX(SC_LTStd,MATCH("S01",SC_ID,0))^2)+E18*INDEX(SC_LT,MATCH("S01",SC_ID,0)))*(H18*INDEX(LC_Mult,MATCH("Canada",LC_Country,0)))*HoldRate,9.99E+99) | Q18: =IFERROR((z*SQRT(INDEX(SC_LT,MATCH("S01",SC_ID,0))*F18^2+E18^2*INDEX(SC_LTStd,MATCH("S01",SC_ID,0))^2)+E18*INDEX(SC_LT,MATCH("S01",SC_ID,0)))*(H18*INDEX(LC_Mult,MATCH("Canada",LC_Country,0))),0) | R18: =IF(L18=MIN(L18,N18,P18),"Mexico",IF(N18=MIN(L18,N18,P18),"USA","Canada")) | S18: =MIN(L18,N18,P18) | T18: =K18-S18 | U18: =IFERROR(T18/K18,0) | V18: =J18-IF(L18=MIN(L18,N18,P18),M18,IF(N18=MIN(L18,N18,P18),O18,Q18)) | W18: =IF(T18>0,"Nearshore: lower total cost",IF(U18>=-LC_Premium,"Nearshore candidate: small premium for resilience","Keep offshore")) | X18: =MATCH("NB-0001",P_SKU,0)
A19: =INDEX(P_SKU,$X19) | B19: =INDEX(P_Name,$X19) | C19: =INDEX(P_Sup,$X19) | D19: =INDEX(Supplier_Scorecard!$C$5:$C$12,MATCH(C19,SC_ID,0)) | E19: =INDEX(P_Demand,$X19) | F19: =INDEX(P_Std,$X19) | G19: =INDEX(P_Cost,$X19) | H19: =G19/INDEX(LC_Price,MATCH(D19,LC_Country,0)) | I19: =H19*INDEX(LC_Mult,MATCH(D19,LC_Country,0)) | J19: =(z*SQRT(INDEX(SC_LT,MATCH(C19,SC_ID,0))*F19^2+E19^2*INDEX(SC_LTStd,MATCH(C19,SC_ID,0))^2)+E19*INDEX(SC_LT,MATCH(C19,SC_ID,0)))*I19 | K19: =E19*WeeksYear*I19+(z*SQRT(INDEX(SC_LT,MATCH(C19,SC_ID,0))*F19^2+E19^2*INDEX(SC_LTStd,MATCH(C19,SC_ID,0))^2)+E19*INDEX(SC_LT,MATCH(C19,SC_ID,0)))*I19*HoldRate | L19: =IFERROR(E19*WeeksYear*(H19*INDEX(LC_Mult,MATCH("Mexico",LC_Country,0)))+(z*SQRT(INDEX(SC_LT,MATCH("S04",SC_ID,0))*F19^2+E19^2*INDEX(SC_LTStd,MATCH("S04",SC_ID,0))^2)+E19*INDEX(SC_LT,MATCH("S04",SC_ID,0)))*(H19*INDEX(LC_Mult,MATCH("Mexico",LC_Country,0)))*HoldRate,9.99E+99) | M19: =IFERROR((z*SQRT(INDEX(SC_LT,MATCH("S04",SC_ID,0))*F19^2+E19^2*INDEX(SC_LTStd,MATCH("S04",SC_ID,0))^2)+E19*INDEX(SC_LT,MATCH("S04",SC_ID,0)))*(H19*INDEX(LC_Mult,MATCH("Mexico",LC_Country,0))),0) | N19: =IFERROR(E19*WeeksYear*(H19*INDEX(LC_Mult,MATCH("USA",LC_Country,0)))+(z*SQRT(INDEX(SC_LT,MATCH("S02",SC_ID,0))*F19^2+E19^2*INDEX(SC_LTStd,MATCH("S02",SC_ID,0))^2)+E19*INDEX(SC_LT,MATCH("S02",SC_ID,0)))*(H19*INDEX(LC_Mult,MATCH("USA",LC_Country,0)))*HoldRate,9.99E+99) | O19: =IFERROR((z*SQRT(INDEX(SC_LT,MATCH("S02",SC_ID,0))*F19^2+E19^2*INDEX(SC_LTStd,MATCH("S02",SC_ID,0))^2)+E19*INDEX(SC_LT,MATCH("S02",SC_ID,0)))*(H19*INDEX(LC_Mult,MATCH("USA",LC_Country,0))),0) | P19: =IFERROR(E19*WeeksYear*(H19*INDEX(LC_Mult,MATCH("Canada",LC_Country,0)))+(z*SQRT(INDEX(SC_LT,MATCH("S01",SC_ID,0))*F19^2+E19^2*INDEX(SC_LTStd,MATCH("S01",SC_ID,0))^2)+E19*INDEX(SC_LT,MATCH("S01",SC_ID,0)))*(H19*INDEX(LC_Mult,MATCH("Canada",LC_Country,0)))*HoldRate,9.99E+99) | Q19: =IFERROR((z*SQRT(INDEX(SC_LT,MATCH("S01",SC_ID,0))*F19^2+E19^2*INDEX(SC_LTStd,MATCH("S01",SC_ID,0))^2)+E19*INDEX(SC_LT,MATCH("S01",SC_ID,0)))*(H19*INDEX(LC_Mult,MATCH("Canada",LC_Country,0))),0) | R19: =IF(L19=MIN(L19,N19,P19),"Mexico",IF(N19=MIN(L19,N19,P19),"USA","Canada")) | S19: =MIN(L19,N19,P19) | T19: =K19-S19 | U19: =IFERROR(T19/K19,0) | V19: =J19-IF(L19=MIN(L19,N19,P19),M19,IF(N19=MIN(L19,N19,P19),O19,Q19)) | W19: =IF(T19>0,"Nearshore: lower total cost",IF(U19>=-LC_Premium,"Nearshore candidate: small premium for resilience","Keep offshore")) | X19: =MATCH("NB-0002",P_SKU,0)
A20: =INDEX(P_SKU,$X20) | B20: =INDEX(P_Name,$X20) | C20: =INDEX(P_Sup,$X20) | D20: =INDEX(Supplier_Scorecard!$C$5:$C$12,MATCH(C20,SC_ID,0)) | E20: =INDEX(P_Demand,$X20) | F20: =INDEX(P_Std,$X20) | G20: =INDEX(P_Cost,$X20) | H20: =G20/INDEX(LC_Price,MATCH(D20,LC_Country,0)) | I20: =H20*INDEX(LC_Mult,MATCH(D20,LC_Country,0)) | J20: =(z*SQRT(INDEX(SC_LT,MATCH(C20,SC_ID,0))*F20^2+E20^2*INDEX(SC_LTStd,MATCH(C20,SC_ID,0))^2)+E20*INDEX(SC_LT,MATCH(C20,SC_ID,0)))*I20 | K20: =E20*WeeksYear*I20+(z*SQRT(INDEX(SC_LT,MATCH(C20,SC_ID,0))*F20^2+E20^2*INDEX(SC_LTStd,MATCH(C20,SC_ID,0))^2)+E20*INDEX(SC_LT,MATCH(C20,SC_ID,0)))*I20*HoldRate | L20: =IFERROR(E20*WeeksYear*(H20*INDEX(LC_Mult,MATCH("Mexico",LC_Country,0)))+(z*SQRT(INDEX(SC_LT,MATCH("S04",SC_ID,0))*F20^2+E20^2*INDEX(SC_LTStd,MATCH("S04",SC_ID,0))^2)+E20*INDEX(SC_LT,MATCH("S04",SC_ID,0)))*(H20*INDEX(LC_Mult,MATCH("Mexico",LC_Country,0)))*HoldRate,9.99E+99) | M20: =IFERROR((z*SQRT(INDEX(SC_LT,MATCH("S04",SC_ID,0))*F20^2+E20^2*INDEX(SC_LTStd,MATCH("S04",SC_ID,0))^2)+E20*INDEX(SC_LT,MATCH("S04",SC_ID,0)))*(H20*INDEX(LC_Mult,MATCH("Mexico",LC_Country,0))),0) | N20: =IFERROR(E20*WeeksYear*(H20*INDEX(LC_Mult,MATCH("USA",LC_Country,0)))+(z*SQRT(INDEX(SC_LT,MATCH("S02",SC_ID,0))*F20^2+E20^2*INDEX(SC_LTStd,MATCH("S02",SC_ID,0))^2)+E20*INDEX(SC_LT,MATCH("S02",SC_ID,0)))*(H20*INDEX(LC_Mult,MATCH("USA",LC_Country,0)))*HoldRate,9.99E+99) | O20: =IFERROR((z*SQRT(INDEX(SC_LT,MATCH("S02",SC_ID,0))*F20^2+E20^2*INDEX(SC_LTStd,MATCH("S02",SC_ID,0))^2)+E20*INDEX(SC_LT,MATCH("S02",SC_ID,0)))*(H20*INDEX(LC_Mult,MATCH("USA",LC_Country,0))),0) | P20: =IFERROR(E20*WeeksYear*(H20*INDEX(LC_Mult,MATCH("Canada",LC_Country,0)))+(z*SQRT(INDEX(SC_LT,MATCH("S01",SC_ID,0))*F20^2+E20^2*INDEX(SC_LTStd,MATCH("S01",SC_ID,0))^2)+E20*INDEX(SC_LT,MATCH("S01",SC_ID,0)))*(H20*INDEX(LC_Mult,MATCH("Canada",LC_Country,0)))*HoldRate,9.99E+99) | Q20: =IFERROR((z*SQRT(INDEX(SC_LT,MATCH("S01",SC_ID,0))*F20^2+E20^2*INDEX(SC_LTStd,MATCH("S01",SC_ID,0))^2)+E20*INDEX(SC_LT,MATCH("S01",SC_ID,0)))*(H20*INDEX(LC_Mult,MATCH("Canada",LC_Country,0))),0) | R20: =IF(L20=MIN(L20,N20,P20),"Mexico",IF(N20=MIN(L20,N20,P20),"USA","Canada")) | S20: =MIN(L20,N20,P20) | T20: =K20-S20 | U20: =IFERROR(T20/K20,0) | V20: =J20-IF(L20=MIN(L20,N20,P20),M20,IF(N20=MIN(L20,N20,P20),O20,Q20)) | W20: =IF(T20>0,"Nearshore: lower total cost",IF(U20>=-LC_Premium,"Nearshore candidate: small premium for resilience","Keep offshore")) | X20: =MATCH("NB-0004",P_SKU,0)
A21: =INDEX(P_SKU,$X21) | B21: =INDEX(P_Name,$X21) | C21: =INDEX(P_Sup,$X21) | D21: =INDEX(Supplier_Scorecard!$C$5:$C$12,MATCH(C21,SC_ID,0)) | E21: =INDEX(P_Demand,$X21) | F21: =INDEX(P_Std,$X21) | G21: =INDEX(P_Cost,$X21) | H21: =G21/INDEX(LC_Price,MATCH(D21,LC_Country,0)) | I21: =H21*INDEX(LC_Mult,MATCH(D21,LC_Country,0)) | J21: =(z*SQRT(INDEX(SC_LT,MATCH(C21,SC_ID,0))*F21^2+E21^2*INDEX(SC_LTStd,MATCH(C21,SC_ID,0))^2)+E21*INDEX(SC_LT,MATCH(C21,SC_ID,0)))*I21 | K21: =E21*WeeksYear*I21+(z*SQRT(INDEX(SC_LT,MATCH(C21,SC_ID,0))*F21^2+E21^2*INDEX(SC_LTStd,MATCH(C21,SC_ID,0))^2)+E21*INDEX(SC_LT,MATCH(C21,SC_ID,0)))*I21*HoldRate | L21: =IFERROR(E21*WeeksYear*(H21*INDEX(LC_Mult,MATCH("Mexico",LC_Country,0)))+(z*SQRT(INDEX(SC_LT,MATCH("S04",SC_ID,0))*F21^2+E21^2*INDEX(SC_LTStd,MATCH("S04",SC_ID,0))^2)+E21*INDEX(SC_LT,MATCH("S04",SC_ID,0)))*(H21*INDEX(LC_Mult,MATCH("Mexico",LC_Country,0)))*HoldRate,9.99E+99) | M21: =IFERROR((z*SQRT(INDEX(SC_LT,MATCH("S04",SC_ID,0))*F21^2+E21^2*INDEX(SC_LTStd,MATCH("S04",SC_ID,0))^2)+E21*INDEX(SC_LT,MATCH("S04",SC_ID,0)))*(H21*INDEX(LC_Mult,MATCH("Mexico",LC_Country,0))),0) | N21: =IFERROR(E21*WeeksYear*(H21*INDEX(LC_Mult,MATCH("USA",LC_Country,0)))+(z*SQRT(INDEX(SC_LT,MATCH("S02",SC_ID,0))*F21^2+E21^2*INDEX(SC_LTStd,MATCH("S02",SC_ID,0))^2)+E21*INDEX(SC_LT,MATCH("S02",SC_ID,0)))*(H21*INDEX(LC_Mult,MATCH("USA",LC_Country,0)))*HoldRate,9.99E+99) | O21: =IFERROR((z*SQRT(INDEX(SC_LT,MATCH("S02",SC_ID,0))*F21^2+E21^2*INDEX(SC_LTStd,MATCH("S02",SC_ID,0))^2)+E21*INDEX(SC_LT,MATCH("S02",SC_ID,0)))*(H21*INDEX(LC_Mult,MATCH("USA",LC_Country,0))),0) | P21: =IFERROR(E21*WeeksYear*(H21*INDEX(LC_Mult,MATCH("Canada",LC_Country,0)))+(z*SQRT(INDEX(SC_LT,MATCH("S01",SC_ID,0))*F21^2+E21^2*INDEX(SC_LTStd,MATCH("S01",SC_ID,0))^2)+E21*INDEX(SC_LT,MATCH("S01",SC_ID,0)))*(H21*INDEX(LC_Mult,MATCH("Canada",LC_Country,0)))*HoldRate,9.99E+99) | Q21: =IFERROR((z*SQRT(INDEX(SC_LT,MATCH("S01",SC_ID,0))*F21^2+E21^2*INDEX(SC_LTStd,MATCH("S01",SC_ID,0))^2)+E21*INDEX(SC_LT,MATCH("S01",SC_ID,0)))*(H21*INDEX(LC_Mult,MATCH("Canada",LC_Country,0))),0) | R21: =IF(L21=MIN(L21,N21,P21),"Mexico",IF(N21=MIN(L21,N21,P21),"USA","Canada")) | S21: =MIN(L21,N21,P21) | T21: =K21-S21 | U21: =IFERROR(T21/K21,0) | V21: =J21-IF(L21=MIN(L21,N21,P21),M21,IF(N21=MIN(L21,N21,P21),O21,Q21)) | W21: =IF(T21>0,"Nearshore: lower total cost",IF(U21>=-LC_Premium,"Nearshore candidate: small premium for resilience","Keep offshore")) | X21: =MATCH("NB-0005",P_SKU,0)
A22: =INDEX(P_SKU,$X22) | B22: =INDEX(P_Name,$X22) | C22: =INDEX(P_Sup,$X22) | D22: =INDEX(Supplier_Scorecard!$C$5:$C$12,MATCH(C22,SC_ID,0)) | E22: =INDEX(P_Demand,$X22) | F22: =INDEX(P_Std,$X22) | G22: =INDEX(P_Cost,$X22) | H22: =G22/INDEX(LC_Price,MATCH(D22,LC_Country,0)) | I22: =H22*INDEX(LC_Mult,MATCH(D22,LC_Country,0)) | J22: =(z*SQRT(INDEX(SC_LT,MATCH(C22,SC_ID,0))*F22^2+E22^2*INDEX(SC_LTStd,MATCH(C22,SC_ID,0))^2)+E22*INDEX(SC_LT,MATCH(C22,SC_ID,0)))*I22 | K22: =E22*WeeksYear*I22+(z*SQRT(INDEX(SC_LT,MATCH(C22,SC_ID,0))*F22^2+E22^2*INDEX(SC_LTStd,MATCH(C22,SC_ID,0))^2)+E22*INDEX(SC_LT,MATCH(C22,SC_ID,0)))*I22*HoldRate | L22: =IFERROR(E22*WeeksYear*(H22*INDEX(LC_Mult,MATCH("Mexico",LC_Country,0)))+(z*SQRT(INDEX(SC_LT,MATCH("S04",SC_ID,0))*F22^2+E22^2*INDEX(SC_LTStd,MATCH("S04",SC_ID,0))^2)+E22*INDEX(SC_LT,MATCH("S04",SC_ID,0)))*(H22*INDEX(LC_Mult,MATCH("Mexico",LC_Country,0)))*HoldRate,9.99E+99) | M22: =IFERROR((z*SQRT(INDEX(SC_LT,MATCH("S04",SC_ID,0))*F22^2+E22^2*INDEX(SC_LTStd,MATCH("S04",SC_ID,0))^2)+E22*INDEX(SC_LT,MATCH("S04",SC_ID,0)))*(H22*INDEX(LC_Mult,MATCH("Mexico",LC_Country,0))),0) | N22: =IFERROR(E22*WeeksYear*(H22*INDEX(LC_Mult,MATCH("USA",LC_Country,0)))+(z*SQRT(INDEX(SC_LT,MATCH("S02",SC_ID,0))*F22^2+E22^2*INDEX(SC_LTStd,MATCH("S02",SC_ID,0))^2)+E22*INDEX(SC_LT,MATCH("S02",SC_ID,0)))*(H22*INDEX(LC_Mult,MATCH("USA",LC_Country,0)))*HoldRate,9.99E+99) | O22: =IFERROR((z*SQRT(INDEX(SC_LT,MATCH("S02",SC_ID,0))*F22^2+E22^2*INDEX(SC_LTStd,MATCH("S02",SC_ID,0))^2)+E22*INDEX(SC_LT,MATCH("S02",SC_ID,0)))*(H22*INDEX(LC_Mult,MATCH("USA",LC_Country,0))),0) | P22: =IFERROR(E22*WeeksYear*(H22*INDEX(LC_Mult,MATCH("Canada",LC_Country,0)))+(z*SQRT(INDEX(SC_LT,MATCH("S01",SC_ID,0))*F22^2+E22^2*INDEX(SC_LTStd,MATCH("S01",SC_ID,0))^2)+E22*INDEX(SC_LT,MATCH("S01",SC_ID,0)))*(H22*INDEX(LC_Mult,MATCH("Canada",LC_Country,0)))*HoldRate,9.99E+99) | Q22: =IFERROR((z*SQRT(INDEX(SC_LT,MATCH("S01",SC_ID,0))*F22^2+E22^2*INDEX(SC_LTStd,MATCH("S01",SC_ID,0))^2)+E22*INDEX(SC_LT,MATCH("S01",SC_ID,0)))*(H22*INDEX(LC_Mult,MATCH("Canada",LC_Country,0))),0) | R22: =IF(L22=MIN(L22,N22,P22),"Mexico",IF(N22=MIN(L22,N22,P22),"USA","Canada")) | S22: =MIN(L22,N22,P22) | T22: =K22-S22 | U22: =IFERROR(T22/K22,0) | V22: =J22-IF(L22=MIN(L22,N22,P22),M22,IF(N22=MIN(L22,N22,P22),O22,Q22)) | W22: =IF(T22>0,"Nearshore: lower total cost",IF(U22>=-LC_Premium,"Nearshore candidate: small premium for resilience","Keep offshore")) | X22: =MATCH("NB-0007",P_SKU,0)
A23: =INDEX(P_SKU,$X23) | B23: =INDEX(P_Name,$X23) | C23: =INDEX(P_Sup,$X23) | D23: =INDEX(Supplier_Scorecard!$C$5:$C$12,MATCH(C23,SC_ID,0)) | E23: =INDEX(P_Demand,$X23) | F23: =INDEX(P_Std,$X23) | G23: =INDEX(P_Cost,$X23) | H23: =G23/INDEX(LC_Price,MATCH(D23,LC_Country,0)) | I23: =H23*INDEX(LC_Mult,MATCH(D23,LC_Country,0)) | J23: =(z*SQRT(INDEX(SC_LT,MATCH(C23,SC_ID,0))*F23^2+E23^2*INDEX(SC_LTStd,MATCH(C23,SC_ID,0))^2)+E23*INDEX(SC_LT,MATCH(C23,SC_ID,0)))*I23 | K23: =E23*WeeksYear*I23+(z*SQRT(INDEX(SC_LT,MATCH(C23,SC_ID,0))*F23^2+E23^2*INDEX(SC_LTStd,MATCH(C23,SC_ID,0))^2)+E23*INDEX(SC_LT,MATCH(C23,SC_ID,0)))*I23*HoldRate | L23: =IFERROR(E23*WeeksYear*(H23*INDEX(LC_Mult,MATCH("Mexico",LC_Country,0)))+(z*SQRT(INDEX(SC_LT,MATCH("S04",SC_ID,0))*F23^2+E23^2*INDEX(SC_LTStd,MATCH("S04",SC_ID,0))^2)+E23*INDEX(SC_LT,MATCH("S04",SC_ID,0)))*(H23*INDEX(LC_Mult,MATCH("Mexico",LC_Country,0)))*HoldRate,9.99E+99) | M23: =IFERROR((z*SQRT(INDEX(SC_LT,MATCH("S04",SC_ID,0))*F23^2+E23^2*INDEX(SC_LTStd,MATCH("S04",SC_ID,0))^2)+E23*INDEX(SC_LT,MATCH("S04",SC_ID,0)))*(H23*INDEX(LC_Mult,MATCH("Mexico",LC_Country,0))),0) | N23: =IFERROR(E23*WeeksYear*(H23*INDEX(LC_Mult,MATCH("USA",LC_Country,0)))+(z*SQRT(INDEX(SC_LT,MATCH("S02",SC_ID,0))*F23^2+E23^2*INDEX(SC_LTStd,MATCH("S02",SC_ID,0))^2)+E23*INDEX(SC_LT,MATCH("S02",SC_ID,0)))*(H23*INDEX(LC_Mult,MATCH("USA",LC_Country,0)))*HoldRate,9.99E+99) | O23: =IFERROR((z*SQRT(INDEX(SC_LT,MATCH("S02",SC_ID,0))*F23^2+E23^2*INDEX(SC_LTStd,MATCH("S02",SC_ID,0))^2)+E23*INDEX(SC_LT,MATCH("S02",SC_ID,0)))*(H23*INDEX(LC_Mult,MATCH("USA",LC_Country,0))),0) | P23: =IFERROR(E23*WeeksYear*(H23*INDEX(LC_Mult,MATCH("Canada",LC_Country,0)))+(z*SQRT(INDEX(SC_LT,MATCH("S01",SC_ID,0))*F23^2+E23^2*INDEX(SC_LTStd,MATCH("S01",SC_ID,0))^2)+E23*INDEX(SC_LT,MATCH("S01",SC_ID,0)))*(H23*INDEX(LC_Mult,MATCH("Canada",LC_Country,0)))*HoldRate,9.99E+99) | Q23: =IFERROR((z*SQRT(INDEX(SC_LT,MATCH("S01",SC_ID,0))*F23^2+E23^2*INDEX(SC_LTStd,MATCH("S01",SC_ID,0))^2)+E23*INDEX(SC_LT,MATCH("S01",SC_ID,0)))*(H23*INDEX(LC_Mult,MATCH("Canada",LC_Country,0))),0) | R23: =IF(L23=MIN(L23,N23,P23),"Mexico",IF(N23=MIN(L23,N23,P23),"USA","Canada")) | S23: =MIN(L23,N23,P23) | T23: =K23-S23 | U23: =IFERROR(T23/K23,0) | V23: =J23-IF(L23=MIN(L23,N23,P23),M23,IF(N23=MIN(L23,N23,P23),O23,Q23)) | W23: =IF(T23>0,"Nearshore: lower total cost",IF(U23>=-LC_Premium,"Nearshore candidate: small premium for resilience","Keep offshore")) | X23: =MATCH("NB-0008",P_SKU,0)
A24: =INDEX(P_SKU,$X24) | B24: =INDEX(P_Name,$X24) | C24: =INDEX(P_Sup,$X24) | D24: =INDEX(Supplier_Scorecard!$C$5:$C$12,MATCH(C24,SC_ID,0)) | E24: =INDEX(P_Demand,$X24) | F24: =INDEX(P_Std,$X24) | G24: =INDEX(P_Cost,$X24) | H24: =G24/INDEX(LC_Price,MATCH(D24,LC_Country,0)) | I24: =H24*INDEX(LC_Mult,MATCH(D24,LC_Country,0)) | J24: =(z*SQRT(INDEX(SC_LT,MATCH(C24,SC_ID,0))*F24^2+E24^2*INDEX(SC_LTStd,MATCH(C24,SC_ID,0))^2)+E24*INDEX(SC_LT,MATCH(C24,SC_ID,0)))*I24 | K24: =E24*WeeksYear*I24+(z*SQRT(INDEX(SC_LT,MATCH(C24,SC_ID,0))*F24^2+E24^2*INDEX(SC_LTStd,MATCH(C24,SC_ID,0))^2)+E24*INDEX(SC_LT,MATCH(C24,SC_ID,0)))*I24*HoldRate | L24: =IFERROR(E24*WeeksYear*(H24*INDEX(LC_Mult,MATCH("Mexico",LC_Country,0)))+(z*SQRT(INDEX(SC_LT,MATCH("S04",SC_ID,0))*F24^2+E24^2*INDEX(SC_LTStd,MATCH("S04",SC_ID,0))^2)+E24*INDEX(SC_LT,MATCH("S04",SC_ID,0)))*(H24*INDEX(LC_Mult,MATCH("Mexico",LC_Country,0)))*HoldRate,9.99E+99) | M24: =IFERROR((z*SQRT(INDEX(SC_LT,MATCH("S04",SC_ID,0))*F24^2+E24^2*INDEX(SC_LTStd,MATCH("S04",SC_ID,0))^2)+E24*INDEX(SC_LT,MATCH("S04",SC_ID,0)))*(H24*INDEX(LC_Mult,MATCH("Mexico",LC_Country,0))),0) | N24: =IFERROR(E24*WeeksYear*(H24*INDEX(LC_Mult,MATCH("USA",LC_Country,0)))+(z*SQRT(INDEX(SC_LT,MATCH("S02",SC_ID,0))*F24^2+E24^2*INDEX(SC_LTStd,MATCH("S02",SC_ID,0))^2)+E24*INDEX(SC_LT,MATCH("S02",SC_ID,0)))*(H24*INDEX(LC_Mult,MATCH("USA",LC_Country,0)))*HoldRate,9.99E+99) | O24: =IFERROR((z*SQRT(INDEX(SC_LT,MATCH("S02",SC_ID,0))*F24^2+E24^2*INDEX(SC_LTStd,MATCH("S02",SC_ID,0))^2)+E24*INDEX(SC_LT,MATCH("S02",SC_ID,0)))*(H24*INDEX(LC_Mult,MATCH("USA",LC_Country,0))),0) | P24: =IFERROR(E24*WeeksYear*(H24*INDEX(LC_Mult,MATCH("Canada",LC_Country,0)))+(z*SQRT(INDEX(SC_LT,MATCH("S01",SC_ID,0))*F24^2+E24^2*INDEX(SC_LTStd,MATCH("S01",SC_ID,0))^2)+E24*INDEX(SC_LT,MATCH("S01",SC_ID,0)))*(H24*INDEX(LC_Mult,MATCH("Canada",LC_Country,0)))*HoldRate,9.99E+99) | Q24: =IFERROR((z*SQRT(INDEX(SC_LT,MATCH("S01",SC_ID,0))*F24^2+E24^2*INDEX(SC_LTStd,MATCH("S01",SC_ID,0))^2)+E24*INDEX(SC_LT,MATCH("S01",SC_ID,0)))*(H24*INDEX(LC_Mult,MATCH("Canada",LC_Country,0))),0) | R24: =IF(L24=MIN(L24,N24,P24),"Mexico",IF(N24=MIN(L24,N24,P24),"USA","Canada")) | S24: =MIN(L24,N24,P24) | T24: =K24-S24 | U24: =IFERROR(T24/K24,0) | V24: =J24-IF(L24=MIN(L24,N24,P24),M24,IF(N24=MIN(L24,N24,P24),O24,Q24)) | W24: =IF(T24>0,"Nearshore: lower total cost",IF(U24>=-LC_Premium,"Nearshore candidate: small premium for resilience","Keep offshore")) | X24: =MATCH("NB-0009",P_SKU,0)
A25: =INDEX(P_SKU,$X25) | B25: =INDEX(P_Name,$X25) | C25: =INDEX(P_Sup,$X25) | D25: =INDEX(Supplier_Scorecard!$C$5:$C$12,MATCH(C25,SC_ID,0)) | E25: =INDEX(P_Demand,$X25) | F25: =INDEX(P_Std,$X25) | G25: =INDEX(P_Cost,$X25) | H25: =G25/INDEX(LC_Price,MATCH(D25,LC_Country,0)) | I25: =H25*INDEX(LC_Mult,MATCH(D25,LC_Country,0)) | J25: =(z*SQRT(INDEX(SC_LT,MATCH(C25,SC_ID,0))*F25^2+E25^2*INDEX(SC_LTStd,MATCH(C25,SC_ID,0))^2)+E25*INDEX(SC_LT,MATCH(C25,SC_ID,0)))*I25 | K25: =E25*WeeksYear*I25+(z*SQRT(INDEX(SC_LT,MATCH(C25,SC_ID,0))*F25^2+E25^2*INDEX(SC_LTStd,MATCH(C25,SC_ID,0))^2)+E25*INDEX(SC_LT,MATCH(C25,SC_ID,0)))*I25*HoldRate | L25: =IFERROR(E25*WeeksYear*(H25*INDEX(LC_Mult,MATCH("Mexico",LC_Country,0)))+(z*SQRT(INDEX(SC_LT,MATCH("S04",SC_ID,0))*F25^2+E25^2*INDEX(SC_LTStd,MATCH("S04",SC_ID,0))^2)+E25*INDEX(SC_LT,MATCH("S04",SC_ID,0)))*(H25*INDEX(LC_Mult,MATCH("Mexico",LC_Country,0)))*HoldRate,9.99E+99) | M25: =IFERROR((z*SQRT(INDEX(SC_LT,MATCH("S04",SC_ID,0))*F25^2+E25^2*INDEX(SC_LTStd,MATCH("S04",SC_ID,0))^2)+E25*INDEX(SC_LT,MATCH("S04",SC_ID,0)))*(H25*INDEX(LC_Mult,MATCH("Mexico",LC_Country,0))),0) | N25: =IFERROR(E25*WeeksYear*(H25*INDEX(LC_Mult,MATCH("USA",LC_Country,0)))+(z*SQRT(INDEX(SC_LT,MATCH("S02",SC_ID,0))*F25^2+E25^2*INDEX(SC_LTStd,MATCH("S02",SC_ID,0))^2)+E25*INDEX(SC_LT,MATCH("S02",SC_ID,0)))*(H25*INDEX(LC_Mult,MATCH("USA",LC_Country,0)))*HoldRate,9.99E+99) | O25: =IFERROR((z*SQRT(INDEX(SC_LT,MATCH("S02",SC_ID,0))*F25^2+E25^2*INDEX(SC_LTStd,MATCH("S02",SC_ID,0))^2)+E25*INDEX(SC_LT,MATCH("S02",SC_ID,0)))*(H25*INDEX(LC_Mult,MATCH("USA",LC_Country,0))),0) | P25: =IFERROR(E25*WeeksYear*(H25*INDEX(LC_Mult,MATCH("Canada",LC_Country,0)))+(z*SQRT(INDEX(SC_LT,MATCH("S01",SC_ID,0))*F25^2+E25^2*INDEX(SC_LTStd,MATCH("S01",SC_ID,0))^2)+E25*INDEX(SC_LT,MATCH("S01",SC_ID,0)))*(H25*INDEX(LC_Mult,MATCH("Canada",LC_Country,0)))*HoldRate,9.99E+99) | Q25: =IFERROR((z*SQRT(INDEX(SC_LT,MATCH("S01",SC_ID,0))*F25^2+E25^2*INDEX(SC_LTStd,MATCH("S01",SC_ID,0))^2)+E25*INDEX(SC_LT,MATCH("S01",SC_ID,0)))*(H25*INDEX(LC_Mult,MATCH("Canada",LC_Country,0))),0) | R25: =IF(L25=MIN(L25,N25,P25),"Mexico",IF(N25=MIN(L25,N25,P25),"USA","Canada")) | S25: =MIN(L25,N25,P25) | T25: =K25-S25 | U25: =IFERROR(T25/K25,0) | V25: =J25-IF(L25=MIN(L25,N25,P25),M25,IF(N25=MIN(L25,N25,P25),O25,Q25)) | W25: =IF(T25>0,"Nearshore: lower total cost",IF(U25>=-LC_Premium,"Nearshore candidate: small premium for resilience","Keep offshore")) | X25: =MATCH("NB-0013",P_SKU,0)
A26: =INDEX(P_SKU,$X26) | B26: =INDEX(P_Name,$X26) | C26: =INDEX(P_Sup,$X26) | D26: =INDEX(Supplier_Scorecard!$C$5:$C$12,MATCH(C26,SC_ID,0)) | E26: =INDEX(P_Demand,$X26) | F26: =INDEX(P_Std,$X26) | G26: =INDEX(P_Cost,$X26) | H26: =G26/INDEX(LC_Price,MATCH(D26,LC_Country,0)) | I26: =H26*INDEX(LC_Mult,MATCH(D26,LC_Country,0)) | J26: =(z*SQRT(INDEX(SC_LT,MATCH(C26,SC_ID,0))*F26^2+E26^2*INDEX(SC_LTStd,MATCH(C26,SC_ID,0))^2)+E26*INDEX(SC_LT,MATCH(C26,SC_ID,0)))*I26 | K26: =E26*WeeksYear*I26+(z*SQRT(INDEX(SC_LT,MATCH(C26,SC_ID,0))*F26^2+E26^2*INDEX(SC_LTStd,MATCH(C26,SC_ID,0))^2)+E26*INDEX(SC_LT,MATCH(C26,SC_ID,0)))*I26*HoldRate | L26: =IFERROR(E26*WeeksYear*(H26*INDEX(LC_Mult,MATCH("Mexico",LC_Country,0)))+(z*SQRT(INDEX(SC_LT,MATCH("S04",SC_ID,0))*F26^2+E26^2*INDEX(SC_LTStd,MATCH("S04",SC_ID,0))^2)+E26*INDEX(SC_LT,MATCH("S04",SC_ID,0)))*(H26*INDEX(LC_Mult,MATCH("Mexico",LC_Country,0)))*HoldRate,9.99E+99) | M26: =IFERROR((z*SQRT(INDEX(SC_LT,MATCH("S04",SC_ID,0))*F26^2+E26^2*INDEX(SC_LTStd,MATCH("S04",SC_ID,0))^2)+E26*INDEX(SC_LT,MATCH("S04",SC_ID,0)))*(H26*INDEX(LC_Mult,MATCH("Mexico",LC_Country,0))),0) | N26: =IFERROR(E26*WeeksYear*(H26*INDEX(LC_Mult,MATCH("USA",LC_Country,0)))+(z*SQRT(INDEX(SC_LT,MATCH("S02",SC_ID,0))*F26^2+E26^2*INDEX(SC_LTStd,MATCH("S02",SC_ID,0))^2)+E26*INDEX(SC_LT,MATCH("S02",SC_ID,0)))*(H26*INDEX(LC_Mult,MATCH("USA",LC_Country,0)))*HoldRate,9.99E+99) | O26: =IFERROR((z*SQRT(INDEX(SC_LT,MATCH("S02",SC_ID,0))*F26^2+E26^2*INDEX(SC_LTStd,MATCH("S02",SC_ID,0))^2)+E26*INDEX(SC_LT,MATCH("S02",SC_ID,0)))*(H26*INDEX(LC_Mult,MATCH("USA",LC_Country,0))),0) | P26: =IFERROR(E26*WeeksYear*(H26*INDEX(LC_Mult,MATCH("Canada",LC_Country,0)))+(z*SQRT(INDEX(SC_LT,MATCH("S01",SC_ID,0))*F26^2+E26^2*INDEX(SC_LTStd,MATCH("S01",SC_ID,0))^2)+E26*INDEX(SC_LT,MATCH("S01",SC_ID,0)))*(H26*INDEX(LC_Mult,MATCH("Canada",LC_Country,0)))*HoldRate,9.99E+99) | Q26: =IFERROR((z*SQRT(INDEX(SC_LT,MATCH("S01",SC_ID,0))*F26^2+E26^2*INDEX(SC_LTStd,MATCH("S01",SC_ID,0))^2)+E26*INDEX(SC_LT,MATCH("S01",SC_ID,0)))*(H26*INDEX(LC_Mult,MATCH("Canada",LC_Country,0))),0) | R26: =IF(L26=MIN(L26,N26,P26),"Mexico",IF(N26=MIN(L26,N26,P26),"USA","Canada")) | S26: =MIN(L26,N26,P26) | T26: =K26-S26 | U26: =IFERROR(T26/K26,0) | V26: =J26-IF(L26=MIN(L26,N26,P26),M26,IF(N26=MIN(L26,N26,P26),O26,Q26)) | W26: =IF(T26>0,"Nearshore: lower total cost",IF(U26>=-LC_Premium,"Nearshore candidate: small premium for resilience","Keep offshore")) | X26: =MATCH("NB-0017",P_SKU,0)
A27: =INDEX(P_SKU,$X27) | B27: =INDEX(P_Name,$X27) | C27: =INDEX(P_Sup,$X27) | D27: =INDEX(Supplier_Scorecard!$C$5:$C$12,MATCH(C27,SC_ID,0)) | E27: =INDEX(P_Demand,$X27) | F27: =INDEX(P_Std,$X27) | G27: =INDEX(P_Cost,$X27) | H27: =G27/INDEX(LC_Price,MATCH(D27,LC_Country,0)) | I27: =H27*INDEX(LC_Mult,MATCH(D27,LC_Country,0)) | J27: =(z*SQRT(INDEX(SC_LT,MATCH(C27,SC_ID,0))*F27^2+E27^2*INDEX(SC_LTStd,MATCH(C27,SC_ID,0))^2)+E27*INDEX(SC_LT,MATCH(C27,SC_ID,0)))*I27 | K27: =E27*WeeksYear*I27+(z*SQRT(INDEX(SC_LT,MATCH(C27,SC_ID,0))*F27^2+E27^2*INDEX(SC_LTStd,MATCH(C27,SC_ID,0))^2)+E27*INDEX(SC_LT,MATCH(C27,SC_ID,0)))*I27*HoldRate | L27: =IFERROR(E27*WeeksYear*(H27*INDEX(LC_Mult,MATCH("Mexico",LC_Country,0)))+(z*SQRT(INDEX(SC_LT,MATCH("S04",SC_ID,0))*F27^2+E27^2*INDEX(SC_LTStd,MATCH("S04",SC_ID,0))^2)+E27*INDEX(SC_LT,MATCH("S04",SC_ID,0)))*(H27*INDEX(LC_Mult,MATCH("Mexico",LC_Country,0)))*HoldRate,9.99E+99) | M27: =IFERROR((z*SQRT(INDEX(SC_LT,MATCH("S04",SC_ID,0))*F27^2+E27^2*INDEX(SC_LTStd,MATCH("S04",SC_ID,0))^2)+E27*INDEX(SC_LT,MATCH("S04",SC_ID,0)))*(H27*INDEX(LC_Mult,MATCH("Mexico",LC_Country,0))),0) | N27: =IFERROR(E27*WeeksYear*(H27*INDEX(LC_Mult,MATCH("USA",LC_Country,0)))+(z*SQRT(INDEX(SC_LT,MATCH("S02",SC_ID,0))*F27^2+E27^2*INDEX(SC_LTStd,MATCH("S02",SC_ID,0))^2)+E27*INDEX(SC_LT,MATCH("S02",SC_ID,0)))*(H27*INDEX(LC_Mult,MATCH("USA",LC_Country,0)))*HoldRate,9.99E+99) | O27: =IFERROR((z*SQRT(INDEX(SC_LT,MATCH("S02",SC_ID,0))*F27^2+E27^2*INDEX(SC_LTStd,MATCH("S02",SC_ID,0))^2)+E27*INDEX(SC_LT,MATCH("S02",SC_ID,0)))*(H27*INDEX(LC_Mult,MATCH("USA",LC_Country,0))),0) | P27: =IFERROR(E27*WeeksYear*(H27*INDEX(LC_Mult,MATCH("Canada",LC_Country,0)))+(z*SQRT(INDEX(SC_LT,MATCH("S01",SC_ID,0))*F27^2+E27^2*INDEX(SC_LTStd,MATCH("S01",SC_ID,0))^2)+E27*INDEX(SC_LT,MATCH("S01",SC_ID,0)))*(H27*INDEX(LC_Mult,MATCH("Canada",LC_Country,0)))*HoldRate,9.99E+99) | Q27: =IFERROR((z*SQRT(INDEX(SC_LT,MATCH("S01",SC_ID,0))*F27^2+E27^2*INDEX(SC_LTStd,MATCH("S01",SC_ID,0))^2)+E27*INDEX(SC_LT,MATCH("S01",SC_ID,0)))*(H27*INDEX(LC_Mult,MATCH("Canada",LC_Country,0))),0) | R27: =IF(L27=MIN(L27,N27,P27),"Mexico",IF(N27=MIN(L27,N27,P27),"USA","Canada")) | S27: =MIN(L27,N27,P27) | T27: =K27-S27 | U27: =IFERROR(T27/K27,0) | V27: =J27-IF(L27=MIN(L27,N27,P27),M27,IF(N27=MIN(L27,N27,P27),O27,Q27)) | W27: =IF(T27>0,"Nearshore: lower total cost",IF(U27>=-LC_Premium,"Nearshore candidate: small premium for resilience","Keep offshore")) | X27: =MATCH("NB-0020",P_SKU,0)
A28: =INDEX(P_SKU,$X28) | B28: =INDEX(P_Name,$X28) | C28: =INDEX(P_Sup,$X28) | D28: =INDEX(Supplier_Scorecard!$C$5:$C$12,MATCH(C28,SC_ID,0)) | E28: =INDEX(P_Demand,$X28) | F28: =INDEX(P_Std,$X28) | G28: =INDEX(P_Cost,$X28) | H28: =G28/INDEX(LC_Price,MATCH(D28,LC_Country,0)) | I28: =H28*INDEX(LC_Mult,MATCH(D28,LC_Country,0)) | J28: =(z*SQRT(INDEX(SC_LT,MATCH(C28,SC_ID,0))*F28^2+E28^2*INDEX(SC_LTStd,MATCH(C28,SC_ID,0))^2)+E28*INDEX(SC_LT,MATCH(C28,SC_ID,0)))*I28 | K28: =E28*WeeksYear*I28+(z*SQRT(INDEX(SC_LT,MATCH(C28,SC_ID,0))*F28^2+E28^2*INDEX(SC_LTStd,MATCH(C28,SC_ID,0))^2)+E28*INDEX(SC_LT,MATCH(C28,SC_ID,0)))*I28*HoldRate | L28: =IFERROR(E28*WeeksYear*(H28*INDEX(LC_Mult,MATCH("Mexico",LC_Country,0)))+(z*SQRT(INDEX(SC_LT,MATCH("S04",SC_ID,0))*F28^2+E28^2*INDEX(SC_LTStd,MATCH("S04",SC_ID,0))^2)+E28*INDEX(SC_LT,MATCH("S04",SC_ID,0)))*(H28*INDEX(LC_Mult,MATCH("Mexico",LC_Country,0)))*HoldRate,9.99E+99) | M28: =IFERROR((z*SQRT(INDEX(SC_LT,MATCH("S04",SC_ID,0))*F28^2+E28^2*INDEX(SC_LTStd,MATCH("S04",SC_ID,0))^2)+E28*INDEX(SC_LT,MATCH("S04",SC_ID,0)))*(H28*INDEX(LC_Mult,MATCH("Mexico",LC_Country,0))),0) | N28: =IFERROR(E28*WeeksYear*(H28*INDEX(LC_Mult,MATCH("USA",LC_Country,0)))+(z*SQRT(INDEX(SC_LT,MATCH("S02",SC_ID,0))*F28^2+E28^2*INDEX(SC_LTStd,MATCH("S02",SC_ID,0))^2)+E28*INDEX(SC_LT,MATCH("S02",SC_ID,0)))*(H28*INDEX(LC_Mult,MATCH("USA",LC_Country,0)))*HoldRate,9.99E+99) | O28: =IFERROR((z*SQRT(INDEX(SC_LT,MATCH("S02",SC_ID,0))*F28^2+E28^2*INDEX(SC_LTStd,MATCH("S02",SC_ID,0))^2)+E28*INDEX(SC_LT,MATCH("S02",SC_ID,0)))*(H28*INDEX(LC_Mult,MATCH("USA",LC_Country,0))),0) | P28: =IFERROR(E28*WeeksYear*(H28*INDEX(LC_Mult,MATCH("Canada",LC_Country,0)))+(z*SQRT(INDEX(SC_LT,MATCH("S01",SC_ID,0))*F28^2+E28^2*INDEX(SC_LTStd,MATCH("S01",SC_ID,0))^2)+E28*INDEX(SC_LT,MATCH("S01",SC_ID,0)))*(H28*INDEX(LC_Mult,MATCH("Canada",LC_Country,0)))*HoldRate,9.99E+99) | Q28: =IFERROR((z*SQRT(INDEX(SC_LT,MATCH("S01",SC_ID,0))*F28^2+E28^2*INDEX(SC_LTStd,MATCH("S01",SC_ID,0))^2)+E28*INDEX(SC_LT,MATCH("S01",SC_ID,0)))*(H28*INDEX(LC_Mult,MATCH("Canada",LC_Country,0))),0) | R28: =IF(L28=MIN(L28,N28,P28),"Mexico",IF(N28=MIN(L28,N28,P28),"USA","Canada")) | S28: =MIN(L28,N28,P28) | T28: =K28-S28 | U28: =IFERROR(T28/K28,0) | V28: =J28-IF(L28=MIN(L28,N28,P28),M28,IF(N28=MIN(L28,N28,P28),O28,Q28)) | W28: =IF(T28>0,"Nearshore: lower total cost",IF(U28>=-LC_Premium,"Nearshore candidate: small premium for resilience","Keep offshore")) | X28: =MATCH("NB-0021",P_SKU,0)
A29: =INDEX(P_SKU,$X29) | B29: =INDEX(P_Name,$X29) | C29: =INDEX(P_Sup,$X29) | D29: =INDEX(Supplier_Scorecard!$C$5:$C$12,MATCH(C29,SC_ID,0)) | E29: =INDEX(P_Demand,$X29) | F29: =INDEX(P_Std,$X29) | G29: =INDEX(P_Cost,$X29) | H29: =G29/INDEX(LC_Price,MATCH(D29,LC_Country,0)) | I29: =H29*INDEX(LC_Mult,MATCH(D29,LC_Country,0)) | J29: =(z*SQRT(INDEX(SC_LT,MATCH(C29,SC_ID,0))*F29^2+E29^2*INDEX(SC_LTStd,MATCH(C29,SC_ID,0))^2)+E29*INDEX(SC_LT,MATCH(C29,SC_ID,0)))*I29 | K29: =E29*WeeksYear*I29+(z*SQRT(INDEX(SC_LT,MATCH(C29,SC_ID,0))*F29^2+E29^2*INDEX(SC_LTStd,MATCH(C29,SC_ID,0))^2)+E29*INDEX(SC_LT,MATCH(C29,SC_ID,0)))*I29*HoldRate | L29: =IFERROR(E29*WeeksYear*(H29*INDEX(LC_Mult,MATCH("Mexico",LC_Country,0)))+(z*SQRT(INDEX(SC_LT,MATCH("S04",SC_ID,0))*F29^2+E29^2*INDEX(SC_LTStd,MATCH("S04",SC_ID,0))^2)+E29*INDEX(SC_LT,MATCH("S04",SC_ID,0)))*(H29*INDEX(LC_Mult,MATCH("Mexico",LC_Country,0)))*HoldRate,9.99E+99) | M29: =IFERROR((z*SQRT(INDEX(SC_LT,MATCH("S04",SC_ID,0))*F29^2+E29^2*INDEX(SC_LTStd,MATCH("S04",SC_ID,0))^2)+E29*INDEX(SC_LT,MATCH("S04",SC_ID,0)))*(H29*INDEX(LC_Mult,MATCH("Mexico",LC_Country,0))),0) | N29: =IFERROR(E29*WeeksYear*(H29*INDEX(LC_Mult,MATCH("USA",LC_Country,0)))+(z*SQRT(INDEX(SC_LT,MATCH("S02",SC_ID,0))*F29^2+E29^2*INDEX(SC_LTStd,MATCH("S02",SC_ID,0))^2)+E29*INDEX(SC_LT,MATCH("S02",SC_ID,0)))*(H29*INDEX(LC_Mult,MATCH("USA",LC_Country,0)))*HoldRate,9.99E+99) | O29: =IFERROR((z*SQRT(INDEX(SC_LT,MATCH("S02",SC_ID,0))*F29^2+E29^2*INDEX(SC_LTStd,MATCH("S02",SC_ID,0))^2)+E29*INDEX(SC_LT,MATCH("S02",SC_ID,0)))*(H29*INDEX(LC_Mult,MATCH("USA",LC_Country,0))),0) | P29: =IFERROR(E29*WeeksYear*(H29*INDEX(LC_Mult,MATCH("Canada",LC_Country,0)))+(z*SQRT(INDEX(SC_LT,MATCH("S01",SC_ID,0))*F29^2+E29^2*INDEX(SC_LTStd,MATCH("S01",SC_ID,0))^2)+E29*INDEX(SC_LT,MATCH("S01",SC_ID,0)))*(H29*INDEX(LC_Mult,MATCH("Canada",LC_Country,0)))*HoldRate,9.99E+99) | Q29: =IFERROR((z*SQRT(INDEX(SC_LT,MATCH("S01",SC_ID,0))*F29^2+E29^2*INDEX(SC_LTStd,MATCH("S01",SC_ID,0))^2)+E29*INDEX(SC_LT,MATCH("S01",SC_ID,0)))*(H29*INDEX(LC_Mult,MATCH("Canada",LC_Country,0))),0) | R29: =IF(L29=MIN(L29,N29,P29),"Mexico",IF(N29=MIN(L29,N29,P29),"USA","Canada")) | S29: =MIN(L29,N29,P29) | T29: =K29-S29 | U29: =IFERROR(T29/K29,0) | V29: =J29-IF(L29=MIN(L29,N29,P29),M29,IF(N29=MIN(L29,N29,P29),O29,Q29)) | W29: =IF(T29>0,"Nearshore: lower total cost",IF(U29>=-LC_Premium,"Nearshore candidate: small premium for resilience","Keep offshore")) | X29: =MATCH("NB-0022",P_SKU,0)
A30: =INDEX(P_SKU,$X30) | B30: =INDEX(P_Name,$X30) | C30: =INDEX(P_Sup,$X30) | D30: =INDEX(Supplier_Scorecard!$C$5:$C$12,MATCH(C30,SC_ID,0)) | E30: =INDEX(P_Demand,$X30) | F30: =INDEX(P_Std,$X30) | G30: =INDEX(P_Cost,$X30) | H30: =G30/INDEX(LC_Price,MATCH(D30,LC_Country,0)) | I30: =H30*INDEX(LC_Mult,MATCH(D30,LC_Country,0)) | J30: =(z*SQRT(INDEX(SC_LT,MATCH(C30,SC_ID,0))*F30^2+E30^2*INDEX(SC_LTStd,MATCH(C30,SC_ID,0))^2)+E30*INDEX(SC_LT,MATCH(C30,SC_ID,0)))*I30 | K30: =E30*WeeksYear*I30+(z*SQRT(INDEX(SC_LT,MATCH(C30,SC_ID,0))*F30^2+E30^2*INDEX(SC_LTStd,MATCH(C30,SC_ID,0))^2)+E30*INDEX(SC_LT,MATCH(C30,SC_ID,0)))*I30*HoldRate | L30: =IFERROR(E30*WeeksYear*(H30*INDEX(LC_Mult,MATCH("Mexico",LC_Country,0)))+(z*SQRT(INDEX(SC_LT,MATCH("S04",SC_ID,0))*F30^2+E30^2*INDEX(SC_LTStd,MATCH("S04",SC_ID,0))^2)+E30*INDEX(SC_LT,MATCH("S04",SC_ID,0)))*(H30*INDEX(LC_Mult,MATCH("Mexico",LC_Country,0)))*HoldRate,9.99E+99) | M30: =IFERROR((z*SQRT(INDEX(SC_LT,MATCH("S04",SC_ID,0))*F30^2+E30^2*INDEX(SC_LTStd,MATCH("S04",SC_ID,0))^2)+E30*INDEX(SC_LT,MATCH("S04",SC_ID,0)))*(H30*INDEX(LC_Mult,MATCH("Mexico",LC_Country,0))),0) | N30: =IFERROR(E30*WeeksYear*(H30*INDEX(LC_Mult,MATCH("USA",LC_Country,0)))+(z*SQRT(INDEX(SC_LT,MATCH("S02",SC_ID,0))*F30^2+E30^2*INDEX(SC_LTStd,MATCH("S02",SC_ID,0))^2)+E30*INDEX(SC_LT,MATCH("S02",SC_ID,0)))*(H30*INDEX(LC_Mult,MATCH("USA",LC_Country,0)))*HoldRate,9.99E+99) | O30: =IFERROR((z*SQRT(INDEX(SC_LT,MATCH("S02",SC_ID,0))*F30^2+E30^2*INDEX(SC_LTStd,MATCH("S02",SC_ID,0))^2)+E30*INDEX(SC_LT,MATCH("S02",SC_ID,0)))*(H30*INDEX(LC_Mult,MATCH("USA",LC_Country,0))),0) | P30: =IFERROR(E30*WeeksYear*(H30*INDEX(LC_Mult,MATCH("Canada",LC_Country,0)))+(z*SQRT(INDEX(SC_LT,MATCH("S01",SC_ID,0))*F30^2+E30^2*INDEX(SC_LTStd,MATCH("S01",SC_ID,0))^2)+E30*INDEX(SC_LT,MATCH("S01",SC_ID,0)))*(H30*INDEX(LC_Mult,MATCH("Canada",LC_Country,0)))*HoldRate,9.99E+99) | Q30: =IFERROR((z*SQRT(INDEX(SC_LT,MATCH("S01",SC_ID,0))*F30^2+E30^2*INDEX(SC_LTStd,MATCH("S01",SC_ID,0))^2)+E30*INDEX(SC_LT,MATCH("S01",SC_ID,0)))*(H30*INDEX(LC_Mult,MATCH("Canada",LC_Country,0))),0) | R30: =IF(L30=MIN(L30,N30,P30),"Mexico",IF(N30=MIN(L30,N30,P30),"USA","Canada")) | S30: =MIN(L30,N30,P30) | T30: =K30-S30 | U30: =IFERROR(T30/K30,0) | V30: =J30-IF(L30=MIN(L30,N30,P30),M30,IF(N30=MIN(L30,N30,P30),O30,Q30)) | W30: =IF(T30>0,"Nearshore: lower total cost",IF(U30>=-LC_Premium,"Nearshore candidate: small premium for resilience","Keep offshore")) | X30: =MATCH("NB-0024",P_SKU,0)
A31: =INDEX(P_SKU,$X31) | B31: =INDEX(P_Name,$X31) | C31: =INDEX(P_Sup,$X31) | D31: =INDEX(Supplier_Scorecard!$C$5:$C$12,MATCH(C31,SC_ID,0)) | E31: =INDEX(P_Demand,$X31) | F31: =INDEX(P_Std,$X31) | G31: =INDEX(P_Cost,$X31) | H31: =G31/INDEX(LC_Price,MATCH(D31,LC_Country,0)) | I31: =H31*INDEX(LC_Mult,MATCH(D31,LC_Country,0)) | J31: =(z*SQRT(INDEX(SC_LT,MATCH(C31,SC_ID,0))*F31^2+E31^2*INDEX(SC_LTStd,MATCH(C31,SC_ID,0))^2)+E31*INDEX(SC_LT,MATCH(C31,SC_ID,0)))*I31 | K31: =E31*WeeksYear*I31+(z*SQRT(INDEX(SC_LT,MATCH(C31,SC_ID,0))*F31^2+E31^2*INDEX(SC_LTStd,MATCH(C31,SC_ID,0))^2)+E31*INDEX(SC_LT,MATCH(C31,SC_ID,0)))*I31*HoldRate | L31: =IFERROR(E31*WeeksYear*(H31*INDEX(LC_Mult,MATCH("Mexico",LC_Country,0)))+(z*SQRT(INDEX(SC_LT,MATCH("S04",SC_ID,0))*F31^2+E31^2*INDEX(SC_LTStd,MATCH("S04",SC_ID,0))^2)+E31*INDEX(SC_LT,MATCH("S04",SC_ID,0)))*(H31*INDEX(LC_Mult,MATCH("Mexico",LC_Country,0)))*HoldRate,9.99E+99) | M31: =IFERROR((z*SQRT(INDEX(SC_LT,MATCH("S04",SC_ID,0))*F31^2+E31^2*INDEX(SC_LTStd,MATCH("S04",SC_ID,0))^2)+E31*INDEX(SC_LT,MATCH("S04",SC_ID,0)))*(H31*INDEX(LC_Mult,MATCH("Mexico",LC_Country,0))),0) | N31: =IFERROR(E31*WeeksYear*(H31*INDEX(LC_Mult,MATCH("USA",LC_Country,0)))+(z*SQRT(INDEX(SC_LT,MATCH("S02",SC_ID,0))*F31^2+E31^2*INDEX(SC_LTStd,MATCH("S02",SC_ID,0))^2)+E31*INDEX(SC_LT,MATCH("S02",SC_ID,0)))*(H31*INDEX(LC_Mult,MATCH("USA",LC_Country,0)))*HoldRate,9.99E+99) | O31: =IFERROR((z*SQRT(INDEX(SC_LT,MATCH("S02",SC_ID,0))*F31^2+E31^2*INDEX(SC_LTStd,MATCH("S02",SC_ID,0))^2)+E31*INDEX(SC_LT,MATCH("S02",SC_ID,0)))*(H31*INDEX(LC_Mult,MATCH("USA",LC_Country,0))),0) | P31: =IFERROR(E31*WeeksYear*(H31*INDEX(LC_Mult,MATCH("Canada",LC_Country,0)))+(z*SQRT(INDEX(SC_LT,MATCH("S01",SC_ID,0))*F31^2+E31^2*INDEX(SC_LTStd,MATCH("S01",SC_ID,0))^2)+E31*INDEX(SC_LT,MATCH("S01",SC_ID,0)))*(H31*INDEX(LC_Mult,MATCH("Canada",LC_Country,0)))*HoldRate,9.99E+99) | Q31: =IFERROR((z*SQRT(INDEX(SC_LT,MATCH("S01",SC_ID,0))*F31^2+E31^2*INDEX(SC_LTStd,MATCH("S01",SC_ID,0))^2)+E31*INDEX(SC_LT,MATCH("S01",SC_ID,0)))*(H31*INDEX(LC_Mult,MATCH("Canada",LC_Country,0))),0) | R31: =IF(L31=MIN(L31,N31,P31),"Mexico",IF(N31=MIN(L31,N31,P31),"USA","Canada")) | S31: =MIN(L31,N31,P31) | T31: =K31-S31 | U31: =IFERROR(T31/K31,0) | V31: =J31-IF(L31=MIN(L31,N31,P31),M31,IF(N31=MIN(L31,N31,P31),O31,Q31)) | W31: =IF(T31>0,"Nearshore: lower total cost",IF(U31>=-LC_Premium,"Nearshore candidate: small premium for resilience","Keep offshore")) | X31: =MATCH("NB-0030",P_SKU,0)
A32: =INDEX(P_SKU,$X32) | B32: =INDEX(P_Name,$X32) | C32: =INDEX(P_Sup,$X32) | D32: =INDEX(Supplier_Scorecard!$C$5:$C$12,MATCH(C32,SC_ID,0)) | E32: =INDEX(P_Demand,$X32) | F32: =INDEX(P_Std,$X32) | G32: =INDEX(P_Cost,$X32) | H32: =G32/INDEX(LC_Price,MATCH(D32,LC_Country,0)) | I32: =H32*INDEX(LC_Mult,MATCH(D32,LC_Country,0)) | J32: =(z*SQRT(INDEX(SC_LT,MATCH(C32,SC_ID,0))*F32^2+E32^2*INDEX(SC_LTStd,MATCH(C32,SC_ID,0))^2)+E32*INDEX(SC_LT,MATCH(C32,SC_ID,0)))*I32 | K32: =E32*WeeksYear*I32+(z*SQRT(INDEX(SC_LT,MATCH(C32,SC_ID,0))*F32^2+E32^2*INDEX(SC_LTStd,MATCH(C32,SC_ID,0))^2)+E32*INDEX(SC_LT,MATCH(C32,SC_ID,0)))*I32*HoldRate | L32: =IFERROR(E32*WeeksYear*(H32*INDEX(LC_Mult,MATCH("Mexico",LC_Country,0)))+(z*SQRT(INDEX(SC_LT,MATCH("S04",SC_ID,0))*F32^2+E32^2*INDEX(SC_LTStd,MATCH("S04",SC_ID,0))^2)+E32*INDEX(SC_LT,MATCH("S04",SC_ID,0)))*(H32*INDEX(LC_Mult,MATCH("Mexico",LC_Country,0)))*HoldRate,9.99E+99) | M32: =IFERROR((z*SQRT(INDEX(SC_LT,MATCH("S04",SC_ID,0))*F32^2+E32^2*INDEX(SC_LTStd,MATCH("S04",SC_ID,0))^2)+E32*INDEX(SC_LT,MATCH("S04",SC_ID,0)))*(H32*INDEX(LC_Mult,MATCH("Mexico",LC_Country,0))),0) | N32: =IFERROR(E32*WeeksYear*(H32*INDEX(LC_Mult,MATCH("USA",LC_Country,0)))+(z*SQRT(INDEX(SC_LT,MATCH("S02",SC_ID,0))*F32^2+E32^2*INDEX(SC_LTStd,MATCH("S02",SC_ID,0))^2)+E32*INDEX(SC_LT,MATCH("S02",SC_ID,0)))*(H32*INDEX(LC_Mult,MATCH("USA",LC_Country,0)))*HoldRate,9.99E+99) | O32: =IFERROR((z*SQRT(INDEX(SC_LT,MATCH("S02",SC_ID,0))*F32^2+E32^2*INDEX(SC_LTStd,MATCH("S02",SC_ID,0))^2)+E32*INDEX(SC_LT,MATCH("S02",SC_ID,0)))*(H32*INDEX(LC_Mult,MATCH("USA",LC_Country,0))),0) | P32: =IFERROR(E32*WeeksYear*(H32*INDEX(LC_Mult,MATCH("Canada",LC_Country,0)))+(z*SQRT(INDEX(SC_LT,MATCH("S01",SC_ID,0))*F32^2+E32^2*INDEX(SC_LTStd,MATCH("S01",SC_ID,0))^2)+E32*INDEX(SC_LT,MATCH("S01",SC_ID,0)))*(H32*INDEX(LC_Mult,MATCH("Canada",LC_Country,0)))*HoldRate,9.99E+99) | Q32: =IFERROR((z*SQRT(INDEX(SC_LT,MATCH("S01",SC_ID,0))*F32^2+E32^2*INDEX(SC_LTStd,MATCH("S01",SC_ID,0))^2)+E32*INDEX(SC_LT,MATCH("S01",SC_ID,0)))*(H32*INDEX(LC_Mult,MATCH("Canada",LC_Country,0))),0) | R32: =IF(L32=MIN(L32,N32,P32),"Mexico",IF(N32=MIN(L32,N32,P32),"USA","Canada")) | S32: =MIN(L32,N32,P32) | T32: =K32-S32 | U32: =IFERROR(T32/K32,0) | V32: =J32-IF(L32=MIN(L32,N32,P32),M32,IF(N32=MIN(L32,N32,P32),O32,Q32)) | W32: =IF(T32>0,"Nearshore: lower total cost",IF(U32>=-LC_Premium,"Nearshore candidate: small premium for resilience","Keep offshore")) | X32: =MATCH("NB-0032",P_SKU,0)
A33: =INDEX(P_SKU,$X33) | B33: =INDEX(P_Name,$X33) | C33: =INDEX(P_Sup,$X33) | D33: =INDEX(Supplier_Scorecard!$C$5:$C$12,MATCH(C33,SC_ID,0)) | E33: =INDEX(P_Demand,$X33) | F33: =INDEX(P_Std,$X33) | G33: =INDEX(P_Cost,$X33) | H33: =G33/INDEX(LC_Price,MATCH(D33,LC_Country,0)) | I33: =H33*INDEX(LC_Mult,MATCH(D33,LC_Country,0)) | J33: =(z*SQRT(INDEX(SC_LT,MATCH(C33,SC_ID,0))*F33^2+E33^2*INDEX(SC_LTStd,MATCH(C33,SC_ID,0))^2)+E33*INDEX(SC_LT,MATCH(C33,SC_ID,0)))*I33 | K33: =E33*WeeksYear*I33+(z*SQRT(INDEX(SC_LT,MATCH(C33,SC_ID,0))*F33^2+E33^2*INDEX(SC_LTStd,MATCH(C33,SC_ID,0))^2)+E33*INDEX(SC_LT,MATCH(C33,SC_ID,0)))*I33*HoldRate | L33: =IFERROR(E33*WeeksYear*(H33*INDEX(LC_Mult,MATCH("Mexico",LC_Country,0)))+(z*SQRT(INDEX(SC_LT,MATCH("S04",SC_ID,0))*F33^2+E33^2*INDEX(SC_LTStd,MATCH("S04",SC_ID,0))^2)+E33*INDEX(SC_LT,MATCH("S04",SC_ID,0)))*(H33*INDEX(LC_Mult,MATCH("Mexico",LC_Country,0)))*HoldRate,9.99E+99) | M33: =IFERROR((z*SQRT(INDEX(SC_LT,MATCH("S04",SC_ID,0))*F33^2+E33^2*INDEX(SC_LTStd,MATCH("S04",SC_ID,0))^2)+E33*INDEX(SC_LT,MATCH("S04",SC_ID,0)))*(H33*INDEX(LC_Mult,MATCH("Mexico",LC_Country,0))),0) | N33: =IFERROR(E33*WeeksYear*(H33*INDEX(LC_Mult,MATCH("USA",LC_Country,0)))+(z*SQRT(INDEX(SC_LT,MATCH("S02",SC_ID,0))*F33^2+E33^2*INDEX(SC_LTStd,MATCH("S02",SC_ID,0))^2)+E33*INDEX(SC_LT,MATCH("S02",SC_ID,0)))*(H33*INDEX(LC_Mult,MATCH("USA",LC_Country,0)))*HoldRate,9.99E+99) | O33: =IFERROR((z*SQRT(INDEX(SC_LT,MATCH("S02",SC_ID,0))*F33^2+E33^2*INDEX(SC_LTStd,MATCH("S02",SC_ID,0))^2)+E33*INDEX(SC_LT,MATCH("S02",SC_ID,0)))*(H33*INDEX(LC_Mult,MATCH("USA",LC_Country,0))),0) | P33: =IFERROR(E33*WeeksYear*(H33*INDEX(LC_Mult,MATCH("Canada",LC_Country,0)))+(z*SQRT(INDEX(SC_LT,MATCH("S01",SC_ID,0))*F33^2+E33^2*INDEX(SC_LTStd,MATCH("S01",SC_ID,0))^2)+E33*INDEX(SC_LT,MATCH("S01",SC_ID,0)))*(H33*INDEX(LC_Mult,MATCH("Canada",LC_Country,0)))*HoldRate,9.99E+99) | Q33: =IFERROR((z*SQRT(INDEX(SC_LT,MATCH("S01",SC_ID,0))*F33^2+E33^2*INDEX(SC_LTStd,MATCH("S01",SC_ID,0))^2)+E33*INDEX(SC_LT,MATCH("S01",SC_ID,0)))*(H33*INDEX(LC_Mult,MATCH("Canada",LC_Country,0))),0) | R33: =IF(L33=MIN(L33,N33,P33),"Mexico",IF(N33=MIN(L33,N33,P33),"USA","Canada")) | S33: =MIN(L33,N33,P33) | T33: =K33-S33 | U33: =IFERROR(T33/K33,0) | V33: =J33-IF(L33=MIN(L33,N33,P33),M33,IF(N33=MIN(L33,N33,P33),O33,Q33)) | W33: =IF(T33>0,"Nearshore: lower total cost",IF(U33>=-LC_Premium,"Nearshore candidate: small premium for resilience","Keep offshore")) | X33: =MATCH("NB-0033",P_SKU,0)
A34: =INDEX(P_SKU,$X34) | B34: =INDEX(P_Name,$X34) | C34: =INDEX(P_Sup,$X34) | D34: =INDEX(Supplier_Scorecard!$C$5:$C$12,MATCH(C34,SC_ID,0)) | E34: =INDEX(P_Demand,$X34) | F34: =INDEX(P_Std,$X34) | G34: =INDEX(P_Cost,$X34) | H34: =G34/INDEX(LC_Price,MATCH(D34,LC_Country,0)) | I34: =H34*INDEX(LC_Mult,MATCH(D34,LC_Country,0)) | J34: =(z*SQRT(INDEX(SC_LT,MATCH(C34,SC_ID,0))*F34^2+E34^2*INDEX(SC_LTStd,MATCH(C34,SC_ID,0))^2)+E34*INDEX(SC_LT,MATCH(C34,SC_ID,0)))*I34 | K34: =E34*WeeksYear*I34+(z*SQRT(INDEX(SC_LT,MATCH(C34,SC_ID,0))*F34^2+E34^2*INDEX(SC_LTStd,MATCH(C34,SC_ID,0))^2)+E34*INDEX(SC_LT,MATCH(C34,SC_ID,0)))*I34*HoldRate | L34: =IFERROR(E34*WeeksYear*(H34*INDEX(LC_Mult,MATCH("Mexico",LC_Country,0)))+(z*SQRT(INDEX(SC_LT,MATCH("S04",SC_ID,0))*F34^2+E34^2*INDEX(SC_LTStd,MATCH("S04",SC_ID,0))^2)+E34*INDEX(SC_LT,MATCH("S04",SC_ID,0)))*(H34*INDEX(LC_Mult,MATCH("Mexico",LC_Country,0)))*HoldRate,9.99E+99) | M34: =IFERROR((z*SQRT(INDEX(SC_LT,MATCH("S04",SC_ID,0))*F34^2+E34^2*INDEX(SC_LTStd,MATCH("S04",SC_ID,0))^2)+E34*INDEX(SC_LT,MATCH("S04",SC_ID,0)))*(H34*INDEX(LC_Mult,MATCH("Mexico",LC_Country,0))),0) | N34: =IFERROR(E34*WeeksYear*(H34*INDEX(LC_Mult,MATCH("USA",LC_Country,0)))+(z*SQRT(INDEX(SC_LT,MATCH("S02",SC_ID,0))*F34^2+E34^2*INDEX(SC_LTStd,MATCH("S02",SC_ID,0))^2)+E34*INDEX(SC_LT,MATCH("S02",SC_ID,0)))*(H34*INDEX(LC_Mult,MATCH("USA",LC_Country,0)))*HoldRate,9.99E+99) | O34: =IFERROR((z*SQRT(INDEX(SC_LT,MATCH("S02",SC_ID,0))*F34^2+E34^2*INDEX(SC_LTStd,MATCH("S02",SC_ID,0))^2)+E34*INDEX(SC_LT,MATCH("S02",SC_ID,0)))*(H34*INDEX(LC_Mult,MATCH("USA",LC_Country,0))),0) | P34: =IFERROR(E34*WeeksYear*(H34*INDEX(LC_Mult,MATCH("Canada",LC_Country,0)))+(z*SQRT(INDEX(SC_LT,MATCH("S01",SC_ID,0))*F34^2+E34^2*INDEX(SC_LTStd,MATCH("S01",SC_ID,0))^2)+E34*INDEX(SC_LT,MATCH("S01",SC_ID,0)))*(H34*INDEX(LC_Mult,MATCH("Canada",LC_Country,0)))*HoldRate,9.99E+99) | Q34: =IFERROR((z*SQRT(INDEX(SC_LT,MATCH("S01",SC_ID,0))*F34^2+E34^2*INDEX(SC_LTStd,MATCH("S01",SC_ID,0))^2)+E34*INDEX(SC_LT,MATCH("S01",SC_ID,0)))*(H34*INDEX(LC_Mult,MATCH("Canada",LC_Country,0))),0) | R34: =IF(L34=MIN(L34,N34,P34),"Mexico",IF(N34=MIN(L34,N34,P34),"USA","Canada")) | S34: =MIN(L34,N34,P34) | T34: =K34-S34 | U34: =IFERROR(T34/K34,0) | V34: =J34-IF(L34=MIN(L34,N34,P34),M34,IF(N34=MIN(L34,N34,P34),O34,Q34)) | W34: =IF(T34>0,"Nearshore: lower total cost",IF(U34>=-LC_Premium,"Nearshore candidate: small premium for resilience","Keep offshore")) | X34: =MATCH("NB-0034",P_SKU,0)
A35: =INDEX(P_SKU,$X35) | B35: =INDEX(P_Name,$X35) | C35: =INDEX(P_Sup,$X35) | D35: =INDEX(Supplier_Scorecard!$C$5:$C$12,MATCH(C35,SC_ID,0)) | E35: =INDEX(P_Demand,$X35) | F35: =INDEX(P_Std,$X35) | G35: =INDEX(P_Cost,$X35) | H35: =G35/INDEX(LC_Price,MATCH(D35,LC_Country,0)) | I35: =H35*INDEX(LC_Mult,MATCH(D35,LC_Country,0)) | J35: =(z*SQRT(INDEX(SC_LT,MATCH(C35,SC_ID,0))*F35^2+E35^2*INDEX(SC_LTStd,MATCH(C35,SC_ID,0))^2)+E35*INDEX(SC_LT,MATCH(C35,SC_ID,0)))*I35 | K35: =E35*WeeksYear*I35+(z*SQRT(INDEX(SC_LT,MATCH(C35,SC_ID,0))*F35^2+E35^2*INDEX(SC_LTStd,MATCH(C35,SC_ID,0))^2)+E35*INDEX(SC_LT,MATCH(C35,SC_ID,0)))*I35*HoldRate | L35: =IFERROR(E35*WeeksYear*(H35*INDEX(LC_Mult,MATCH("Mexico",LC_Country,0)))+(z*SQRT(INDEX(SC_LT,MATCH("S04",SC_ID,0))*F35^2+E35^2*INDEX(SC_LTStd,MATCH("S04",SC_ID,0))^2)+E35*INDEX(SC_LT,MATCH("S04",SC_ID,0)))*(H35*INDEX(LC_Mult,MATCH("Mexico",LC_Country,0)))*HoldRate,9.99E+99) | M35: =IFERROR((z*SQRT(INDEX(SC_LT,MATCH("S04",SC_ID,0))*F35^2+E35^2*INDEX(SC_LTStd,MATCH("S04",SC_ID,0))^2)+E35*INDEX(SC_LT,MATCH("S04",SC_ID,0)))*(H35*INDEX(LC_Mult,MATCH("Mexico",LC_Country,0))),0) | N35: =IFERROR(E35*WeeksYear*(H35*INDEX(LC_Mult,MATCH("USA",LC_Country,0)))+(z*SQRT(INDEX(SC_LT,MATCH("S02",SC_ID,0))*F35^2+E35^2*INDEX(SC_LTStd,MATCH("S02",SC_ID,0))^2)+E35*INDEX(SC_LT,MATCH("S02",SC_ID,0)))*(H35*INDEX(LC_Mult,MATCH("USA",LC_Country,0)))*HoldRate,9.99E+99) | O35: =IFERROR((z*SQRT(INDEX(SC_LT,MATCH("S02",SC_ID,0))*F35^2+E35^2*INDEX(SC_LTStd,MATCH("S02",SC_ID,0))^2)+E35*INDEX(SC_LT,MATCH("S02",SC_ID,0)))*(H35*INDEX(LC_Mult,MATCH("USA",LC_Country,0))),0) | P35: =IFERROR(E35*WeeksYear*(H35*INDEX(LC_Mult,MATCH("Canada",LC_Country,0)))+(z*SQRT(INDEX(SC_LT,MATCH("S01",SC_ID,0))*F35^2+E35^2*INDEX(SC_LTStd,MATCH("S01",SC_ID,0))^2)+E35*INDEX(SC_LT,MATCH("S01",SC_ID,0)))*(H35*INDEX(LC_Mult,MATCH("Canada",LC_Country,0)))*HoldRate,9.99E+99) | Q35: =IFERROR((z*SQRT(INDEX(SC_LT,MATCH("S01",SC_ID,0))*F35^2+E35^2*INDEX(SC_LTStd,MATCH("S01",SC_ID,0))^2)+E35*INDEX(SC_LT,MATCH("S01",SC_ID,0)))*(H35*INDEX(LC_Mult,MATCH("Canada",LC_Country,0))),0) | R35: =IF(L35=MIN(L35,N35,P35),"Mexico",IF(N35=MIN(L35,N35,P35),"USA","Canada")) | S35: =MIN(L35,N35,P35) | T35: =K35-S35 | U35: =IFERROR(T35/K35,0) | V35: =J35-IF(L35=MIN(L35,N35,P35),M35,IF(N35=MIN(L35,N35,P35),O35,Q35)) | W35: =IF(T35>0,"Nearshore: lower total cost",IF(U35>=-LC_Premium,"Nearshore candidate: small premium for resilience","Keep offshore")) | X35: =MATCH("NB-0036",P_SKU,0)
A36: =INDEX(P_SKU,$X36) | B36: =INDEX(P_Name,$X36) | C36: =INDEX(P_Sup,$X36) | D36: =INDEX(Supplier_Scorecard!$C$5:$C$12,MATCH(C36,SC_ID,0)) | E36: =INDEX(P_Demand,$X36) | F36: =INDEX(P_Std,$X36) | G36: =INDEX(P_Cost,$X36) | H36: =G36/INDEX(LC_Price,MATCH(D36,LC_Country,0)) | I36: =H36*INDEX(LC_Mult,MATCH(D36,LC_Country,0)) | J36: =(z*SQRT(INDEX(SC_LT,MATCH(C36,SC_ID,0))*F36^2+E36^2*INDEX(SC_LTStd,MATCH(C36,SC_ID,0))^2)+E36*INDEX(SC_LT,MATCH(C36,SC_ID,0)))*I36 | K36: =E36*WeeksYear*I36+(z*SQRT(INDEX(SC_LT,MATCH(C36,SC_ID,0))*F36^2+E36^2*INDEX(SC_LTStd,MATCH(C36,SC_ID,0))^2)+E36*INDEX(SC_LT,MATCH(C36,SC_ID,0)))*I36*HoldRate | L36: =IFERROR(E36*WeeksYear*(H36*INDEX(LC_Mult,MATCH("Mexico",LC_Country,0)))+(z*SQRT(INDEX(SC_LT,MATCH("S04",SC_ID,0))*F36^2+E36^2*INDEX(SC_LTStd,MATCH("S04",SC_ID,0))^2)+E36*INDEX(SC_LT,MATCH("S04",SC_ID,0)))*(H36*INDEX(LC_Mult,MATCH("Mexico",LC_Country,0)))*HoldRate,9.99E+99) | M36: =IFERROR((z*SQRT(INDEX(SC_LT,MATCH("S04",SC_ID,0))*F36^2+E36^2*INDEX(SC_LTStd,MATCH("S04",SC_ID,0))^2)+E36*INDEX(SC_LT,MATCH("S04",SC_ID,0)))*(H36*INDEX(LC_Mult,MATCH("Mexico",LC_Country,0))),0) | N36: =IFERROR(E36*WeeksYear*(H36*INDEX(LC_Mult,MATCH("USA",LC_Country,0)))+(z*SQRT(INDEX(SC_LT,MATCH("S02",SC_ID,0))*F36^2+E36^2*INDEX(SC_LTStd,MATCH("S02",SC_ID,0))^2)+E36*INDEX(SC_LT,MATCH("S02",SC_ID,0)))*(H36*INDEX(LC_Mult,MATCH("USA",LC_Country,0)))*HoldRate,9.99E+99) | O36: =IFERROR((z*SQRT(INDEX(SC_LT,MATCH("S02",SC_ID,0))*F36^2+E36^2*INDEX(SC_LTStd,MATCH("S02",SC_ID,0))^2)+E36*INDEX(SC_LT,MATCH("S02",SC_ID,0)))*(H36*INDEX(LC_Mult,MATCH("USA",LC_Country,0))),0) | P36: =IFERROR(E36*WeeksYear*(H36*INDEX(LC_Mult,MATCH("Canada",LC_Country,0)))+(z*SQRT(INDEX(SC_LT,MATCH("S01",SC_ID,0))*F36^2+E36^2*INDEX(SC_LTStd,MATCH("S01",SC_ID,0))^2)+E36*INDEX(SC_LT,MATCH("S01",SC_ID,0)))*(H36*INDEX(LC_Mult,MATCH("Canada",LC_Country,0)))*HoldRate,9.99E+99) | Q36: =IFERROR((z*SQRT(INDEX(SC_LT,MATCH("S01",SC_ID,0))*F36^2+E36^2*INDEX(SC_LTStd,MATCH("S01",SC_ID,0))^2)+E36*INDEX(SC_LT,MATCH("S01",SC_ID,0)))*(H36*INDEX(LC_Mult,MATCH("Canada",LC_Country,0))),0) | R36: =IF(L36=MIN(L36,N36,P36),"Mexico",IF(N36=MIN(L36,N36,P36),"USA","Canada")) | S36: =MIN(L36,N36,P36) | T36: =K36-S36 | U36: =IFERROR(T36/K36,0) | V36: =J36-IF(L36=MIN(L36,N36,P36),M36,IF(N36=MIN(L36,N36,P36),O36,Q36)) | W36: =IF(T36>0,"Nearshore: lower total cost",IF(U36>=-LC_Premium,"Nearshore candidate: small premium for resilience","Keep offshore")) | X36: =MATCH("NB-0037",P_SKU,0)
A37: =INDEX(P_SKU,$X37) | B37: =INDEX(P_Name,$X37) | C37: =INDEX(P_Sup,$X37) | D37: =INDEX(Supplier_Scorecard!$C$5:$C$12,MATCH(C37,SC_ID,0)) | E37: =INDEX(P_Demand,$X37) | F37: =INDEX(P_Std,$X37) | G37: =INDEX(P_Cost,$X37) | H37: =G37/INDEX(LC_Price,MATCH(D37,LC_Country,0)) | I37: =H37*INDEX(LC_Mult,MATCH(D37,LC_Country,0)) | J37: =(z*SQRT(INDEX(SC_LT,MATCH(C37,SC_ID,0))*F37^2+E37^2*INDEX(SC_LTStd,MATCH(C37,SC_ID,0))^2)+E37*INDEX(SC_LT,MATCH(C37,SC_ID,0)))*I37 | K37: =E37*WeeksYear*I37+(z*SQRT(INDEX(SC_LT,MATCH(C37,SC_ID,0))*F37^2+E37^2*INDEX(SC_LTStd,MATCH(C37,SC_ID,0))^2)+E37*INDEX(SC_LT,MATCH(C37,SC_ID,0)))*I37*HoldRate | L37: =IFERROR(E37*WeeksYear*(H37*INDEX(LC_Mult,MATCH("Mexico",LC_Country,0)))+(z*SQRT(INDEX(SC_LT,MATCH("S04",SC_ID,0))*F37^2+E37^2*INDEX(SC_LTStd,MATCH("S04",SC_ID,0))^2)+E37*INDEX(SC_LT,MATCH("S04",SC_ID,0)))*(H37*INDEX(LC_Mult,MATCH("Mexico",LC_Country,0)))*HoldRate,9.99E+99) | M37: =IFERROR((z*SQRT(INDEX(SC_LT,MATCH("S04",SC_ID,0))*F37^2+E37^2*INDEX(SC_LTStd,MATCH("S04",SC_ID,0))^2)+E37*INDEX(SC_LT,MATCH("S04",SC_ID,0)))*(H37*INDEX(LC_Mult,MATCH("Mexico",LC_Country,0))),0) | N37: =IFERROR(E37*WeeksYear*(H37*INDEX(LC_Mult,MATCH("USA",LC_Country,0)))+(z*SQRT(INDEX(SC_LT,MATCH("S02",SC_ID,0))*F37^2+E37^2*INDEX(SC_LTStd,MATCH("S02",SC_ID,0))^2)+E37*INDEX(SC_LT,MATCH("S02",SC_ID,0)))*(H37*INDEX(LC_Mult,MATCH("USA",LC_Country,0)))*HoldRate,9.99E+99) | O37: =IFERROR((z*SQRT(INDEX(SC_LT,MATCH("S02",SC_ID,0))*F37^2+E37^2*INDEX(SC_LTStd,MATCH("S02",SC_ID,0))^2)+E37*INDEX(SC_LT,MATCH("S02",SC_ID,0)))*(H37*INDEX(LC_Mult,MATCH("USA",LC_Country,0))),0) | P37: =IFERROR(E37*WeeksYear*(H37*INDEX(LC_Mult,MATCH("Canada",LC_Country,0)))+(z*SQRT(INDEX(SC_LT,MATCH("S01",SC_ID,0))*F37^2+E37^2*INDEX(SC_LTStd,MATCH("S01",SC_ID,0))^2)+E37*INDEX(SC_LT,MATCH("S01",SC_ID,0)))*(H37*INDEX(LC_Mult,MATCH("Canada",LC_Country,0)))*HoldRate,9.99E+99) | Q37: =IFERROR((z*SQRT(INDEX(SC_LT,MATCH("S01",SC_ID,0))*F37^2+E37^2*INDEX(SC_LTStd,MATCH("S01",SC_ID,0))^2)+E37*INDEX(SC_LT,MATCH("S01",SC_ID,0)))*(H37*INDEX(LC_Mult,MATCH("Canada",LC_Country,0))),0) | R37: =IF(L37=MIN(L37,N37,P37),"Mexico",IF(N37=MIN(L37,N37,P37),"USA","Canada")) | S37: =MIN(L37,N37,P37) | T37: =K37-S37 | U37: =IFERROR(T37/K37,0) | V37: =J37-IF(L37=MIN(L37,N37,P37),M37,IF(N37=MIN(L37,N37,P37),O37,Q37)) | W37: =IF(T37>0,"Nearshore: lower total cost",IF(U37>=-LC_Premium,"Nearshore candidate: small premium for resilience","Keep offshore")) | X37: =MATCH("NB-0038",P_SKU,0)
A38: =INDEX(P_SKU,$X38) | B38: =INDEX(P_Name,$X38) | C38: =INDEX(P_Sup,$X38) | D38: =INDEX(Supplier_Scorecard!$C$5:$C$12,MATCH(C38,SC_ID,0)) | E38: =INDEX(P_Demand,$X38) | F38: =INDEX(P_Std,$X38) | G38: =INDEX(P_Cost,$X38) | H38: =G38/INDEX(LC_Price,MATCH(D38,LC_Country,0)) | I38: =H38*INDEX(LC_Mult,MATCH(D38,LC_Country,0)) | J38: =(z*SQRT(INDEX(SC_LT,MATCH(C38,SC_ID,0))*F38^2+E38^2*INDEX(SC_LTStd,MATCH(C38,SC_ID,0))^2)+E38*INDEX(SC_LT,MATCH(C38,SC_ID,0)))*I38 | K38: =E38*WeeksYear*I38+(z*SQRT(INDEX(SC_LT,MATCH(C38,SC_ID,0))*F38^2+E38^2*INDEX(SC_LTStd,MATCH(C38,SC_ID,0))^2)+E38*INDEX(SC_LT,MATCH(C38,SC_ID,0)))*I38*HoldRate | L38: =IFERROR(E38*WeeksYear*(H38*INDEX(LC_Mult,MATCH("Mexico",LC_Country,0)))+(z*SQRT(INDEX(SC_LT,MATCH("S04",SC_ID,0))*F38^2+E38^2*INDEX(SC_LTStd,MATCH("S04",SC_ID,0))^2)+E38*INDEX(SC_LT,MATCH("S04",SC_ID,0)))*(H38*INDEX(LC_Mult,MATCH("Mexico",LC_Country,0)))*HoldRate,9.99E+99) | M38: =IFERROR((z*SQRT(INDEX(SC_LT,MATCH("S04",SC_ID,0))*F38^2+E38^2*INDEX(SC_LTStd,MATCH("S04",SC_ID,0))^2)+E38*INDEX(SC_LT,MATCH("S04",SC_ID,0)))*(H38*INDEX(LC_Mult,MATCH("Mexico",LC_Country,0))),0) | N38: =IFERROR(E38*WeeksYear*(H38*INDEX(LC_Mult,MATCH("USA",LC_Country,0)))+(z*SQRT(INDEX(SC_LT,MATCH("S02",SC_ID,0))*F38^2+E38^2*INDEX(SC_LTStd,MATCH("S02",SC_ID,0))^2)+E38*INDEX(SC_LT,MATCH("S02",SC_ID,0)))*(H38*INDEX(LC_Mult,MATCH("USA",LC_Country,0)))*HoldRate,9.99E+99) | O38: =IFERROR((z*SQRT(INDEX(SC_LT,MATCH("S02",SC_ID,0))*F38^2+E38^2*INDEX(SC_LTStd,MATCH("S02",SC_ID,0))^2)+E38*INDEX(SC_LT,MATCH("S02",SC_ID,0)))*(H38*INDEX(LC_Mult,MATCH("USA",LC_Country,0))),0) | P38: =IFERROR(E38*WeeksYear*(H38*INDEX(LC_Mult,MATCH("Canada",LC_Country,0)))+(z*SQRT(INDEX(SC_LT,MATCH("S01",SC_ID,0))*F38^2+E38^2*INDEX(SC_LTStd,MATCH("S01",SC_ID,0))^2)+E38*INDEX(SC_LT,MATCH("S01",SC_ID,0)))*(H38*INDEX(LC_Mult,MATCH("Canada",LC_Country,0)))*HoldRate,9.99E+99) | Q38: =IFERROR((z*SQRT(INDEX(SC_LT,MATCH("S01",SC_ID,0))*F38^2+E38^2*INDEX(SC_LTStd,MATCH("S01",SC_ID,0))^2)+E38*INDEX(SC_LT,MATCH("S01",SC_ID,0)))*(H38*INDEX(LC_Mult,MATCH("Canada",LC_Country,0))),0) | R38: =IF(L38=MIN(L38,N38,P38),"Mexico",IF(N38=MIN(L38,N38,P38),"USA","Canada")) | S38: =MIN(L38,N38,P38) | T38: =K38-S38 | U38: =IFERROR(T38/K38,0) | V38: =J38-IF(L38=MIN(L38,N38,P38),M38,IF(N38=MIN(L38,N38,P38),O38,Q38)) | W38: =IF(T38>0,"Nearshore: lower total cost",IF(U38>=-LC_Premium,"Nearshore candidate: small premium for resilience","Keep offshore")) | X38: =MATCH("NB-0039",P_SKU,0)
A39: =INDEX(P_SKU,$X39) | B39: =INDEX(P_Name,$X39) | C39: =INDEX(P_Sup,$X39) | D39: =INDEX(Supplier_Scorecard!$C$5:$C$12,MATCH(C39,SC_ID,0)) | E39: =INDEX(P_Demand,$X39) | F39: =INDEX(P_Std,$X39) | G39: =INDEX(P_Cost,$X39) | H39: =G39/INDEX(LC_Price,MATCH(D39,LC_Country,0)) | I39: =H39*INDEX(LC_Mult,MATCH(D39,LC_Country,0)) | J39: =(z*SQRT(INDEX(SC_LT,MATCH(C39,SC_ID,0))*F39^2+E39^2*INDEX(SC_LTStd,MATCH(C39,SC_ID,0))^2)+E39*INDEX(SC_LT,MATCH(C39,SC_ID,0)))*I39 | K39: =E39*WeeksYear*I39+(z*SQRT(INDEX(SC_LT,MATCH(C39,SC_ID,0))*F39^2+E39^2*INDEX(SC_LTStd,MATCH(C39,SC_ID,0))^2)+E39*INDEX(SC_LT,MATCH(C39,SC_ID,0)))*I39*HoldRate | L39: =IFERROR(E39*WeeksYear*(H39*INDEX(LC_Mult,MATCH("Mexico",LC_Country,0)))+(z*SQRT(INDEX(SC_LT,MATCH("S04",SC_ID,0))*F39^2+E39^2*INDEX(SC_LTStd,MATCH("S04",SC_ID,0))^2)+E39*INDEX(SC_LT,MATCH("S04",SC_ID,0)))*(H39*INDEX(LC_Mult,MATCH("Mexico",LC_Country,0)))*HoldRate,9.99E+99) | M39: =IFERROR((z*SQRT(INDEX(SC_LT,MATCH("S04",SC_ID,0))*F39^2+E39^2*INDEX(SC_LTStd,MATCH("S04",SC_ID,0))^2)+E39*INDEX(SC_LT,MATCH("S04",SC_ID,0)))*(H39*INDEX(LC_Mult,MATCH("Mexico",LC_Country,0))),0) | N39: =IFERROR(E39*WeeksYear*(H39*INDEX(LC_Mult,MATCH("USA",LC_Country,0)))+(z*SQRT(INDEX(SC_LT,MATCH("S02",SC_ID,0))*F39^2+E39^2*INDEX(SC_LTStd,MATCH("S02",SC_ID,0))^2)+E39*INDEX(SC_LT,MATCH("S02",SC_ID,0)))*(H39*INDEX(LC_Mult,MATCH("USA",LC_Country,0)))*HoldRate,9.99E+99) | O39: =IFERROR((z*SQRT(INDEX(SC_LT,MATCH("S02",SC_ID,0))*F39^2+E39^2*INDEX(SC_LTStd,MATCH("S02",SC_ID,0))^2)+E39*INDEX(SC_LT,MATCH("S02",SC_ID,0)))*(H39*INDEX(LC_Mult,MATCH("USA",LC_Country,0))),0) | P39: =IFERROR(E39*WeeksYear*(H39*INDEX(LC_Mult,MATCH("Canada",LC_Country,0)))+(z*SQRT(INDEX(SC_LT,MATCH("S01",SC_ID,0))*F39^2+E39^2*INDEX(SC_LTStd,MATCH("S01",SC_ID,0))^2)+E39*INDEX(SC_LT,MATCH("S01",SC_ID,0)))*(H39*INDEX(LC_Mult,MATCH("Canada",LC_Country,0)))*HoldRate,9.99E+99) | Q39: =IFERROR((z*SQRT(INDEX(SC_LT,MATCH("S01",SC_ID,0))*F39^2+E39^2*INDEX(SC_LTStd,MATCH("S01",SC_ID,0))^2)+E39*INDEX(SC_LT,MATCH("S01",SC_ID,0)))*(H39*INDEX(LC_Mult,MATCH("Canada",LC_Country,0))),0) | R39: =IF(L39=MIN(L39,N39,P39),"Mexico",IF(N39=MIN(L39,N39,P39),"USA","Canada")) | S39: =MIN(L39,N39,P39) | T39: =K39-S39 | U39: =IFERROR(T39/K39,0) | V39: =J39-IF(L39=MIN(L39,N39,P39),M39,IF(N39=MIN(L39,N39,P39),O39,Q39)) | W39: =IF(T39>0,"Nearshore: lower total cost",IF(U39>=-LC_Premium,"Nearshore candidate: small premium for resilience","Keep offshore")) | X39: =MATCH("NB-0043",P_SKU,0)
A40: =INDEX(P_SKU,$X40) | B40: =INDEX(P_Name,$X40) | C40: =INDEX(P_Sup,$X40) | D40: =INDEX(Supplier_Scorecard!$C$5:$C$12,MATCH(C40,SC_ID,0)) | E40: =INDEX(P_Demand,$X40) | F40: =INDEX(P_Std,$X40) | G40: =INDEX(P_Cost,$X40) | H40: =G40/INDEX(LC_Price,MATCH(D40,LC_Country,0)) | I40: =H40*INDEX(LC_Mult,MATCH(D40,LC_Country,0)) | J40: =(z*SQRT(INDEX(SC_LT,MATCH(C40,SC_ID,0))*F40^2+E40^2*INDEX(SC_LTStd,MATCH(C40,SC_ID,0))^2)+E40*INDEX(SC_LT,MATCH(C40,SC_ID,0)))*I40 | K40: =E40*WeeksYear*I40+(z*SQRT(INDEX(SC_LT,MATCH(C40,SC_ID,0))*F40^2+E40^2*INDEX(SC_LTStd,MATCH(C40,SC_ID,0))^2)+E40*INDEX(SC_LT,MATCH(C40,SC_ID,0)))*I40*HoldRate | L40: =IFERROR(E40*WeeksYear*(H40*INDEX(LC_Mult,MATCH("Mexico",LC_Country,0)))+(z*SQRT(INDEX(SC_LT,MATCH("S04",SC_ID,0))*F40^2+E40^2*INDEX(SC_LTStd,MATCH("S04",SC_ID,0))^2)+E40*INDEX(SC_LT,MATCH("S04",SC_ID,0)))*(H40*INDEX(LC_Mult,MATCH("Mexico",LC_Country,0)))*HoldRate,9.99E+99) | M40: =IFERROR((z*SQRT(INDEX(SC_LT,MATCH("S04",SC_ID,0))*F40^2+E40^2*INDEX(SC_LTStd,MATCH("S04",SC_ID,0))^2)+E40*INDEX(SC_LT,MATCH("S04",SC_ID,0)))*(H40*INDEX(LC_Mult,MATCH("Mexico",LC_Country,0))),0) | N40: =IFERROR(E40*WeeksYear*(H40*INDEX(LC_Mult,MATCH("USA",LC_Country,0)))+(z*SQRT(INDEX(SC_LT,MATCH("S02",SC_ID,0))*F40^2+E40^2*INDEX(SC_LTStd,MATCH("S02",SC_ID,0))^2)+E40*INDEX(SC_LT,MATCH("S02",SC_ID,0)))*(H40*INDEX(LC_Mult,MATCH("USA",LC_Country,0)))*HoldRate,9.99E+99) | O40: =IFERROR((z*SQRT(INDEX(SC_LT,MATCH("S02",SC_ID,0))*F40^2+E40^2*INDEX(SC_LTStd,MATCH("S02",SC_ID,0))^2)+E40*INDEX(SC_LT,MATCH("S02",SC_ID,0)))*(H40*INDEX(LC_Mult,MATCH("USA",LC_Country,0))),0) | P40: =IFERROR(E40*WeeksYear*(H40*INDEX(LC_Mult,MATCH("Canada",LC_Country,0)))+(z*SQRT(INDEX(SC_LT,MATCH("S01",SC_ID,0))*F40^2+E40^2*INDEX(SC_LTStd,MATCH("S01",SC_ID,0))^2)+E40*INDEX(SC_LT,MATCH("S01",SC_ID,0)))*(H40*INDEX(LC_Mult,MATCH("Canada",LC_Country,0)))*HoldRate,9.99E+99) | Q40: =IFERROR((z*SQRT(INDEX(SC_LT,MATCH("S01",SC_ID,0))*F40^2+E40^2*INDEX(SC_LTStd,MATCH("S01",SC_ID,0))^2)+E40*INDEX(SC_LT,MATCH("S01",SC_ID,0)))*(H40*INDEX(LC_Mult,MATCH("Canada",LC_Country,0))),0) | R40: =IF(L40=MIN(L40,N40,P40),"Mexico",IF(N40=MIN(L40,N40,P40),"USA","Canada")) | S40: =MIN(L40,N40,P40) | T40: =K40-S40 | U40: =IFERROR(T40/K40,0) | V40: =J40-IF(L40=MIN(L40,N40,P40),M40,IF(N40=MIN(L40,N40,P40),O40,Q40)) | W40: =IF(T40>0,"Nearshore: lower total cost",IF(U40>=-LC_Premium,"Nearshore candidate: small premium for resilience","Keep offshore")) | X40: =MATCH("NB-0044",P_SKU,0)
A41: =INDEX(P_SKU,$X41) | B41: =INDEX(P_Name,$X41) | C41: =INDEX(P_Sup,$X41) | D41: =INDEX(Supplier_Scorecard!$C$5:$C$12,MATCH(C41,SC_ID,0)) | E41: =INDEX(P_Demand,$X41) | F41: =INDEX(P_Std,$X41) | G41: =INDEX(P_Cost,$X41) | H41: =G41/INDEX(LC_Price,MATCH(D41,LC_Country,0)) | I41: =H41*INDEX(LC_Mult,MATCH(D41,LC_Country,0)) | J41: =(z*SQRT(INDEX(SC_LT,MATCH(C41,SC_ID,0))*F41^2+E41^2*INDEX(SC_LTStd,MATCH(C41,SC_ID,0))^2)+E41*INDEX(SC_LT,MATCH(C41,SC_ID,0)))*I41 | K41: =E41*WeeksYear*I41+(z*SQRT(INDEX(SC_LT,MATCH(C41,SC_ID,0))*F41^2+E41^2*INDEX(SC_LTStd,MATCH(C41,SC_ID,0))^2)+E41*INDEX(SC_LT,MATCH(C41,SC_ID,0)))*I41*HoldRate | L41: =IFERROR(E41*WeeksYear*(H41*INDEX(LC_Mult,MATCH("Mexico",LC_Country,0)))+(z*SQRT(INDEX(SC_LT,MATCH("S04",SC_ID,0))*F41^2+E41^2*INDEX(SC_LTStd,MATCH("S04",SC_ID,0))^2)+E41*INDEX(SC_LT,MATCH("S04",SC_ID,0)))*(H41*INDEX(LC_Mult,MATCH("Mexico",LC_Country,0)))*HoldRate,9.99E+99) | M41: =IFERROR((z*SQRT(INDEX(SC_LT,MATCH("S04",SC_ID,0))*F41^2+E41^2*INDEX(SC_LTStd,MATCH("S04",SC_ID,0))^2)+E41*INDEX(SC_LT,MATCH("S04",SC_ID,0)))*(H41*INDEX(LC_Mult,MATCH("Mexico",LC_Country,0))),0) | N41: =IFERROR(E41*WeeksYear*(H41*INDEX(LC_Mult,MATCH("USA",LC_Country,0)))+(z*SQRT(INDEX(SC_LT,MATCH("S02",SC_ID,0))*F41^2+E41^2*INDEX(SC_LTStd,MATCH("S02",SC_ID,0))^2)+E41*INDEX(SC_LT,MATCH("S02",SC_ID,0)))*(H41*INDEX(LC_Mult,MATCH("USA",LC_Country,0)))*HoldRate,9.99E+99) | O41: =IFERROR((z*SQRT(INDEX(SC_LT,MATCH("S02",SC_ID,0))*F41^2+E41^2*INDEX(SC_LTStd,MATCH("S02",SC_ID,0))^2)+E41*INDEX(SC_LT,MATCH("S02",SC_ID,0)))*(H41*INDEX(LC_Mult,MATCH("USA",LC_Country,0))),0) | P41: =IFERROR(E41*WeeksYear*(H41*INDEX(LC_Mult,MATCH("Canada",LC_Country,0)))+(z*SQRT(INDEX(SC_LT,MATCH("S01",SC_ID,0))*F41^2+E41^2*INDEX(SC_LTStd,MATCH("S01",SC_ID,0))^2)+E41*INDEX(SC_LT,MATCH("S01",SC_ID,0)))*(H41*INDEX(LC_Mult,MATCH("Canada",LC_Country,0)))*HoldRate,9.99E+99) | Q41: =IFERROR((z*SQRT(INDEX(SC_LT,MATCH("S01",SC_ID,0))*F41^2+E41^2*INDEX(SC_LTStd,MATCH("S01",SC_ID,0))^2)+E41*INDEX(SC_LT,MATCH("S01",SC_ID,0)))*(H41*INDEX(LC_Mult,MATCH("Canada",LC_Country,0))),0) | R41: =IF(L41=MIN(L41,N41,P41),"Mexico",IF(N41=MIN(L41,N41,P41),"USA","Canada")) | S41: =MIN(L41,N41,P41) | T41: =K41-S41 | U41: =IFERROR(T41/K41,0) | V41: =J41-IF(L41=MIN(L41,N41,P41),M41,IF(N41=MIN(L41,N41,P41),O41,Q41)) | W41: =IF(T41>0,"Nearshore: lower total cost",IF(U41>=-LC_Premium,"Nearshore candidate: small premium for resilience","Keep offshore")) | X41: =MATCH("NB-0045",P_SKU,0)
A42: =INDEX(P_SKU,$X42) | B42: =INDEX(P_Name,$X42) | C42: =INDEX(P_Sup,$X42) | D42: =INDEX(Supplier_Scorecard!$C$5:$C$12,MATCH(C42,SC_ID,0)) | E42: =INDEX(P_Demand,$X42) | F42: =INDEX(P_Std,$X42) | G42: =INDEX(P_Cost,$X42) | H42: =G42/INDEX(LC_Price,MATCH(D42,LC_Country,0)) | I42: =H42*INDEX(LC_Mult,MATCH(D42,LC_Country,0)) | J42: =(z*SQRT(INDEX(SC_LT,MATCH(C42,SC_ID,0))*F42^2+E42^2*INDEX(SC_LTStd,MATCH(C42,SC_ID,0))^2)+E42*INDEX(SC_LT,MATCH(C42,SC_ID,0)))*I42 | K42: =E42*WeeksYear*I42+(z*SQRT(INDEX(SC_LT,MATCH(C42,SC_ID,0))*F42^2+E42^2*INDEX(SC_LTStd,MATCH(C42,SC_ID,0))^2)+E42*INDEX(SC_LT,MATCH(C42,SC_ID,0)))*I42*HoldRate | L42: =IFERROR(E42*WeeksYear*(H42*INDEX(LC_Mult,MATCH("Mexico",LC_Country,0)))+(z*SQRT(INDEX(SC_LT,MATCH("S04",SC_ID,0))*F42^2+E42^2*INDEX(SC_LTStd,MATCH("S04",SC_ID,0))^2)+E42*INDEX(SC_LT,MATCH("S04",SC_ID,0)))*(H42*INDEX(LC_Mult,MATCH("Mexico",LC_Country,0)))*HoldRate,9.99E+99) | M42: =IFERROR((z*SQRT(INDEX(SC_LT,MATCH("S04",SC_ID,0))*F42^2+E42^2*INDEX(SC_LTStd,MATCH("S04",SC_ID,0))^2)+E42*INDEX(SC_LT,MATCH("S04",SC_ID,0)))*(H42*INDEX(LC_Mult,MATCH("Mexico",LC_Country,0))),0) | N42: =IFERROR(E42*WeeksYear*(H42*INDEX(LC_Mult,MATCH("USA",LC_Country,0)))+(z*SQRT(INDEX(SC_LT,MATCH("S02",SC_ID,0))*F42^2+E42^2*INDEX(SC_LTStd,MATCH("S02",SC_ID,0))^2)+E42*INDEX(SC_LT,MATCH("S02",SC_ID,0)))*(H42*INDEX(LC_Mult,MATCH("USA",LC_Country,0)))*HoldRate,9.99E+99) | O42: =IFERROR((z*SQRT(INDEX(SC_LT,MATCH("S02",SC_ID,0))*F42^2+E42^2*INDEX(SC_LTStd,MATCH("S02",SC_ID,0))^2)+E42*INDEX(SC_LT,MATCH("S02",SC_ID,0)))*(H42*INDEX(LC_Mult,MATCH("USA",LC_Country,0))),0) | P42: =IFERROR(E42*WeeksYear*(H42*INDEX(LC_Mult,MATCH("Canada",LC_Country,0)))+(z*SQRT(INDEX(SC_LT,MATCH("S01",SC_ID,0))*F42^2+E42^2*INDEX(SC_LTStd,MATCH("S01",SC_ID,0))^2)+E42*INDEX(SC_LT,MATCH("S01",SC_ID,0)))*(H42*INDEX(LC_Mult,MATCH("Canada",LC_Country,0)))*HoldRate,9.99E+99) | Q42: =IFERROR((z*SQRT(INDEX(SC_LT,MATCH("S01",SC_ID,0))*F42^2+E42^2*INDEX(SC_LTStd,MATCH("S01",SC_ID,0))^2)+E42*INDEX(SC_LT,MATCH("S01",SC_ID,0)))*(H42*INDEX(LC_Mult,MATCH("Canada",LC_Country,0))),0) | R42: =IF(L42=MIN(L42,N42,P42),"Mexico",IF(N42=MIN(L42,N42,P42),"USA","Canada")) | S42: =MIN(L42,N42,P42) | T42: =K42-S42 | U42: =IFERROR(T42/K42,0) | V42: =J42-IF(L42=MIN(L42,N42,P42),M42,IF(N42=MIN(L42,N42,P42),O42,Q42)) | W42: =IF(T42>0,"Nearshore: lower total cost",IF(U42>=-LC_Premium,"Nearshore candidate: small premium for resilience","Keep offshore")) | X42: =MATCH("NB-0046",P_SKU,0)
A43: =INDEX(P_SKU,$X43) | B43: =INDEX(P_Name,$X43) | C43: =INDEX(P_Sup,$X43) | D43: =INDEX(Supplier_Scorecard!$C$5:$C$12,MATCH(C43,SC_ID,0)) | E43: =INDEX(P_Demand,$X43) | F43: =INDEX(P_Std,$X43) | G43: =INDEX(P_Cost,$X43) | H43: =G43/INDEX(LC_Price,MATCH(D43,LC_Country,0)) | I43: =H43*INDEX(LC_Mult,MATCH(D43,LC_Country,0)) | J43: =(z*SQRT(INDEX(SC_LT,MATCH(C43,SC_ID,0))*F43^2+E43^2*INDEX(SC_LTStd,MATCH(C43,SC_ID,0))^2)+E43*INDEX(SC_LT,MATCH(C43,SC_ID,0)))*I43 | K43: =E43*WeeksYear*I43+(z*SQRT(INDEX(SC_LT,MATCH(C43,SC_ID,0))*F43^2+E43^2*INDEX(SC_LTStd,MATCH(C43,SC_ID,0))^2)+E43*INDEX(SC_LT,MATCH(C43,SC_ID,0)))*I43*HoldRate | L43: =IFERROR(E43*WeeksYear*(H43*INDEX(LC_Mult,MATCH("Mexico",LC_Country,0)))+(z*SQRT(INDEX(SC_LT,MATCH("S04",SC_ID,0))*F43^2+E43^2*INDEX(SC_LTStd,MATCH("S04",SC_ID,0))^2)+E43*INDEX(SC_LT,MATCH("S04",SC_ID,0)))*(H43*INDEX(LC_Mult,MATCH("Mexico",LC_Country,0)))*HoldRate,9.99E+99) | M43: =IFERROR((z*SQRT(INDEX(SC_LT,MATCH("S04",SC_ID,0))*F43^2+E43^2*INDEX(SC_LTStd,MATCH("S04",SC_ID,0))^2)+E43*INDEX(SC_LT,MATCH("S04",SC_ID,0)))*(H43*INDEX(LC_Mult,MATCH("Mexico",LC_Country,0))),0) | N43: =IFERROR(E43*WeeksYear*(H43*INDEX(LC_Mult,MATCH("USA",LC_Country,0)))+(z*SQRT(INDEX(SC_LT,MATCH("S02",SC_ID,0))*F43^2+E43^2*INDEX(SC_LTStd,MATCH("S02",SC_ID,0))^2)+E43*INDEX(SC_LT,MATCH("S02",SC_ID,0)))*(H43*INDEX(LC_Mult,MATCH("USA",LC_Country,0)))*HoldRate,9.99E+99) | O43: =IFERROR((z*SQRT(INDEX(SC_LT,MATCH("S02",SC_ID,0))*F43^2+E43^2*INDEX(SC_LTStd,MATCH("S02",SC_ID,0))^2)+E43*INDEX(SC_LT,MATCH("S02",SC_ID,0)))*(H43*INDEX(LC_Mult,MATCH("USA",LC_Country,0))),0) | P43: =IFERROR(E43*WeeksYear*(H43*INDEX(LC_Mult,MATCH("Canada",LC_Country,0)))+(z*SQRT(INDEX(SC_LT,MATCH("S01",SC_ID,0))*F43^2+E43^2*INDEX(SC_LTStd,MATCH("S01",SC_ID,0))^2)+E43*INDEX(SC_LT,MATCH("S01",SC_ID,0)))*(H43*INDEX(LC_Mult,MATCH("Canada",LC_Country,0)))*HoldRate,9.99E+99) | Q43: =IFERROR((z*SQRT(INDEX(SC_LT,MATCH("S01",SC_ID,0))*F43^2+E43^2*INDEX(SC_LTStd,MATCH("S01",SC_ID,0))^2)+E43*INDEX(SC_LT,MATCH("S01",SC_ID,0)))*(H43*INDEX(LC_Mult,MATCH("Canada",LC_Country,0))),0) | R43: =IF(L43=MIN(L43,N43,P43),"Mexico",IF(N43=MIN(L43,N43,P43),"USA","Canada")) | S43: =MIN(L43,N43,P43) | T43: =K43-S43 | U43: =IFERROR(T43/K43,0) | V43: =J43-IF(L43=MIN(L43,N43,P43),M43,IF(N43=MIN(L43,N43,P43),O43,Q43)) | W43: =IF(T43>0,"Nearshore: lower total cost",IF(U43>=-LC_Premium,"Nearshore candidate: small premium for resilience","Keep offshore")) | X43: =MATCH("NB-0047",P_SKU,0)

Sheet Products
A1: SKU | B1: Product | C1: Category | D1: Unit cost (CAD) | E1: Supplier ID
A2: NB-0001 | B2: Nitrile Exam Gloves M | C2: PPE | D2: 35.73 | E2: S08
A3: NB-0002 | B3: Nitrile Exam Gloves L | C3: PPE | D3: 35.21 | E3: S07
A4: NB-0003 | B4: Vinyl Gloves S | C4: PPE | D4: 42 | E4: S02
A5: NB-0004 | B5: Surgical Mask Level 2 | C5: PPE | D5: 6.62 | E5: S08
A6: NB-0005 | B6: N95 Respirator | C6: PPE | D6: 43.8 | E6: S07
A7: NB-0006 | B7: Isolation Gown | C7: PPE | D7: 10.33 | E7: S02
A8: NB-0007 | B8: Face Shield | C8: PPE | D8: 19.19 | E8: S05
A9: NB-0008 | B9: Shoe Covers | C9: PPE | D9: 31.46 | E9: S07
A10: NB-0009 | B10: Bouffant Cap | C10: PPE | D10: 38.12 | E10: S07
A11: NB-0010 | B11: Latex Gloves M | C11: PPE | D11: 12.2 | E11: S02
A12: NB-0011 | B12: Gauze Pad 4x4 | C12: Wound Care | D12: 48.16 | E12: S02
A13: NB-0012 | B13: Foam Dressing 10cm | C13: Wound Care | D13: 31.44 | E13: S02
... A50: NB-0049 | B50: Instrument Wrap | C50: Sterilization | D50: 22.29 | E50: S01

Sheet Suppliers
A1: Supplier ID | B1: Supplier | C1: Country | D1: Promised lead time (wks)
A2: S01 | B2: Maple Leaf Medical Mfg | C2: Canada | D2: 2
A3: S02 | B3: Great Lakes Health Products | C3: USA | D3: 3
A4: S03 | B4: Rhein MedTech GmbH | C4: Germany | D4: 6
A5: S04 | B5: Monterrey Surgical SA | C5: Mexico | D5: 4
A6: S05 | B6: Penang Glove Industries | C6: Malaysia | D6: 8
A7: S06 | B7: Chennai Healthcare Exports | C7: India | D7: 9
A8: S07 | B8: Saigon Textile Medical | C8: Vietnam | D8: 8
A9: S08 | B9: Shenzhen Diagnostics Co | C9: China | D9: 10

Sheet Weekly_Demand
A1: Week start | B1: SKU | C1: Units | D1: In last 52 wks (1/0) | E1: Units² (last 52 wks)
A2: 45292 | B2: NB-0001 | C2: 119 | D2: =IF(A2>LastWeek-364,1,0) | E2: =C2^2*D2
A3: 45299 | B3: NB-0001 | C3: 138 | D3: =IF(A3>LastWeek-364,1,0) | E3: =C3^2*D3
A4: 45306 | B4: NB-0001 | C4: 108 | D4: =IF(A4>LastWeek-364,1,0) | E4: =C4^2*D4
A5: 45313 | B5: NB-0001 | C5: 114 | D5: =IF(A5>LastWeek-364,1,0) | E5: =C5^2*D5
A6: 45320 | B6: NB-0001 | C6: 103 | D6: =IF(A6>LastWeek-364,1,0) | E6: =C6^2*D6
A7: 45327 | B7: NB-0001 | C7: 100 | D7: =IF(A7>LastWeek-364,1,0) | E7: =C7^2*D7
A8: 45334 | B8: NB-0001 | C8: 74 | D8: =IF(A8>LastWeek-364,1,0) | E8: =C8^2*D8
A9: 45341 | B9: NB-0001 | C9: 107 | D9: =IF(A9>LastWeek-364,1,0) | E9: =C9^2*D9
A10: 45348 | B10: NB-0001 | C10: 91 | D10: =IF(A10>LastWeek-364,1,0) | E10: =C10^2*D10
A11: 45355 | B11: NB-0001 | C11: 157 | D11: =IF(A11>LastWeek-364,1,0) | E11: =C11^2*D11
A12: 45362 | B12: NB-0001 | C12: 137 | D12: =IF(A12>LastWeek-364,1,0) | E12: =C12^2*D12
A13: 45369 | B13: NB-0001 | C13: 98 | D13: =IF(A13>LastWeek-364,1,0) | E13: =C13^2*D13
... A5097: 46013 | B5097: NB-0049 | C5097: 23 | D5097: =IF(A5097>LastWeek-364,1,0) | E5097: =C5097^2*D5097

Sheet Purchase_Orders
A1: PO ID | B1: Supplier ID | C1: SKU | D1: Order date | E1: Promised date | F1: Received date | G1: Qty ordered | H1: Qty received | I1: Qty defective | J1: PO value (CAD) | K1: Lead time (wks) | L1: Lead time² | M1: On time (1/0) | N1: Days late
A2: PO-00001 | B2: S08 | C2: NB-0001 | D2: 45292 | E2: 45362 | F2: 45360 | G2: 283 | H2: 283 | I2: 8 | J2: 10111.59 | K2: =(F2-D2)/7 | L2: =K2^2 | M2: =IF(F2<=E2,1,0) | N2: =MAX(0,F2-E2)
A3: PO-00002 | B3: S08 | C3: NB-0001 | D3: 45323 | E3: 45393 | F3: 45392 | G3: 293 | H3: 293 | I3: 12 | J3: 10468.89 | K3: =(F3-D3)/7 | L3: =K3^2 | M3: =IF(F3<=E3,1,0) | N3: =MAX(0,F3-E3)
A4: PO-00003 | B4: S08 | C4: NB-0001 | D4: 45352 | E4: 45422 | F4: 45420 | G4: 301 | H4: 301 | I4: 7 | J4: 10754.73 | K4: =(F4-D4)/7 | L4: =K4^2 | M4: =IF(F4<=E4,1,0) | N4: =MAX(0,F4-E4)
A5: PO-00004 | B5: S08 | C5: NB-0001 | D5: 45377 | E5: 45447 | F5: 45446 | G5: 280 | H5: 280 | I5: 4 | J5: 10004.4 | K5: =(F5-D5)/7 | L5: =K5^2 | M5: =IF(F5<=E5,1,0) | N5: =MAX(0,F5-E5)
A6: PO-00005 | B6: S08 | C6: NB-0001 | D6: 45408 | E6: 45478 | F6: 45509 | G6: 311 | H6: 311 | I6: 8 | J6: 11112.03 | K6: =(F6-D6)/7 | L6: =K6^2 | M6: =IF(F6<=E6,1,0) | N6: =MAX(0,F6-E6)
A7: PO-00006 | B7: S08 | C7: NB-0001 | D7: 45432 | E7: 45502 | F7: 45501 | G7: 303 | H7: 303 | I7: 5 | J7: 10826.19 | K7: =(F7-D7)/7 | L7: =K7^2 | M7: =IF(F7<=E7,1,0) | N7: =MAX(0,F7-E7)
A8: PO-00007 | B8: S08 | C8: NB-0001 | D8: 45462 | E8: 45532 | F8: 45532 | G8: 283 | H8: 283 | I8: 5 | J8: 10111.59 | K8: =(F8-D8)/7 | L8: =K8^2 | M8: =IF(F8<=E8,1,0) | N8: =MAX(0,F8-E8)
A9: PO-00008 | B9: S08 | C9: NB-0001 | D9: 45489 | E9: 45559 | F9: 45558 | G9: 341 | H9: 341 | I9: 7 | J9: 12183.93 | K9: =(F9-D9)/7 | L9: =K9^2 | M9: =IF(F9<=E9,1,0) | N9: =MAX(0,F9-E9)
A10: PO-00009 | B10: S08 | C10: NB-0001 | D10: 45516 | E10: 45586 | F10: 45591 | G10: 372 | H10: 372 | I10: 9 | J10: 13291.56 | K10: =(F10-D10)/7 | L10: =K10^2 | M10: =IF(F10<=E10,1,0) | N10: =MAX(0,F10-E10)
A11: PO-00010 | B11: S08 | C11: NB-0001 | D11: 45544 | E11: 45614 | F11: 45635 | G11: 305 | H11: 305 | I11: 8 | J11: 10897.65 | K11: =(F11-D11)/7 | L11: =K11^2 | M11: =IF(F11<=E11,1,0) | N11: =MAX(0,F11-E11)
A12: PO-00011 | B12: S08 | C12: NB-0001 | D12: 45574 | E12: 45644 | F12: 45669 | G12: 267 | H12: 267 | I12: 7 | J12: 9539.91 | K12: =(F12-D12)/7 | L12: =K12^2 | M12: =IF(F12<=E12,1,0) | N12: =MAX(0,F12-E12)
A13: PO-00012 | B13: S08 | C13: NB-0001 | D13: 45601 | E13: 45671 | F13: 45671 | G13: 328 | H13: 328 | I13: 9 | J13: 11719.44 | K13: =(F13-D13)/7 | L13: =K13^2 | M13: =IF(F13<=E13,1,0) | N13: =MAX(0,F13-E13)
... A1275: PO-01274 | B1275: S01 | C1275: NB-0049 | D1275: 45995 | E1275: 46009 | F1275: 46008 | G1275: 78 | H1275: 78 | I1275: 1 | J1275: 1738.62 | K1275: =(F1275-D1275)/7 | L1275: =K1275^2 | M1275: =IF(F1275<=E1275,1,0) | N1275: =MAX(0,F1275-E1275)

Sheet Inventory
A1: SKU | B1: On hand (units) | C1: On order (units)
A2: NB-0001 | B2: 1257 | C2: 314
A3: NB-0002 | B3: 375 | C3: 94
A4: NB-0003 | B4: 869 | C4: 0
A5: NB-0004 | B5: 922 | C5: 369
A6: NB-0005 | B6: 371 | C6: 0
A7: NB-0006 | B7: 317 | C7: 0
A8: NB-0007 | B8: 2054 | C8: 513
A9: NB-0008 | B9: 1787 | C9: 0
A10: NB-0009 | B10: 125 | C10: 157
A11: NB-0010 | B11: 176 | C11: 0
A12: NB-0011 | B12: 62 | C12: 0
A13: NB-0012 | B13: 23 | C13: 0
... A50: NB-0049 | B50: 159 | C50: 0
